Workbook
Name \a: #REF!
Name \a: #REF!
Name \b: #REF!
Name \b: #REF!
Name \c: #REF!
Name \c: #REF!
Name \d: #REF!
Name \d: #REF!
Name \e: #REF!
Name \e: #REF!
Name \f: #REF!
Name \f: #REF!
Name a: #REF!
Name a: #REF!
Name Banco_dados_IM: #REF!
Name Banco_dados_IM: #REF!
Name dd: #REF!
Name GWP.CH4: [1]FE_HuellaChile_2017!$B$6
Name GWP.CO2: [1]FE_HuellaChile_2017!$B$5
Name GWP.N2O: [1]FE_HuellaChile_2017!$B$7
Name Impact_flag: #N/A
Name Index: #N/A
Name IndexArray: #N/A
Name j: #REF!
Name kcal.a.kJ: [1]FE_HuellaChile_2017!$B$8
Name LatestChange: #N/A
Name LatestPerson: #N/A
Name LatestVersion: #N/A
Name Macro_status: #N/A
Name ModelName: #N/A
Name ºººº: #REF!
Name ºººº: #REF!
Name PC_G: [1]FE_HuellaChile_2017!$B$13
Name PC_SyL: [1]FE_HuellaChile_2017!$B$12
Name Q: #REF!
Name Q: #REF!
Name Quality_flag: #N/A
Name Risk_flag: #N/A
Name s: #REF!
Name s: #REF!
Name SECR_Cars_MarketSegment_Column: #N/A
Name SECR_Cars_MarketSegment_RANGE: #N/A
Name SECR_Cars_MarketSegment_Row: #N/A
Name Status_Checking: #N/A
Name Status_Overall: #N/A
Name Status_Update: #N/A
Name t_Bioenergy: #N/A
Name t_Bioenergy_LY: #N/A
Name t_Business_travel_air: #N/A
Name t_Business_travel_air_LY: #N/A
Name t_Business_travel_land: #N/A
Name t_business_travel_land_LY: #N/A
Name t_Business_travel_sea: #N/A
Name t_business_travel_sea_LY: #N/A
Name t_Conversions: #N/A
Name t_Conversions_LY: #N/A
Name t_Delivery_vehicles: #N/A
Name t_Delivery_vehicles_LY: #N/A
Name t_Freighting_goods: #N/A
Name t_Freighting_goods_LY: #N/A

Sheet INICIO
B11: Versión N° | C11: 2
B12: Fecha de última actualización | C12: 46146
B13: Desarrollado por | C13: Nataly Moyano Pozo - Profesional Programa HuellaChile
B14: Revisado y aprobado por | C14: Arturo Espinosa Cáceres - Coordinador Programa HuellaChile
B17: Leyenda | C17: Descripción
B18: INICIO | C18: Descripción del documento.
B19: RESUMEN | C19: Hoja resumen que agrupa todos los factores de emisión del documento.
B20: CONTROL DE CAMBIOS | C20: Contiene el seguimiento de los cambios realizados entre versiones del documento.
B21: 1.1 Combustión estacionaria | C21: Factores de emisión para combustión estacionaria. Utiliza de base las hojas: 1.1 V2 CH2 T2.4 y 1.1 y 1.2CUADROA1 - BNE 2024
B22: 1.1 V2 CH2 T2.4 | C22: Tabla proveniente de IPCC 2006 (vol2; chapter 2) , Table 2.4. Proporciona factores de emisión por defecto para la combustión estacionaria en la categoría Comercial/Institucional.
B23: 1.2 Combustión móvil | C23: Factores de emisión para combustión móvil. Utiliza de base las hojas: 1.2 V2 CH3 T3.2.1, 1.2 V2 CH3 T3.2.2 y 1.1 y 1.2CUADROA1 - BNE 2024
B24: 1.2 V2 CH3 T3.2.1 | C24: Tabla proveniente de IPCC 2006 (vol2; chapter 3) , Table 3.2.1. Proporciona factores de emisión de CO2 poe defecto del transporte terrestre y ragos de incertidumbre.
B25: 1.2 V2 CH3 T3.2.2 | C25: Tabla proveniente de IPCC 2006 (vol2; chapter 3) , Table 3.2.2. Proporciona factores de emisión por defecto de N2O y CH4 del transporte terrestre y rangos de incertidumbre.
B26: 1.1 y 1.2CUADROA1 - BNE 2024 | C26: Tablas provenientes del Balance Nacional de Energía 2024. Proporciona densidades y poderes caloríficos de diversos productos.
... B58: 3.6 Waste disposal | C58: Hoja proveniente de DEFRA 2025. Proporciona factores de emisión para tratamiento y/o disposición de residuos.

Sheet RESUMEN
B8: Alcance | C8: Categoría | D8: Subcategoría | E8: Nombre | F8: Auxiliar | G8: Unidad del dato de actividad | H8: Factor de emisión | I8: Unidades del factor de emisión | J8: Fuente 1 | K8: Fuente 2 | L8: Fuente 3
B9: Emisiones directas | C9: 1.1 Combustión estacionaria | D9: Caldera/Generador/General | E9: Nafta | F9: - | G9: metros cúbicos | H9: {=_xlfn.XLOOKUP(E9&G9,'1.1 Combustión estacionaria'!$B$16:$B$48&'1.1 Combustión estacionaria'!$F$16:$F$48,'1.1 Combustión estacionaria'!$AB$16:$AB$48,"-")} -> 2361.0161 | I9: {=_xlfn.XLOOKUP(E9&G9,'1.1 Combustión estacionaria'!$B$16:$B$48&'1.1 Combustión estacionaria'!$F$16:$F$48,'1.1 Combustión estacionaria'!$AC$16:$AC$48,"-")} -> kgCO2e/metros cúbicos | J9: {=_xlfn.XLOOKUP(E9&G9,'1.1 Combustión estacionaria'!$B$16:$B$48&'1.1 Combustión estacionaria'!$F$16:$F$48,'1.1 Combustión estacionaria'!$AD$16:$AD$48,"-")} -> IPCC 2006 (vol2; chapter 2) , Table 2.4 | K9: {=_xlfn.XLOOKUP(E9&G9,'1.1 Combustión estacionaria'!$B$16:$B$48&'1.1 Combustión estacionaria'!$F$16:$F$48,'1.1 Combustión estacionaria'!$AE$16:$AE$48,"-")} -> CNE BNE 2024 | L9: {=_xlfn.XLOOKUP(E9&G9,'1.1 Combustión estacionaria'!$B$16:$B$48&'1.1 Combustión estacionaria'!$F$16:$F$48,'1.1 Combustión estacionaria'!$AF$16:$AF$48,"-")} -> -
B10: Emisiones directas | C10: 1.1 Combustión estacionaria | D10: Caldera/Generador/General | E10: Nafta | F10: - | G10: litros | H10: {=_xlfn.XLOOKUP(E10&G10,'1.1 Combustión estacionaria'!$B$16:$B$48&'1.1 Combustión estacionaria'!$F$16:$F$48,'1.1 Combustión estacionaria'!$AB$16:$AB$48,"-")} -> 2.3610161 | I10: {=_xlfn.XLOOKUP(E10&G10,'1.1 Combustión estacionaria'!$B$16:$B$48&'1.1 Combustión estacionaria'!$F$16:$F$48,'1.1 Combustión estacionaria'!$AC$16:$AC$48,"-")} -> kgCO2e/litros | J10: {=_xlfn.XLOOKUP(E10&G10,'1.1 Combustión estacionaria'!$B$16:$B$48&'1.1 Combustión estacionaria'!$F$16:$F$48,'1.1 Combustión estacionaria'!$AD$16:$AD$48,"-")} -> IPCC 2006 (vol2; chapter 2) , Table 2.4 | K10: {=_xlfn.XLOOKUP(E10&G10,'1.1 Combustión estacionaria'!$B$16:$B$48&'1.1 Combustión estacionaria'!$F$16:$F$48,'1.1 Combustión estacionaria'!$AE$16:$AE$48,"-")} -> CNE BNE 2024 | L10: {=_xlfn.XLOOKUP(E10&G10,'1.1 Combustión estacionaria'!$B$16:$B$48&'1.1 Combustión estacionaria'!$F$16:$F$48,'1.1 Combustión estacionaria'!$AF$16:$AF$48,"-")} -> -
B11: Emisiones directas | C11: 1.1 Combustión estacionaria | D11: Caldera/Generador/General | E11: Carbón metalúrgico | F11: - | G11: toneladas | H11: {=_xlfn.XLOOKUP(E11&G11,'1.1 Combustión estacionaria'!$B$16:$B$48&'1.1 Combustión estacionaria'!$F$16:$F$48,'1.1 Combustión estacionaria'!$AB$16:$AB$48,"-")} -> 2652.7371 | I11: {=_xlfn.XLOOKUP(E11&G11,'1.1 Combustión estacionaria'!$B$16:$B$48&'1.1 Combustión estacionaria'!$F$16:$F$48,'1.1 Combustión estacionaria'!$AC$16:$AC$48,"-")} -> kgCO2e/toneladas | J11: {=_xlfn.XLOOKUP(E11&G11,'1.1 Combustión estacionaria'!$B$16:$B$48&'1.1 Combustión estacionaria'!$F$16:$F$48,'1.1 Combustión estacionaria'!$AD$16:$AD$48,"-")} -> IPCC 2006 (vol2; chapter 2) , Table 2.4 | K11: {=_xlfn.XLOOKUP(E11&G11,'1.1 Combustión estacionaria'!$B$16:$B$48&'1.1 Combustión estacionaria'!$F$16:$F$48,'1.1 Combustión estacionaria'!$AE$16:$AE$48,"-")} -> CNE BNE 2024 | L11: {=_xlfn.XLOOKUP(E11&G11,'1.1 Combustión estacionaria'!$B$16:$B$48&'1.1 Combustión estacionaria'!$F$16:$F$48,'1.1 Combustión estacionaria'!$AF$16:$AF$48,"-")} -> -
B12: Emisiones directas | C12: 1.1 Combustión estacionaria | D12: Caldera/Generador/General | E12: Carbón metalúrgico | F12: - | G12: kilogramos | H12: {=_xlfn.XLOOKUP(E12&G12,'1.1 Combustión estacionaria'!$B$16:$B$48&'1.1 Combustión estacionaria'!$F$16:$F$48,'1.1 Combustión estacionaria'!$AB$16:$AB$48,"-")} -> 2.6527371 | I12: {=_xlfn.XLOOKUP(E12&G12,'1.1 Combustión estacionaria'!$B$16:$B$48&'1.1 Combustión estacionaria'!$F$16:$F$48,'1.1 Combustión estacionaria'!$AC$16:$AC$48,"-")} -> kgCO2e/kilogramos | J12: {=_xlfn.XLOOKUP(E12&G12,'1.1 Combustión estacionaria'!$B$16:$B$48&'1.1 Combustión estacionaria'!$F$16:$F$48,'1.1 Combustión estacionaria'!$AD$16:$AD$48,"-")} -> IPCC 2006 (vol2; chapter 2) , Table 2.4 | K12: {=_xlfn.XLOOKUP(E12&G12,'1.1 Combustión estacionaria'!$B$16:$B$48&'1.1 Combustión estacionaria'!$F$16:$F$48,'1.1 Combustión estacionaria'!$AE$16:$AE$48,"-")} -> CNE BNE 2024 | L12: {=_xlfn.XLOOKUP(E12&G12,'1.1 Combustión estacionaria'!$B$16:$B$48&'1.1 Combustión estacionaria'!$F$16:$F$48,'1.1 Combustión estacionaria'!$AF$16:$AF$48,"-")} -> -
B13: Emisiones directas | C13: 1.1 Combustión estacionaria | D13: Caldera/Generador/General | E13: Carbón metalúrgico | F13: - | G13: gramos | H13: {=_xlfn.XLOOKUP(E13&G13,'1.1 Combustión estacionaria'!$B$16:$B$48&'1.1 Combustión estacionaria'!$F$16:$F$48,'1.1 Combustión estacionaria'!$AB$16:$AB$48,"-")} -> 0.0026527371 | I13: {=_xlfn.XLOOKUP(E13&G13,'1.1 Combustión estacionaria'!$B$16:$B$48&'1.1 Combustión estacionaria'!$F$16:$F$48,'1.1 Combustión estacionaria'!$AC$16:$AC$48,"-")} -> kgCO2e/gramos | J13: {=_xlfn.XLOOKUP(E13&G13,'1.1 Combustión estacionaria'!$B$16:$B$48&'1.1 Combustión estacionaria'!$F$16:$F$48,'1.1 Combustión estacionaria'!$AD$16:$AD$48,"-")} -> IPCC 2006 (vol2; chapter 2) , Table 2.4 | K13: {=_xlfn.XLOOKUP(E13&G13,'1.1 Combustión estacionaria'!$B$16:$B$48&'1.1 Combustión estacionaria'!$F$16:$F$48,'1.1 Combustión estacionaria'!$AE$16:$AE$48,"-")} -> CNE BNE 2024 | L13: {=_xlfn.XLOOKUP(E13&G13,'1.1 Combustión estacionaria'!$B$16:$B$48&'1.1 Combustión estacionaria'!$F$16:$F$48,'1.1 Combustión estacionaria'!$AF$16:$AF$48,"-")} -> -
B14: Emisiones directas | C14: 1.1 Combustión estacionaria | D14: Caldera/Generador/General | E14: Carbón térmico | F14: - | G14: toneladas | H14: {=_xlfn.XLOOKUP(E14&G14,'1.1 Combustión estacionaria'!$B$16:$B$48&'1.1 Combustión estacionaria'!$F$16:$F$48,'1.1 Combustión estacionaria'!$AB$16:$AB$48,"-")} -> 2652.7371 | I14: {=_xlfn.XLOOKUP(E14&G14,'1.1 Combustión estacionaria'!$B$16:$B$48&'1.1 Combustión estacionaria'!$F$16:$F$48,'1.1 Combustión estacionaria'!$AC$16:$AC$48,"-")} -> kgCO2e/toneladas | J14: {=_xlfn.XLOOKUP(E14&G14,'1.1 Combustión estacionaria'!$B$16:$B$48&'1.1 Combustión estacionaria'!$F$16:$F$48,'1.1 Combustión estacionaria'!$AD$16:$AD$48,"-")} -> IPCC 2006 (vol2; chapter 2) , Table 2.4 | K14: {=_xlfn.XLOOKUP(E14&G14,'1.1 Combustión estacionaria'!$B$16:$B$48&'1.1 Combustión estacionaria'!$F$16:$F$48,'1.1 Combustión estacionaria'!$AE$16:$AE$48,"-")} -> CNE BNE 2024 | L14: {=_xlfn.XLOOKUP(E14&G14,'1.1 Combustión estacionaria'!$B$16:$B$48&'1.1 Combustión estacionaria'!$F$16:$F$48,'1.1 Combustión estacionaria'!$AF$16:$AF$48,"-")} -> -
B15: Emisiones directas | C15: 1.1 Combustión estacionaria | D15: Caldera/Generador/General | E15: Carbón térmico | F15: - | G15: kilogramos | H15: {=_xlfn.XLOOKUP(E15&G15,'1.1 Combustión estacionaria'!$B$16:$B$48&'1.1 Combustión estacionaria'!$F$16:$F$48,'1.1 Combustión estacionaria'!$AB$16:$AB$48,"-")} -> 2.6527371 | I15: {=_xlfn.XLOOKUP(E15&G15,'1.1 Combustión estacionaria'!$B$16:$B$48&'1.1 Combustión estacionaria'!$F$16:$F$48,'1.1 Combustión estacionaria'!$AC$16:$AC$48,"-")} -> kgCO2e/kilogramos | J15: {=_xlfn.XLOOKUP(E15&G15,'1.1 Combustión estacionaria'!$B$16:$B$48&'1.1 Combustión estacionaria'!$F$16:$F$48,'1.1 Combustión estacionaria'!$AD$16:$AD$48,"-")} -> IPCC 2006 (vol2; chapter 2) , Table 2.4 | K15: {=_xlfn.XLOOKUP(E15&G15,'1.1 Combustión estacionaria'!$B$16:$B$48&'1.1 Combustión estacionaria'!$F$16:$F$48,'1.1 Combustión estacionaria'!$AE$16:$AE$48,"-")} -> CNE BNE 2024 | L15: {=_xlfn.XLOOKUP(E15&G15,'1.1 Combustión estacionaria'!$B$16:$B$48&'1.1 Combustión estacionaria'!$F$16:$F$48,'1.1 Combustión estacionaria'!$AF$16:$AF$48,"-")} -> -
B16: Emisiones directas | C16: 1.1 Combustión estacionaria | D16: Caldera/Generador/General | E16: Carbón térmico | F16: - | G16: gramos | H16: {=_xlfn.XLOOKUP(E16&G16,'1.1 Combustión estacionaria'!$B$16:$B$48&'1.1 Combustión estacionaria'!$F$16:$F$48,'1.1 Combustión estacionaria'!$AB$16:$AB$48,"-")} -> 0.0026527371 | I16: {=_xlfn.XLOOKUP(E16&G16,'1.1 Combustión estacionaria'!$B$16:$B$48&'1.1 Combustión estacionaria'!$F$16:$F$48,'1.1 Combustión estacionaria'!$AC$16:$AC$48,"-")} -> kgCO2e/gramos | J16: {=_xlfn.XLOOKUP(E16&G16,'1.1 Combustión estacionaria'!$B$16:$B$48&'1.1 Combustión estacionaria'!$F$16:$F$48,'1.1 Combustión estacionaria'!$AD$16:$AD$48,"-")} -> IPCC 2006 (vol2; chapter 2) , Table 2.4 | K16: {=_xlfn.XLOOKUP(E16&G16,'1.1 Combustión estacionaria'!$B$16:$B$48&'1.1 Combustión estacionaria'!$F$16:$F$48,'1.1 Combustión estacionaria'!$AE$16:$AE$48,"-")} -> CNE BNE 2024 | L16: {=_xlfn.XLOOKUP(E16&G16,'1.1 Combustión estacionaria'!$B$16:$B$48&'1.1 Combustión estacionaria'!$F$16:$F$48,'1.1 Combustión estacionaria'!$AF$16:$AF$48,"-")} -> -
B17: Emisiones directas | C17: 1.1 Combustión estacionaria | D17: Caldera/Generador/General | E17: Gasolina | F17: - | G17: metros cúbicos | H17: {=_xlfn.XLOOKUP(E17&G17,'1.1 Combustión estacionaria'!$B$16:$B$48&'1.1 Combustión estacionaria'!$F$16:$F$48,'1.1 Combustión estacionaria'!$AB$16:$AB$48,"-")} -> 2267.8923 | I17: {=_xlfn.XLOOKUP(E17&G17,'1.1 Combustión estacionaria'!$B$16:$B$48&'1.1 Combustión estacionaria'!$F$16:$F$48,'1.1 Combustión estacionaria'!$AC$16:$AC$48,"-")} -> kgCO2e/metros cúbicos | J17: {=_xlfn.XLOOKUP(E17&G17,'1.1 Combustión estacionaria'!$B$16:$B$48&'1.1 Combustión estacionaria'!$F$16:$F$48,'1.1 Combustión estacionaria'!$AD$16:$AD$48,"-")} -> IPCC 2006 (vol2; chapter 2) , Table 2.4 | K17: {=_xlfn.XLOOKUP(E17&G17,'1.1 Combustión estacionaria'!$B$16:$B$48&'1.1 Combustión estacionaria'!$F$16:$F$48,'1.1 Combustión estacionaria'!$AE$16:$AE$48,"-")} -> CNE BNE 2024 | L17: {=_xlfn.XLOOKUP(E17&G17,'1.1 Combustión estacionaria'!$B$16:$B$48&'1.1 Combustión estacionaria'!$F$16:$F$48,'1.1 Combustión estacionaria'!$AF$16:$AF$48,"-")} -> -
B18: Emisiones directas | C18: 1.1 Combustión estacionaria | D18: Caldera/Generador/General | E18: Gasolina | F18: - | G18: litros | H18: {=_xlfn.XLOOKUP(E18&G18,'1.1 Combustión estacionaria'!$B$16:$B$48&'1.1 Combustión estacionaria'!$F$16:$F$48,'1.1 Combustión estacionaria'!$AB$16:$AB$48,"-")} -> 2.2678923 | I18: {=_xlfn.XLOOKUP(E18&G18,'1.1 Combustión estacionaria'!$B$16:$B$48&'1.1 Combustión estacionaria'!$F$16:$F$48,'1.1 Combustión estacionaria'!$AC$16:$AC$48,"-")} -> kgCO2e/litros | J18: {=_xlfn.XLOOKUP(E18&G18,'1.1 Combustión estacionaria'!$B$16:$B$48&'1.1 Combustión estacionaria'!$F$16:$F$48,'1.1 Combustión estacionaria'!$AD$16:$AD$48,"-")} -> IPCC 2006 (vol2; chapter 2) , Table 2.4 | K18: {=_xlfn.XLOOKUP(E18&G18,'1.1 Combustión estacionaria'!$B$16:$B$48&'1.1 Combustión estacionaria'!$F$16:$F$48,'1.1 Combustión estacionaria'!$AE$16:$AE$48,"-")} -> CNE BNE 2024 | L18: {=_xlfn.XLOOKUP(E18&G18,'1.1 Combustión estacionaria'!$B$16:$B$48&'1.1 Combustión estacionaria'!$F$16:$F$48,'1.1 Combustión estacionaria'!$AF$16:$AF$48,"-")} -> -
B19: Emisiones directas | C19: 1.1 Combustión estacionaria | D19: Caldera/Generador/General | E19: Gas de alto horno | F19: - | G19: toneladas | H19: {=_xlfn.XLOOKUP(E19&G19,'1.1 Combustión estacionaria'!$B$16:$B$48&'1.1 Combustión estacionaria'!$F$16:$F$48,'1.1 Combustión estacionaria'!$AB$16:$AB$48,"-")} -> 578.35013 | I19: {=_xlfn.XLOOKUP(E19&G19,'1.1 Combustión estacionaria'!$B$16:$B$48&'1.1 Combustión estacionaria'!$F$16:$F$48,'1.1 Combustión estacionaria'!$AC$16:$AC$48,"-")} -> kgCO2e/toneladas | J19: {=_xlfn.XLOOKUP(E19&G19,'1.1 Combustión estacionaria'!$B$16:$B$48&'1.1 Combustión estacionaria'!$F$16:$F$48,'1.1 Combustión estacionaria'!$AD$16:$AD$48,"-")} -> IPCC 2006 (vol2; chapter 2) , Table 2.4 | K19: {=_xlfn.XLOOKUP(E19&G19,'1.1 Combustión estacionaria'!$B$16:$B$48&'1.1 Combustión estacionaria'!$F$16:$F$48,'1.1 Combustión estacionaria'!$AE$16:$AE$48,"-")} -> CNE BNE 2024 | L19: {=_xlfn.XLOOKUP(E19&G19,'1.1 Combustión estacionaria'!$B$16:$B$48&'1.1 Combustión estacionaria'!$F$16:$F$48,'1.1 Combustión estacionaria'!$AF$16:$AF$48,"-")} -> IPCC 2006 (vol2; chapter 1) , Table 1.2
B20: Emisiones directas | C20: 1.1 Combustión estacionaria | D20: Caldera/Generador/General | E20: Gas de alto horno | F20: - | G20: kilogramos | H20: {=_xlfn.XLOOKUP(E20&G20,'1.1 Combustión estacionaria'!$B$16:$B$48&'1.1 Combustión estacionaria'!$F$16:$F$48,'1.1 Combustión estacionaria'!$AB$16:$AB$48,"-")} -> 0.57835013 | I20: {=_xlfn.XLOOKUP(E20&G20,'1.1 Combustión estacionaria'!$B$16:$B$48&'1.1 Combustión estacionaria'!$F$16:$F$48,'1.1 Combustión estacionaria'!$AC$16:$AC$48,"-")} -> kgCO2e/kilogramos | J20: {=_xlfn.XLOOKUP(E20&G20,'1.1 Combustión estacionaria'!$B$16:$B$48&'1.1 Combustión estacionaria'!$F$16:$F$48,'1.1 Combustión estacionaria'!$AD$16:$AD$48,"-")} -> IPCC 2006 (vol2; chapter 2) , Table 2.4 | K20: {=_xlfn.XLOOKUP(E20&G20,'1.1 Combustión estacionaria'!$B$16:$B$48&'1.1 Combustión estacionaria'!$F$16:$F$48,'1.1 Combustión estacionaria'!$AE$16:$AE$48,"-")} -> CNE BNE 2024 | L20: {=_xlfn.XLOOKUP(E20&G20,'1.1 Combustión estacionaria'!$B$16:$B$48&'1.1 Combustión estacionaria'!$F$16:$F$48,'1.1 Combustión estacionaria'!$AF$16:$AF$48,"-")} -> IPCC 2006 (vol2; chapter 1) , Table 1.2
... B41: Emisiones directas | C41: 1.1 Combustión estacionaria | D41: Caldera/Generador/General | E41: Petróleo 6 | F41: - | G41: litros | H41: {=_xlfn.XLOOKUP(E41&G41,'1.1 Combustión estacionaria'!$B$16:$B$48&'1.1 Combustión estacionaria'!$F$16:$F$48,'1.1 Combustión estacionaria'!$AB$16:$AB$48,"-")} -> 3.072021 | I41: {=_xlfn.XLOOKUP(E41&G41,'1.1 Combustión estacionaria'!$B$16:$B$48&'1.1 Combustión estacionaria'!$F$16:$F$48,'1.1 Combustión estacionaria'!$AC$16:$AC$48,"-")} -> kgCO2e/litros | J41: {=_xlfn.XLOOKUP(E41&G41,'1.1 Combustión estacionaria'!$B$16:$B$48&'1.1 Combustión estacionaria'!$F$16:$F$48,'1.1 Combustión estacionaria'!$AD$16:$AD$48,"-")} -> IPCC 2006 (vol2; chapter 2) , Table 2.4 | K41: {=_xlfn.XLOOKUP(E41&G41,'1.1 Combustión estacionaria'!$B$16:$B$48&'1.1 Combustión estacionaria'!$F$16:$F$48,'1.1 Combustión estacionaria'!$AE$16:$AE$48,"-")} -> CNE BNE 2024 | L41: {=_xlfn.XLOOKUP(E41&G41,'1.1 Combustión estacionaria'!$B$16:$B$48&'1.1 Combustión estacionaria'!$F$16:$F$48,'1.1 Combustión estacionaria'!$AF$16:$AF$48,"-")} -> -
B42: Emisiones directas | C42: 1.2 Combustión móvil | D42: Vehíulos de pasajeros o carga | E42: Petróleo 2 (Diesel) | F42: - | G42: metros cúbicos | H42: {=_xlfn.XLOOKUP(E42&G42,'1.2 Combustión móvil'!$B$16:$B$24&'1.2 Combustión móvil'!$F$16:$F$24,'1.2 Combustión móvil'!$AB$16:$AB$24,"-")} -> 2740.1603 | I42: {=_xlfn.XLOOKUP(E42&G42,'1.2 Combustión móvil'!$B$16:$B$24&'1.2 Combustión móvil'!$F$16:$F$24,'1.2 Combustión móvil'!$AC$16:$AC$24,"-")} -> kgCO2e/metros cúbicos | J42: {=_xlfn.XLOOKUP(E42&G42,'1.2 Combustión móvil'!$B$16:$B$24&'1.2 Combustión móvil'!$F$16:$F$24,'1.2 Combustión móvil'!$AD$16:$AD$24,"-")} -> IPCC 2006 (vol2; chapter 3) , Table 3.2.1 and Table 3.2.2 | K42: {=_xlfn.XLOOKUP(E42&G42,'1.2 Combustión móvil'!$B$16:$B$24&'1.2 Combustión móvil'!$F$16:$F$24,'1.2 Combustión móvil'!$AE$16:$AE$24,"-")} -> CNE BNE 2024 | L42: {=_xlfn.XLOOKUP(E42&G42,'1.2 Combustión móvil'!$B$16:$B$24&'1.2 Combustión móvil'!$F$16:$F$24,'1.2 Combustión móvil'!$AF$16:$AF$24,"-")} -> -
B43: Emisiones directas | C43: 1.2 Combustión móvil | D43: Vehíulos de pasajeros o carga | E43: Petróleo 2 (Diesel) | F43: - | G43: litros | H43: {=_xlfn.XLOOKUP(E43&G43,'1.2 Combustión móvil'!$B$16:$B$24&'1.2 Combustión móvil'!$F$16:$F$24,'1.2 Combustión móvil'!$AB$16:$AB$24,"-")} -> 2.7401603 | I43: {=_xlfn.XLOOKUP(E43&G43,'1.2 Combustión móvil'!$B$16:$B$24&'1.2 Combustión móvil'!$F$16:$F$24,'1.2 Combustión móvil'!$AC$16:$AC$24,"-")} -> kgCO2e/litros | J43: {=_xlfn.XLOOKUP(E43&G43,'1.2 Combustión móvil'!$B$16:$B$24&'1.2 Combustión móvil'!$F$16:$F$24,'1.2 Combustión móvil'!$AD$16:$AD$24,"-")} -> IPCC 2006 (vol2; chapter 3) , Table 3.2.1 and Table 3.2.2 | K43: {=_xlfn.XLOOKUP(E43&G43,'1.2 Combustión móvil'!$B$16:$B$24&'1.2 Combustión móvil'!$F$16:$F$24,'1.2 Combustión móvil'!$AE$16:$AE$24,"-")} -> CNE BNE 2024 | L43: {=_xlfn.XLOOKUP(E43&G43,'1.2 Combustión móvil'!$B$16:$B$24&'1.2 Combustión móvil'!$F$16:$F$24,'1.2 Combustión móvil'!$AF$16:$AF$24,"-")} -> -
B44: Emisiones directas | C44: 1.2 Combustión móvil | D44: Vehíulos de pasajeros o carga | E44: Gas licuado | F44: - | G44: metros cúbicos | H44: {=_xlfn.XLOOKUP(E44&G44,'1.2 Combustión móvil'!$B$16:$B$24&'1.2 Combustión móvil'!$F$16:$F$24,'1.2 Combustión móvil'!$AB$16:$AB$24,"-")} -> 1717.6116 | I44: {=_xlfn.XLOOKUP(E44&G44,'1.2 Combustión móvil'!$B$16:$B$24&'1.2 Combustión móvil'!$F$16:$F$24,'1.2 Combustión móvil'!$AC$16:$AC$24,"-")} -> kgCO2e/metros cúbicos | J44: {=_xlfn.XLOOKUP(E44&G44,'1.2 Combustión móvil'!$B$16:$B$24&'1.2 Combustión móvil'!$F$16:$F$24,'1.2 Combustión móvil'!$AD$16:$AD$24,"-")} -> IPCC 2006 (vol2; chapter 3) , Table 3.2.1 and Table 3.2.2 | K44: {=_xlfn.XLOOKUP(E44&G44,'1.2 Combustión móvil'!$B$16:$B$24&'1.2 Combustión móvil'!$F$16:$F$24,'1.2 Combustión móvil'!$AE$16:$AE$24,"-")} -> CNE BNE 2024 | L44: {=_xlfn.XLOOKUP(E44&G44,'1.2 Combustión móvil'!$B$16:$B$24&'1.2 Combustión móvil'!$F$16:$F$24,'1.2 Combustión móvil'!$AF$16:$AF$24,"-")} -> -
B45: Emisiones directas | C45: 1.2 Combustión móvil | D45: Vehíulos de pasajeros o carga | E45: Gas licuado | F45: - | G45: litros | H45: {=_xlfn.XLOOKUP(E45&G45,'1.2 Combustión móvil'!$B$16:$B$24&'1.2 Combustión móvil'!$F$16:$F$24,'1.2 Combustión móvil'!$AB$16:$AB$24,"-")} -> 1.7176116 | I45: {=_xlfn.XLOOKUP(E45&G45,'1.2 Combustión móvil'!$B$16:$B$24&'1.2 Combustión móvil'!$F$16:$F$24,'1.2 Combustión móvil'!$AC$16:$AC$24,"-")} -> kgCO2e/litros | J45: {=_xlfn.XLOOKUP(E45&G45,'1.2 Combustión móvil'!$B$16:$B$24&'1.2 Combustión móvil'!$F$16:$F$24,'1.2 Combustión móvil'!$AD$16:$AD$24,"-")} -> IPCC 2006 (vol2; chapter 3) , Table 3.2.1 and Table 3.2.2 | K45: {=_xlfn.XLOOKUP(E45&G45,'1.2 Combustión móvil'!$B$16:$B$24&'1.2 Combustión móvil'!$F$16:$F$24,'1.2 Combustión móvil'!$AE$16:$AE$24,"-")} -> CNE BNE 2024 | L45: {=_xlfn.XLOOKUP(E45&G45,'1.2 Combustión móvil'!$B$16:$B$24&'1.2 Combustión móvil'!$F$16:$F$24,'1.2 Combustión móvil'!$AF$16:$AF$24,"-")} -> -
B46: Emisiones directas | C46: 1.2 Combustión móvil | D46: Vehíulos de pasajeros o carga | E46: Gas natural | F46: - | G46: metros cúbicos | H46: {=_xlfn.XLOOKUP(E46&G46,'1.2 Combustión móvil'!$B$16:$B$24&'1.2 Combustión móvil'!$F$16:$F$24,'1.2 Combustión móvil'!$AB$16:$AB$24,"-")} -> 2.0932608 | I46: {=_xlfn.XLOOKUP(E46&G46,'1.2 Combustión móvil'!$B$16:$B$24&'1.2 Combustión móvil'!$F$16:$F$24,'1.2 Combustión móvil'!$AC$16:$AC$24,"-")} -> kgCO2e/metros cúbicos | J46: {=_xlfn.XLOOKUP(E46&G46,'1.2 Combustión móvil'!$B$16:$B$24&'1.2 Combustión móvil'!$F$16:$F$24,'1.2 Combustión móvil'!$AD$16:$AD$24,"-")} -> IPCC 2006 (vol2; chapter 3) , Table 3.2.1 and Table 3.2.2 | K46: {=_xlfn.XLOOKUP(E46&G46,'1.2 Combustión móvil'!$B$16:$B$24&'1.2 Combustión móvil'!$F$16:$F$24,'1.2 Combustión móvil'!$AE$16:$AE$24,"-")} -> CNE BNE 2024 | L46: {=_xlfn.XLOOKUP(E46&G46,'1.2 Combustión móvil'!$B$16:$B$24&'1.2 Combustión móvil'!$F$16:$F$24,'1.2 Combustión móvil'!$AF$16:$AF$24,"-")} -> -
B47: Emisiones directas | C47: 1.2 Combustión móvil | D47: Vehíulos de pasajeros o carga | E47: Gasolina | F47: - | G47: metros cúbicos | H47: {=_xlfn.XLOOKUP(E47&G47,'1.2 Combustión móvil'!$B$16:$B$24&'1.2 Combustión móvil'!$F$16:$F$24,'1.2 Combustión móvil'!$AB$16:$AB$24,"-")} -> 2345.3217 | I47: {=_xlfn.XLOOKUP(E47&G47,'1.2 Combustión móvil'!$B$16:$B$24&'1.2 Combustión móvil'!$F$16:$F$24,'1.2 Combustión móvil'!$AC$16:$AC$24,"-")} -> kgCO2e/metros cúbicos | J47: {=_xlfn.XLOOKUP(E47&G47,'1.2 Combustión móvil'!$B$16:$B$24&'1.2 Combustión móvil'!$F$16:$F$24,'1.2 Combustión móvil'!$AD$16:$AD$24,"-")} -> IPCC 2006 (vol2; chapter 3) , Table 3.2.1 and Table 3.2.2 | K47: {=_xlfn.XLOOKUP(E47&G47,'1.2 Combustión móvil'!$B$16:$B$24&'1.2 Combustión móvil'!$F$16:$F$24,'1.2 Combustión móvil'!$AE$16:$AE$24,"-")} -> CNE BNE 2024 | L47: {=_xlfn.XLOOKUP(E47&G47,'1.2 Combustión móvil'!$B$16:$B$24&'1.2 Combustión móvil'!$F$16:$F$24,'1.2 Combustión móvil'!$AF$16:$AF$24,"-")} -> -
B48: Emisiones directas | C48: 1.2 Combustión móvil | D48: Vehíulos de pasajeros o carga | E48: Gasolina | F48: - | G48: litros | H48: {=_xlfn.XLOOKUP(E48&G48,'1.2 Combustión móvil'!$B$16:$B$24&'1.2 Combustión móvil'!$F$16:$F$24,'1.2 Combustión móvil'!$AB$16:$AB$24,"-")} -> 2.3453217 | I48: {=_xlfn.XLOOKUP(E48&G48,'1.2 Combustión móvil'!$B$16:$B$24&'1.2 Combustión móvil'!$F$16:$F$24,'1.2 Combustión móvil'!$AC$16:$AC$24,"-")} -> kgCO2e/litros | J48: {=_xlfn.XLOOKUP(E48&G48,'1.2 Combustión móvil'!$B$16:$B$24&'1.2 Combustión móvil'!$F$16:$F$24,'1.2 Combustión móvil'!$AD$16:$AD$24,"-")} -> IPCC 2006 (vol2; chapter 3) , Table 3.2.1 and Table 3.2.2 | K48: {=_xlfn.XLOOKUP(E48&G48,'1.2 Combustión móvil'!$B$16:$B$24&'1.2 Combustión móvil'!$F$16:$F$24,'1.2 Combustión móvil'!$AE$16:$AE$24,"-")} -> CNE BNE 2024 | L48: {=_xlfn.XLOOKUP(E48&G48,'1.2 Combustión móvil'!$B$16:$B$24&'1.2 Combustión móvil'!$F$16:$F$24,'1.2 Combustión móvil'!$AF$16:$AF$24,"-")} -> -
B49: Emisiones directas | C49: 1.2 Combustión móvil | D49: Vehíulos de pasajeros o carga | E49: Kerosene | F49: - | G49: metros cúbicos | H49: {=_xlfn.XLOOKUP(E49&G49,'1.2 Combustión móvil'!$B$16:$B$24&'1.2 Combustión móvil'!$F$16:$F$24,'1.2 Combustión móvil'!$AB$16:$AB$24,"-")} -> 2579.9306 | I49: {=_xlfn.XLOOKUP(E49&G49,'1.2 Combustión móvil'!$B$16:$B$24&'1.2 Combustión móvil'!$F$16:$F$24,'1.2 Combustión móvil'!$AC$16:$AC$24,"-")} -> kgCO2e/metros cúbicos | J49: {=_xlfn.XLOOKUP(E49&G49,'1.2 Combustión móvil'!$B$16:$B$24&'1.2 Combustión móvil'!$F$16:$F$24,'1.2 Combustión móvil'!$AD$16:$AD$24,"-")} -> IPCC 2006 (vol2; chapter 3) , Table 3.2.1 and Table 3.2.2 | K49: {=_xlfn.XLOOKUP(E49&G49,'1.2 Combustión móvil'!$B$16:$B$24&'1.2 Combustión móvil'!$F$16:$F$24,'1.2 Combustión móvil'!$AE$16:$AE$24,"-")} -> CNE BNE 2024 | L49: {=_xlfn.XLOOKUP(E49&G49,'1.2 Combustión móvil'!$B$16:$B$24&'1.2 Combustión móvil'!$F$16:$F$24,'1.2 Combustión móvil'!$AF$16:$AF$24,"-")} -> IPCC 2006 (vol2; chapter 2), Table 2.3
B50: Emisiones directas | C50: 1.2 Combustión móvil | D50: Vehíulos de pasajeros o carga | E50: Kerosene | F50: - | G50: litros | H50: {=_xlfn.XLOOKUP(E50&G50,'1.2 Combustión móvil'!$B$16:$B$24&'1.2 Combustión móvil'!$F$16:$F$24,'1.2 Combustión móvil'!$AB$16:$AB$24,"-")} -> 2.5799306 | I50: {=_xlfn.XLOOKUP(E50&G50,'1.2 Combustión móvil'!$B$16:$B$24&'1.2 Combustión móvil'!$F$16:$F$24,'1.2 Combustión móvil'!$AC$16:$AC$24,"-")} -> kgCO2e/litros | J50: {=_xlfn.XLOOKUP(E50&G50,'1.2 Combustión móvil'!$B$16:$B$24&'1.2 Combustión móvil'!$F$16:$F$24,'1.2 Combustión móvil'!$AD$16:$AD$24,"-")} -> IPCC 2006 (vol2; chapter 3) , Table 3.2.1 and Table 3.2.2 | K50: {=_xlfn.XLOOKUP(E50&G50,'1.2 Combustión móvil'!$B$16:$B$24&'1.2 Combustión móvil'!$F$16:$F$24,'1.2 Combustión móvil'!$AE$16:$AE$24,"-")} -> CNE BNE 2024 | L50: {=_xlfn.XLOOKUP(E50&G50,'1.2 Combustión móvil'!$B$16:$B$24&'1.2 Combustión móvil'!$F$16:$F$24,'1.2 Combustión móvil'!$AF$16:$AF$24,"-")} -> IPCC 2006 (vol2; chapter 2), Table 2.3
B51: Emisiones directas | C51: 1.3 Procesos industriales | D51: Producción minerales | E51: Producción de cemento | F51: - | G51: toneladas | H51: {=_xlfn.XLOOKUP(E51&G51,'1.3 Procesos industriales'!$B$12:$B$67&'1.3 Procesos industriales'!$C$12:$C$67,'1.3 Procesos industriales'!$T$12:$T$67,"-")} -> 316.8324 | I51: {=_xlfn.XLOOKUP(E51&G51,'1.3 Procesos industriales'!$B$12:$B$67&'1.3 Procesos industriales'!$C$12:$C$67,'1.3 Procesos industriales'!$U$12:$U$67,"-")} -> kgCO2e/toneladas | J51: {=_xlfn.XLOOKUP(E51&G51,'1.3 Procesos industriales'!$B$12:$B$67&'1.3 Procesos industriales'!$C$12:$C$67,'1.3 Procesos industriales'!$V$12:$V$67,"-")} -> INGEI + IPCC 2006. Ver su hoja correspondiente para más detalles. | K51: - | L51: -
B52: Emisiones directas | C52: 1.3 Procesos industriales | D52: Producción minerales | E52: Producción de cemento | F52: - | G52: kilogramos | H52: {=_xlfn.XLOOKUP(E52&G52,'1.3 Procesos industriales'!$B$12:$B$67&'1.3 Procesos industriales'!$C$12:$C$67,'1.3 Procesos industriales'!$T$12:$T$67,"-")} -> 0.3168324 | I52: {=_xlfn.XLOOKUP(E52&G52,'1.3 Procesos industriales'!$B$12:$B$67&'1.3 Procesos industriales'!$C$12:$C$67,'1.3 Procesos industriales'!$U$12:$U$67,"-")} -> kgCO2e/kilogramos | J52: {=_xlfn.XLOOKUP(E52&G52,'1.3 Procesos industriales'!$B$12:$B$67&'1.3 Procesos industriales'!$C$12:$C$67,'1.3 Procesos industriales'!$V$12:$V$67,"-")} -> INGEI + IPCC 2006. Ver su hoja correspondiente para más detalles. | K52: - | L52: -
B53: Emisiones directas | C53: 1.3 Procesos industriales | D53: Producción minerales | E53: Producción de cemento | F53: - | G53: gramos | H53: {=_xlfn.XLOOKUP(E53&G53,'1.3 Procesos industriales'!$B$12:$B$67&'1.3 Procesos industriales'!$C$12:$C$67,'1.3 Procesos industriales'!$T$12:$T$67,"-")} -> 0.0003168324 | I53: {=_xlfn.XLOOKUP(E53&G53,'1.3 Procesos industriales'!$B$12:$B$67&'1.3 Procesos industriales'!$C$12:$C$67,'1.3 Procesos industriales'!$U$12:$U$67,"-")} -> kgCO2e/gramos | J53: {=_xlfn.XLOOKUP(E53&G53,'1.3 Procesos industriales'!$B$12:$B$67&'1.3 Procesos industriales'!$C$12:$C$67,'1.3 Procesos industriales'!$V$12:$V$67,"-")} -> INGEI + IPCC 2006. Ver su hoja correspondiente para más detalles. | K53: - | L53: -
B54: Emisiones directas | C54: 1.3 Procesos industriales | D54: Producción minerales | E54: Producción de cal | F54: - | G54: toneladas | H54: {=_xlfn.XLOOKUP(E54&G54,'1.3 Procesos industriales'!$B$12:$B$67&'1.3 Procesos industriales'!$C$12:$C$67,'1.3 Procesos industriales'!$T$12:$T$67,"-")} -> 695.1277 | I54: {=_xlfn.XLOOKUP(E54&G54,'1.3 Procesos industriales'!$B$12:$B$67&'1.3 Procesos industriales'!$C$12:$C$67,'1.3 Procesos industriales'!$U$12:$U$67,"-")} -> kgCO2e/toneladas | J54: {=_xlfn.XLOOKUP(E54&G54,'1.3 Procesos industriales'!$B$12:$B$67&'1.3 Procesos industriales'!$C$12:$C$67,'1.3 Procesos industriales'!$V$12:$V$67,"-")} -> INGEI + IPCC 2006. Ver su hoja correspondiente para más detalles. | K54: - | L54: -
B55: Emisiones directas | C55: 1.3 Procesos industriales | D55: Producción minerales | E55: Producción de cal | F55: - | G55: kilogramos | H55: {=_xlfn.XLOOKUP(E55&G55,'1.3 Procesos industriales'!$B$12:$B$67&'1.3 Procesos industriales'!$C$12:$C$67,'1.3 Procesos industriales'!$T$12:$T$67,"-")} -> 0.6951277 | I55: {=_xlfn.XLOOKUP(E55&G55,'1.3 Procesos industriales'!$B$12:$B$67&'1.3 Procesos industriales'!$C$12:$C$67,'1.3 Procesos industriales'!$U$12:$U$67,"-")} -> kgCO2e/kilogramos | J55: {=_xlfn.XLOOKUP(E55&G55,'1.3 Procesos industriales'!$B$12:$B$67&'1.3 Procesos industriales'!$C$12:$C$67,'1.3 Procesos industriales'!$V$12:$V$67,"-")} -> INGEI + IPCC 2006. Ver su hoja correspondiente para más detalles. | K55: - | L55: -
B56: Emisiones directas | C56: 1.3 Procesos industriales | D56: Producción minerales | E56: Producción de cal | F56: - | G56: gramos | H56: {=_xlfn.XLOOKUP(E56&G56,'1.3 Procesos industriales'!$B$12:$B$67&'1.3 Procesos industriales'!$C$12:$C$67,'1.3 Procesos industriales'!$T$12:$T$67,"-")} -> 0.00069512771 | I56: {=_xlfn.XLOOKUP(E56&G56,'1.3 Procesos industriales'!$B$12:$B$67&'1.3 Procesos industriales'!$C$12:$C$67,'1.3 Procesos industriales'!$U$12:$U$67,"-")} -> kgCO2e/gramos | J56: {=_xlfn.XLOOKUP(E56&G56,'1.3 Procesos industriales'!$B$12:$B$67&'1.3 Procesos industriales'!$C$12:$C$67,'1.3 Procesos industriales'!$V$12:$V$67,"-")} -> INGEI + IPCC 2006. Ver su hoja correspondiente para más detalles. | K56: - | L56: -
B57: Emisiones directas | C57: 1.3 Procesos industriales | D57: Producción minerales | E57: Producción de vidrio | F57: - | G57: toneladas | H57: {=_xlfn.XLOOKUP(E57&G57,'1.3 Procesos industriales'!$B$12:$B$67&'1.3 Procesos industriales'!$C$12:$C$67,'1.3 Procesos industriales'!$T$12:$T$67,"-")} -> 145.16437 | I57: {=_xlfn.XLOOKUP(E57&G57,'1.3 Procesos industriales'!$B$12:$B$67&'1.3 Procesos industriales'!$C$12:$C$67,'1.3 Procesos industriales'!$U$12:$U$67,"-")} -> kgCO2e/toneladas | J57: {=_xlfn.XLOOKUP(E57&G57,'1.3 Procesos industriales'!$B$12:$B$67&'1.3 Procesos industriales'!$C$12:$C$67,'1.3 Procesos industriales'!$V$12:$V$67,"-")} -> INGEI + IPCC 2006. Ver su hoja correspondiente para más detalles. | K57: - | L57: -
B58: Emisiones directas | C58: 1.3 Procesos industriales | D58: Producción minerales | E58: Producción de vidrio | F58: - | G58: kilogramos | H58: {=_xlfn.XLOOKUP(E58&G58,'1.3 Procesos industriales'!$B$12:$B$67&'1.3 Procesos industriales'!$C$12:$C$67,'1.3 Procesos industriales'!$T$12:$T$67,"-")} -> 0.14516437 | I58: {=_xlfn.XLOOKUP(E58&G58,'1.3 Procesos industriales'!$B$12:$B$67&'1.3 Procesos industriales'!$C$12:$C$67,'1.3 Procesos industriales'!$U$12:$U$67,"-")} -> kgCO2e/kilogramos | J58: {=_xlfn.XLOOKUP(E58&G58,'1.3 Procesos industriales'!$B$12:$B$67&'1.3 Procesos industriales'!$C$12:$C$67,'1.3 Procesos industriales'!$V$12:$V$67,"-")} -> INGEI + IPCC 2006. Ver su hoja correspondiente para más detalles. | K58: - | L58: -
B59: Emisiones directas | C59: 1.3 Procesos industriales | D59: Producción minerales | E59: Producción de vidrio | F59: - | G59: gramos | H59: {=_xlfn.XLOOKUP(E59&G59,'1.3 Procesos industriales'!$B$12:$B$67&'1.3 Procesos industriales'!$C$12:$C$67,'1.3 Procesos industriales'!$T$12:$T$67,"-")} -> 0.00014516437 | I59: {=_xlfn.XLOOKUP(E59&G59,'1.3 Procesos industriales'!$B$12:$B$67&'1.3 Procesos industriales'!$C$12:$C$67,'1.3 Procesos industriales'!$U$12:$U$67,"-")} -> kgCO2e/gramos | J59: {=_xlfn.XLOOKUP(E59&G59,'1.3 Procesos industriales'!$B$12:$B$67&'1.3 Procesos industriales'!$C$12:$C$67,'1.3 Procesos industriales'!$V$12:$V$67,"-")} -> INGEI + IPCC 2006. Ver su hoja correspondiente para más detalles. | K59: - | L59: -
B60: Emisiones directas | C60: 1.3 Procesos industriales | D60: Producción minerales | E60: Producción de coke | F60: - | G60: toneladas | H60: {=_xlfn.XLOOKUP(E60&G60,'1.3 Procesos industriales'!$B$12:$B$67&'1.3 Procesos industriales'!$C$12:$C$67,'1.3 Procesos industriales'!$T$12:$T$67,"-")} -> 560.0028 | I60: {=_xlfn.XLOOKUP(E60&G60,'1.3 Procesos industriales'!$B$12:$B$67&'1.3 Procesos industriales'!$C$12:$C$67,'1.3 Procesos industriales'!$U$12:$U$67,"-")} -> kgCO2e/toneladas | J60: {=_xlfn.XLOOKUP(E60&G60,'1.3 Procesos industriales'!$B$12:$B$67&'1.3 Procesos industriales'!$C$12:$C$67,'1.3 Procesos industriales'!$V$12:$V$67,"-")} -> INGEI + IPCC 2006. Ver su hoja correspondiente para más detalles. | K60: - | L60: -
B61: Emisiones directas | C61: 1.3 Procesos industriales | D61: Producción minerales | E61: Producción de coke | F61: - | G61: kilogramos | H61: {=_xlfn.XLOOKUP(E61&G61,'1.3 Procesos industriales'!$B$12:$B$67&'1.3 Procesos industriales'!$C$12:$C$67,'1.3 Procesos industriales'!$T$12:$T$67,"-")} -> 0.5600028 | I61: {=_xlfn.XLOOKUP(E61&G61,'1.3 Procesos industriales'!$B$12:$B$67&'1.3 Procesos industriales'!$C$12:$C$67,'1.3 Procesos industriales'!$U$12:$U$67,"-")} -> kgCO2e/kilogramos | J61: {=_xlfn.XLOOKUP(E61&G61,'1.3 Procesos industriales'!$B$12:$B$67&'1.3 Procesos industriales'!$C$12:$C$67,'1.3 Procesos industriales'!$V$12:$V$67,"-")} -> INGEI + IPCC 2006. Ver su hoja correspondiente para más detalles. | K61: - | L61: -
B62: Emisiones directas | C62: 1.3 Procesos industriales | D62: Producción minerales | E62: Producción de coke | F62: - | G62: gramos | H62: {=_xlfn.XLOOKUP(E62&G62,'1.3 Procesos industriales'!$B$12:$B$67&'1.3 Procesos industriales'!$C$12:$C$67,'1.3 Procesos industriales'!$T$12:$T$67,"-")} -> 0.0005600028 | I62: {=_xlfn.XLOOKUP(E62&G62,'1.3 Procesos industriales'!$B$12:$B$67&'1.3 Procesos industriales'!$C$12:$C$67,'1.3 Procesos industriales'!$U$12:$U$67,"-")} -> kgCO2e/gramos | J62: {=_xlfn.XLOOKUP(E62&G62,'1.3 Procesos industriales'!$B$12:$B$67&'1.3 Procesos industriales'!$C$12:$C$67,'1.3 Procesos industriales'!$V$12:$V$67,"-")} -> INGEI + IPCC 2006. Ver su hoja correspondiente para más detalles. | K62: - | L62: -
... B92: Emisiones directas | C92: 1.3 Procesos industriales | D92: Industria química | E92: Producción de ácido nítrico (Plantas a alta presión) | F92: - | G92: gramos | H92: {=_xlfn.XLOOKUP(E92&G92,'1.3 Procesos industriales'!$B$12:$B$67&'1.3 Procesos industriales'!$C$12:$C$67,'1.3 Procesos industriales'!$T$12:$T$67,"-")} -> 0.0026235 | I92: {=_xlfn.XLOOKUP(E92&G92,'1.3 Procesos industriales'!$B$12:$B$67&'1.3 Procesos industriales'!$C$12:$C$67,'1.3 Procesos industriales'!$U$12:$U$67,"-")} -> kgCO2e/gramos | J92: {=_xlfn.XLOOKUP(E92&G92,'1.3 Procesos industriales'!$B$12:$B$67&'1.3 Procesos industriales'!$C$12:$C$67,'1.3 Procesos industriales'!$V$12:$V$67,"-")} -> INGEI + IPCC 2006. Ver su hoja correspondiente para más detalles. | K92: - | L92: -
B93: Emisiones directas | C93: 1.4 Emisiones fugitivas | D93: Emisiones fugitivas | E93: HFC-245fa | F93: - | G93: kilogramos | H93: {=_xlfn.XLOOKUP(E93&G93,'1.4 Emisiones fugitivas'!$C$7:$C$61&'1.4 Emisiones fugitivas'!$F$7:$F$61,'1.4 Emisiones fugitivas'!$G$7:$G$61,"-")} -> 858 | I93: {=_xlfn.XLOOKUP(E93&G93,'1.4 Emisiones fugitivas'!$C$7:$C$61&'1.4 Emisiones fugitivas'!$F$7:$F$61,'1.4 Emisiones fugitivas'!$H$7:$H$61,"-")} -> kgCO2e/kilogramos | J93: {=_xlfn.XLOOKUP(E93&G93,'1.4 Emisiones fugitivas'!$C$7:$C$61&'1.4 Emisiones fugitivas'!$F$7:$F$61,'1.4 Emisiones fugitivas'!$I$7:$I$61,"-")} -> IPCC 2006 (vol3; chapter 7) , Table 7.8 | IPCC 2012 (AR5; chapter 8), Table 8.A.1 | K93: - | L93: -
B94: Emisiones directas | C94: 1.4 Emisiones fugitivas | D94: Emisiones fugitivas | E94: HFC-32 | F94: - | G94: kilogramos | H94: {=_xlfn.XLOOKUP(E94&G94,'1.4 Emisiones fugitivas'!$C$7:$C$61&'1.4 Emisiones fugitivas'!$F$7:$F$61,'1.4 Emisiones fugitivas'!$G$7:$G$61,"-")} -> 677 | I94: {=_xlfn.XLOOKUP(E94&G94,'1.4 Emisiones fugitivas'!$C$7:$C$61&'1.4 Emisiones fugitivas'!$F$7:$F$61,'1.4 Emisiones fugitivas'!$H$7:$H$61,"-")} -> kgCO2e/kilogramos | J94: {=_xlfn.XLOOKUP(E94&G94,'1.4 Emisiones fugitivas'!$C$7:$C$61&'1.4 Emisiones fugitivas'!$F$7:$F$61,'1.4 Emisiones fugitivas'!$I$7:$I$61,"-")} -> IPCC 2006 (vol3; chapter 7) , Table 7.8 | IPCC 2012 (AR5; chapter 8), Table 8.A.1 | K94: - | L94: -
B95: Emisiones directas | C95: 1.4 Emisiones fugitivas | D95: Emisiones fugitivas | E95: HFC-41 | F95: - | G95: kilogramos | H95: {=_xlfn.XLOOKUP(E95&G95,'1.4 Emisiones fugitivas'!$C$7:$C$61&'1.4 Emisiones fugitivas'!$F$7:$F$61,'1.4 Emisiones fugitivas'!$G$7:$G$61,"-")} -> 116 | I95: {=_xlfn.XLOOKUP(E95&G95,'1.4 Emisiones fugitivas'!$C$7:$C$61&'1.4 Emisiones fugitivas'!$F$7:$F$61,'1.4 Emisiones fugitivas'!$H$7:$H$61,"-")} -> kgCO2e/kilogramos | J95: {=_xlfn.XLOOKUP(E95&G95,'1.4 Emisiones fugitivas'!$C$7:$C$61&'1.4 Emisiones fugitivas'!$F$7:$F$61,'1.4 Emisiones fugitivas'!$I$7:$I$61,"-")} -> IPCC 2006 (vol3; chapter 7) , Table 7.8 | IPCC 2012 (AR5; chapter 8), Table 8.A.1 | K95: - | L95: -
B96: Emisiones directas | C96: 1.4 Emisiones fugitivas | D96: Emisiones fugitivas | E96: HFC-43-I0mee | F96: - | G96: kilogramos | H96: {=_xlfn.XLOOKUP(E96&G96,'1.4 Emisiones fugitivas'!$C$7:$C$61&'1.4 Emisiones fugitivas'!$F$7:$F$61,'1.4 Emisiones fugitivas'!$G$7:$G$61,"-")} -> 1650 | I96: {=_xlfn.XLOOKUP(E96&G96,'1.4 Emisiones fugitivas'!$C$7:$C$61&'1.4 Emisiones fugitivas'!$F$7:$F$61,'1.4 Emisiones fugitivas'!$H$7:$H$61,"-")} -> kgCO2e/kilogramos | J96: {=_xlfn.XLOOKUP(E96&G96,'1.4 Emisiones fugitivas'!$C$7:$C$61&'1.4 Emisiones fugitivas'!$F$7:$F$61,'1.4 Emisiones fugitivas'!$I$7:$I$61,"-")} -> IPCC 2006 (vol3; chapter 7) , Table 7.8 | IPCC 2012 (AR5; chapter 8), Table 8.A.1 | K96: - | L96: -
B97: Emisiones directas | C97: 1.4 Emisiones fugitivas | D97: Emisiones fugitivas | E97: Perfluorobutano (PFC-3-1-10) | F97: - | G97: kilogramos | H97: {=_xlfn.XLOOKUP(E97&G97,'1.4 Emisiones fugitivas'!$C$7:$C$61&'1.4 Emisiones fugitivas'!$F$7:$F$61,'1.4 Emisiones fugitivas'!$G$7:$G$61,"-")} -> 9200 | I97: {=_xlfn.XLOOKUP(E97&G97,'1.4 Emisiones fugitivas'!$C$7:$C$61&'1.4 Emisiones fugitivas'!$F$7:$F$61,'1.4 Emisiones fugitivas'!$H$7:$H$61,"-")} -> kgCO2e/kilogramos | J97: {=_xlfn.XLOOKUP(E97&G97,'1.4 Emisiones fugitivas'!$C$7:$C$61&'1.4 Emisiones fugitivas'!$F$7:$F$61,'1.4 Emisiones fugitivas'!$I$7:$I$61,"-")} -> IPCC 2006 (vol3; chapter 7) , Table 7.8 | IPCC 2012 (AR5; chapter 8), Table 8.A.1 | K97: - | L97: -
B98: Emisiones directas | C98: 1.4 Emisiones fugitivas | D98: Emisiones fugitivas | E98: Perfluorociclobutano (PFC-318) | F98: - | G98: kilogramos | H98: {=_xlfn.XLOOKUP(E98&G98,'1.4 Emisiones fugitivas'!$C$7:$C$61&'1.4 Emisiones fugitivas'!$F$7:$F$61,'1.4 Emisiones fugitivas'!$G$7:$G$61,"-")} -> 9540 | I98: {=_xlfn.XLOOKUP(E98&G98,'1.4 Emisiones fugitivas'!$C$7:$C$61&'1.4 Emisiones fugitivas'!$F$7:$F$61,'1.4 Emisiones fugitivas'!$H$7:$H$61,"-")} -> kgCO2e/kilogramos | J98: {=_xlfn.XLOOKUP(E98&G98,'1.4 Emisiones fugitivas'!$C$7:$C$61&'1.4 Emisiones fugitivas'!$F$7:$F$61,'1.4 Emisiones fugitivas'!$I$7:$I$61,"-")} -> IPCC 2006 (vol3; chapter 7) , Table 7.8 | IPCC 2012 (AR5; chapter 8), Table 8.A.1 | K98: - | L98: -
B99: Emisiones directas | C99: 1.4 Emisiones fugitivas | D99: Emisiones fugitivas | E99: Perfluoroetano (PFC-116) | F99: - | G99: kilogramos | H99: {=_xlfn.XLOOKUP(E99&G99,'1.4 Emisiones fugitivas'!$C$7:$C$61&'1.4 Emisiones fugitivas'!$F$7:$F$61,'1.4 Emisiones fugitivas'!$G$7:$G$61,"-")} -> 11100 | I99: {=_xlfn.XLOOKUP(E99&G99,'1.4 Emisiones fugitivas'!$C$7:$C$61&'1.4 Emisiones fugitivas'!$F$7:$F$61,'1.4 Emisiones fugitivas'!$H$7:$H$61,"-")} -> kgCO2e/kilogramos | J99: {=_xlfn.XLOOKUP(E99&G99,'1.4 Emisiones fugitivas'!$C$7:$C$61&'1.4 Emisiones fugitivas'!$F$7:$F$61,'1.4 Emisiones fugitivas'!$I$7:$I$61,"-")} -> IPCC 2006 (vol3; chapter 7) , Table 7.8 | IPCC 2012 (AR5; chapter 8), Table 8.A.1 | K99: - | L99: -
B100: Emisiones directas | C100: 1.4 Emisiones fugitivas | D100: Emisiones fugitivas | E100: Perfluorohexano (PFC-5-1-14) | F100: - | G100: kilogramos | H100: {=_xlfn.XLOOKUP(E100&G100,'1.4 Emisiones fugitivas'!$C$7:$C$61&'1.4 Emisiones fugitivas'!$F$7:$F$61,'1.4 Emisiones fugitivas'!$G$7:$G$61,"-")} -> 7910 | I100: {=_xlfn.XLOOKUP(E100&G100,'1.4 Emisiones fugitivas'!$C$7:$C$61&'1.4 Emisiones fugitivas'!$F$7:$F$61,'1.4 Emisiones fugitivas'!$H$7:$H$61,"-")} -> kgCO2e/kilogramos | J100: {=_xlfn.XLOOKUP(E100&G100,'1.4 Emisiones fugitivas'!$C$7:$C$61&'1.4 Emisiones fugitivas'!$F$7:$F$61,'1.4 Emisiones fugitivas'!$I$7:$I$61,"-")} -> IPCC 2006 (vol3; chapter 7) , Table 7.8 | IPCC 2012 (AR5; chapter 8), Table 8.A.1 | K100: - | L100: -
B101: Emisiones directas | C101: 1.4 Emisiones fugitivas | D101: Emisiones fugitivas | E101: Perfluorometano (PFC-14) | F101: - | G101: kilogramos | H101: {=_xlfn.XLOOKUP(E101&G101,'1.4 Emisiones fugitivas'!$C$7:$C$61&'1.4 Emisiones fugitivas'!$F$7:$F$61,'1.4 Emisiones fugitivas'!$G$7:$G$61,"-")} -> 6630 | I101: {=_xlfn.XLOOKUP(E101&G101,'1.4 Emisiones fugitivas'!$C$7:$C$61&'1.4 Emisiones fugitivas'!$F$7:$F$61,'1.4 Emisiones fugitivas'!$H$7:$H$61,"-")} -> kgCO2e/kilogramos | J101: {=_xlfn.XLOOKUP(E101&G101,'1.4 Emisiones fugitivas'!$C$7:$C$61&'1.4 Emisiones fugitivas'!$F$7:$F$61,'1.4 Emisiones fugitivas'!$I$7:$I$61,"-")} -> IPCC 2006 (vol3; chapter 7) , Table 7.8 | IPCC 2012 (AR5; chapter 8), Table 8.A.1 | K101: - | L101: -
B102: Emisiones directas | C102: 1.4 Emisiones fugitivas | D102: Emisiones fugitivas | E102: Perfluoropentano (PFC-4-1-12) | F102: - | G102: kilogramos | H102: {=_xlfn.XLOOKUP(E102&G102,'1.4 Emisiones fugitivas'!$C$7:$C$61&'1.4 Emisiones fugitivas'!$F$7:$F$61,'1.4 Emisiones fugitivas'!$G$7:$G$61,"-")} -> 8550 | I102: {=_xlfn.XLOOKUP(E102&G102,'1.4 Emisiones fugitivas'!$C$7:$C$61&'1.4 Emisiones fugitivas'!$F$7:$F$61,'1.4 Emisiones fugitivas'!$H$7:$H$61,"-")} -> kgCO2e/kilogramos | J102: {=_xlfn.XLOOKUP(E102&G102,'1.4 Emisiones fugitivas'!$C$7:$C$61&'1.4 Emisiones fugitivas'!$F$7:$F$61,'1.4 Emisiones fugitivas'!$I$7:$I$61,"-")} -> IPCC 2006 (vol3; chapter 7) , Table 7.8 | IPCC 2012 (AR5; chapter 8), Table 8.A.1 | K102: - | L102: -
B103: Emisiones directas | C103: 1.4 Emisiones fugitivas | D103: Emisiones fugitivas | E103: HFC-125 | F103: - | G103: kilogramos | H103: {=_xlfn.XLOOKUP(E103&G103,'1.4 Emisiones fugitivas'!$C$7:$C$61&'1.4 Emisiones fugitivas'!$F$7:$F$61,'1.4 Emisiones fugitivas'!$G$7:$G$61,"-")} -> 3170 | I103: {=_xlfn.XLOOKUP(E103&G103,'1.4 Emisiones fugitivas'!$C$7:$C$61&'1.4 Emisiones fugitivas'!$F$7:$F$61,'1.4 Emisiones fugitivas'!$H$7:$H$61,"-")} -> kgCO2e/kilogramos | J103: {=_xlfn.XLOOKUP(E103&G103,'1.4 Emisiones fugitivas'!$C$7:$C$61&'1.4 Emisiones fugitivas'!$F$7:$F$61,'1.4 Emisiones fugitivas'!$I$7:$I$61,"-")} -> IPCC 2006 (vol3; chapter 7) , Table 7.8 | IPCC 2012 (AR5; chapter 8), Table 8.A.1 | K103: - | L103: -
B104: Emisiones directas | C104: 1.4 Emisiones fugitivas | D104: Emisiones fugitivas | E104: Perfluoropropano (PFC-218) | F104: - | G104: kilogramos | H104: {=_xlfn.XLOOKUP(E104&G104,'1.4 Emisiones fugitivas'!$C$7:$C$61&'1.4 Emisiones fugitivas'!$F$7:$F$61,'1.4 Emisiones fugitivas'!$G$7:$G$61,"-")} -> 8900 | I104: {=_xlfn.XLOOKUP(E104&G104,'1.4 Emisiones fugitivas'!$C$7:$C$61&'1.4 Emisiones fugitivas'!$F$7:$F$61,'1.4 Emisiones fugitivas'!$H$7:$H$61,"-")} -> kgCO2e/kilogramos | J104: {=_xlfn.XLOOKUP(E104&G104,'1.4 Emisiones fugitivas'!$C$7:$C$61&'1.4 Emisiones fugitivas'!$F$7:$F$61,'1.4 Emisiones fugitivas'!$I$7:$I$61,"-")} -> IPCC 2006 (vol3; chapter 7) , Table 7.8 | IPCC 2012 (AR5; chapter 8), Table 8.A.1 | K104: - | L104: -
... B147: Emisiones directas | C147: 1.4 Emisiones fugitivas | D147: Emisiones fugitivas | E147: Óxido nitroso (N2O) | F147: - | G147: kilogramos | H147: {=_xlfn.XLOOKUP(E147&G147,'1.4 Emisiones fugitivas'!$C$7:$C$61&'1.4 Emisiones fugitivas'!$F$7:$F$61,'1.4 Emisiones fugitivas'!$G$7:$G$61,"-")} -> 265 | I147: {=_xlfn.XLOOKUP(E147&G147,'1.4 Emisiones fugitivas'!$C$7:$C$61&'1.4 Emisiones fugitivas'!$F$7:$F$61,'1.4 Emisiones fugitivas'!$H$7:$H$61,"-")} -> kgCO2e/kilogramos | J147: {=_xlfn.XLOOKUP(E147&G147,'1.4 Emisiones fugitivas'!$C$7:$C$61&'1.4 Emisiones fugitivas'!$F$7:$F$61,'1.4 Emisiones fugitivas'!$I$7:$I$61,"-")} -> IPCC 2006 (vol3; chapter 7) , Table 7.8 | IPCC 2012 (AR5; chapter 8), Table 8.A.1 | K147: - | L147: -
B148: Emisiones indirectas por energía importada | C148: 2.1 Electricidad | D148: Emisiones indirectas por energía importada | E148: Sistema Interconectado del Norte Grande (SING) | F148: 2015 | G148: MWh | H148: {=_xlfn.XLOOKUP(E148&F148&G148,'2.1 Electricidad'!B:B&'2.1 Electricidad'!C:C&'2.1 Electricidad'!D:D,'2.1 Electricidad'!E:E,"-")} -> 764.4 | I148: {=_xlfn.XLOOKUP(E148&F148&G148,'2.1 Electricidad'!B:B&'2.1 Electricidad'!C:C&'2.1 Electricidad'!D:D,'2.1 Electricidad'!F:F,"-")} -> kgCO2e/MWh | J148: {=_xlfn.XLOOKUP(E148&F148&G148,'2.1 Electricidad'!B:B&'2.1 Electricidad'!C:C&'2.1 Electricidad'!D:D,'2.1 Electricidad'!G:G,"-")} -> Ministerio de Energía 2015 (Energía Abierta: http://energiaabierta.cl/visualizaciones/factor-de-emision-sic-sing/) | K148: - | L148: -
B149: Emisiones indirectas por energía importada | C149: 2.1 Electricidad | D149: Emisiones indirectas por energía importada | E149: Sistema Interconectado del Norte Grande (SING) | F149: 2015 | G149: GWh | H149: {=_xlfn.XLOOKUP(E149&F149&G149,'2.1 Electricidad'!B:B&'2.1 Electricidad'!C:C&'2.1 Electricidad'!D:D,'2.1 Electricidad'!E:E,"-")} -> 764400 | I149: {=_xlfn.XLOOKUP(E149&F149&G149,'2.1 Electricidad'!B:B&'2.1 Electricidad'!C:C&'2.1 Electricidad'!D:D,'2.1 Electricidad'!F:F,"-")} -> kgCO2e/GWh | J149: {=_xlfn.XLOOKUP(E149&F149&G149,'2.1 Electricidad'!B:B&'2.1 Electricidad'!C:C&'2.1 Electricidad'!D:D,'2.1 Electricidad'!G:G,"-")} -> Ministerio de Energía 2015 (Energía Abierta: http://energiaabierta.cl/visualizaciones/factor-de-emision-sic-sing/) | K149: - | L149: -
B150: Emisiones indirectas por energía importada | C150: 2.1 Electricidad | D150: Emisiones indirectas por energía importada | E150: Sistema Interconectado del Norte Grande (SING) | F150: 2015 | G150: kWh | H150: {=_xlfn.XLOOKUP(E150&F150&G150,'2.1 Electricidad'!B:B&'2.1 Electricidad'!C:C&'2.1 Electricidad'!D:D,'2.1 Electricidad'!E:E,"-")} -> 0.7644 | I150: {=_xlfn.XLOOKUP(E150&F150&G150,'2.1 Electricidad'!B:B&'2.1 Electricidad'!C:C&'2.1 Electricidad'!D:D,'2.1 Electricidad'!F:F,"-")} -> kgCO2e/kWh | J150: {=_xlfn.XLOOKUP(E150&F150&G150,'2.1 Electricidad'!B:B&'2.1 Electricidad'!C:C&'2.1 Electricidad'!D:D,'2.1 Electricidad'!G:G,"-")} -> Ministerio de Energía 2015 (Energía Abierta: http://energiaabierta.cl/visualizaciones/factor-de-emision-sic-sing/) | K150: - | L150: -
B151: Emisiones indirectas por energía importada | C151: 2.1 Electricidad | D151: Emisiones indirectas por energía importada | E151: Sistema Interconectado del Norte Grande (SING) | F151: 2016 | G151: MWh | H151: {=_xlfn.XLOOKUP(E151&F151&G151,'2.1 Electricidad'!B:B&'2.1 Electricidad'!C:C&'2.1 Electricidad'!D:D,'2.1 Electricidad'!E:E,"-")} -> 766.7 | I151: {=_xlfn.XLOOKUP(E151&F151&G151,'2.1 Electricidad'!B:B&'2.1 Electricidad'!C:C&'2.1 Electricidad'!D:D,'2.1 Electricidad'!F:F,"-")} -> kgCO2e/MWh | J151: {=_xlfn.XLOOKUP(E151&F151&G151,'2.1 Electricidad'!B:B&'2.1 Electricidad'!C:C&'2.1 Electricidad'!D:D,'2.1 Electricidad'!G:G,"-")} -> Ministerio de Energía 2016 (Energía Abierta: http://energiaabierta.cl/visualizaciones/factor-de-emision-sic-sing/) | K151: - | L151: -
B152: Emisiones indirectas por energía importada | C152: 2.1 Electricidad | D152: Emisiones indirectas por energía importada | E152: Sistema Interconectado del Norte Grande (SING) | F152: 2016 | G152: GWh | H152: {=_xlfn.XLOOKUP(E152&F152&G152,'2.1 Electricidad'!B:B&'2.1 Electricidad'!C:C&'2.1 Electricidad'!D:D,'2.1 Electricidad'!E:E,"-")} -> 766700 | I152: {=_xlfn.XLOOKUP(E152&F152&G152,'2.1 Electricidad'!B:B&'2.1 Electricidad'!C:C&'2.1 Electricidad'!D:D,'2.1 Electricidad'!F:F,"-")} -> kgCO2e/GWh | J152: {=_xlfn.XLOOKUP(E152&F152&G152,'2.1 Electricidad'!B:B&'2.1 Electricidad'!C:C&'2.1 Electricidad'!D:D,'2.1 Electricidad'!G:G,"-")} -> Ministerio de Energía 2016 (Energía Abierta: http://energiaabierta.cl/visualizaciones/factor-de-emision-sic-sing/) | K152: - | L152: -
B153: Emisiones indirectas por energía importada | C153: 2.1 Electricidad | D153: Emisiones indirectas por energía importada | E153: Sistema Interconectado del Norte Grande (SING) | F153: 2016 | G153: kWh | H153: {=_xlfn.XLOOKUP(E153&F153&G153,'2.1 Electricidad'!B:B&'2.1 Electricidad'!C:C&'2.1 Electricidad'!D:D,'2.1 Electricidad'!E:E,"-")} -> 0.7667 | I153: {=_xlfn.XLOOKUP(E153&F153&G153,'2.1 Electricidad'!B:B&'2.1 Electricidad'!C:C&'2.1 Electricidad'!D:D,'2.1 Electricidad'!F:F,"-")} -> kgCO2e/kWh | J153: {=_xlfn.XLOOKUP(E153&F153&G153,'2.1 Electricidad'!B:B&'2.1 Electricidad'!C:C&'2.1 Electricidad'!D:D,'2.1 Electricidad'!G:G,"-")} -> Ministerio de Energía 2016 (Energía Abierta: http://energiaabierta.cl/visualizaciones/factor-de-emision-sic-sing/) | K153: - | L153: -
B154: Emisiones indirectas por energía importada | C154: 2.1 Electricidad | D154: Emisiones indirectas por energía importada | E154: Sistema Interconectado del Norte Grande (SING) | F154: 2017 | G154: MWh | H154: {=_xlfn.XLOOKUP(E154&F154&G154,'2.1 Electricidad'!B:B&'2.1 Electricidad'!C:C&'2.1 Electricidad'!D:D,'2.1 Electricidad'!E:E,"-")} -> 773 | I154: {=_xlfn.XLOOKUP(E154&F154&G154,'2.1 Electricidad'!B:B&'2.1 Electricidad'!C:C&'2.1 Electricidad'!D:D,'2.1 Electricidad'!F:F,"-")} -> kgCO2e/MWh | J154: {=_xlfn.XLOOKUP(E154&F154&G154,'2.1 Electricidad'!B:B&'2.1 Electricidad'!C:C&'2.1 Electricidad'!D:D,'2.1 Electricidad'!G:G,"-")} -> Ministerio de Energía 2017 (Energía Abierta: http://energiaabierta.cl/visualizaciones/factor-de-emision-sic-sing/) | K154: - | L154: -
B155: Emisiones indirectas por energía importada | C155: 2.1 Electricidad | D155: Emisiones indirectas por energía importada | E155: Sistema Interconectado del Norte Grande (SING) | F155: 2017 | G155: GWh | H155: {=_xlfn.XLOOKUP(E155&F155&G155,'2.1 Electricidad'!B:B&'2.1 Electricidad'!C:C&'2.1 Electricidad'!D:D,'2.1 Electricidad'!E:E,"-")} -> 773000 | I155: {=_xlfn.XLOOKUP(E155&F155&G155,'2.1 Electricidad'!B:B&'2.1 Electricidad'!C:C&'2.1 Electricidad'!D:D,'2.1 Electricidad'!F:F,"-")} -> kgCO2e/GWh | J155: {=_xlfn.XLOOKUP(E155&F155&G155,'2.1 Electricidad'!B:B&'2.1 Electricidad'!C:C&'2.1 Electricidad'!D:D,'2.1 Electricidad'!G:G,"-")} -> Ministerio de Energía 2017 (Energía Abierta: http://energiaabierta.cl/visualizaciones/factor-de-emision-sic-sing/) | K155: - | L155: -
B156: Emisiones indirectas por energía importada | C156: 2.1 Electricidad | D156: Emisiones indirectas por energía importada | E156: Sistema Interconectado del Norte Grande (SING) | F156: 2017 | G156: kWh | H156: {=_xlfn.XLOOKUP(E156&F156&G156,'2.1 Electricidad'!B:B&'2.1 Electricidad'!C:C&'2.1 Electricidad'!D:D,'2.1 Electricidad'!E:E,"-")} -> 0.773 | I156: {=_xlfn.XLOOKUP(E156&F156&G156,'2.1 Electricidad'!B:B&'2.1 Electricidad'!C:C&'2.1 Electricidad'!D:D,'2.1 Electricidad'!F:F,"-")} -> kgCO2e/kWh | J156: {=_xlfn.XLOOKUP(E156&F156&G156,'2.1 Electricidad'!B:B&'2.1 Electricidad'!C:C&'2.1 Electricidad'!D:D,'2.1 Electricidad'!G:G,"-")} -> Ministerio de Energía 2017 (Energía Abierta: http://energiaabierta.cl/visualizaciones/factor-de-emision-sic-sing/) | K156: - | L156: -
B157: Emisiones indirectas por energía importada | C157: 2.1 Electricidad | D157: Emisiones indirectas por energía importada | E157: Sistema Interconectado Central (SIC) | F157: 2015 | G157: MWh | H157: {=_xlfn.XLOOKUP(E157&F157&G157,'2.1 Electricidad'!B:B&'2.1 Electricidad'!C:C&'2.1 Electricidad'!D:D,'2.1 Electricidad'!E:E,"-")} -> 345.9 | I157: {=_xlfn.XLOOKUP(E157&F157&G157,'2.1 Electricidad'!B:B&'2.1 Electricidad'!C:C&'2.1 Electricidad'!D:D,'2.1 Electricidad'!F:F,"-")} -> kgCO2e/MWh | J157: {=_xlfn.XLOOKUP(E157&F157&G157,'2.1 Electricidad'!B:B&'2.1 Electricidad'!C:C&'2.1 Electricidad'!D:D,'2.1 Electricidad'!G:G,"-")} -> Ministerio de Energía 2015 (Energía Abierta: http://energiaabierta.cl/visualizaciones/factor-de-emision-sic-sing/) | K157: - | L157: -
B158: Emisiones indirectas por energía importada | C158: 2.1 Electricidad | D158: Emisiones indirectas por energía importada | E158: Sistema Interconectado Central (SIC) | F158: 2015 | G158: GWh | H158: {=_xlfn.XLOOKUP(E158&F158&G158,'2.1 Electricidad'!B:B&'2.1 Electricidad'!C:C&'2.1 Electricidad'!D:D,'2.1 Electricidad'!E:E,"-")} -> 345900 | I158: {=_xlfn.XLOOKUP(E158&F158&G158,'2.1 Electricidad'!B:B&'2.1 Electricidad'!C:C&'2.1 Electricidad'!D:D,'2.1 Electricidad'!F:F,"-")} -> kgCO2e/GWh | J158: {=_xlfn.XLOOKUP(E158&F158&G158,'2.1 Electricidad'!B:B&'2.1 Electricidad'!C:C&'2.1 Electricidad'!D:D,'2.1 Electricidad'!G:G,"-")} -> Ministerio de Energía 2015 (Energía Abierta: http://energiaabierta.cl/visualizaciones/factor-de-emision-sic-sing/) | K158: - | L158: -
B159: Emisiones indirectas por energía importada | C159: 2.1 Electricidad | D159: Emisiones indirectas por energía importada | E159: Sistema Interconectado Central (SIC) | F159: 2015 | G159: kWh | H159: {=_xlfn.XLOOKUP(E159&F159&G159,'2.1 Electricidad'!B:B&'2.1 Electricidad'!C:C&'2.1 Electricidad'!D:D,'2.1 Electricidad'!E:E,"-")} -> 0.3459 | I159: {=_xlfn.XLOOKUP(E159&F159&G159,'2.1 Electricidad'!B:B&'2.1 Electricidad'!C:C&'2.1 Electricidad'!D:D,'2.1 Electricidad'!F:F,"-")} -> kgCO2e/kWh | J159: {=_xlfn.XLOOKUP(E159&F159&G159,'2.1 Electricidad'!B:B&'2.1 Electricidad'!C:C&'2.1 Electricidad'!D:D,'2.1 Electricidad'!G:G,"-")} -> Ministerio de Energía 2015 (Energía Abierta: http://energiaabierta.cl/visualizaciones/factor-de-emision-sic-sing/) | K159: - | L159: -
... B254: Emisiones indirectas por energía importada | C254: 2.1 Electricidad | D254: Emisiones indirectas por energía importada | E254: Sistema Eléctrico de Magallanes | F254: 2025 | G254: GWh | H254: {=_xlfn.XLOOKUP(E254&F254&G254,'2.1 Electricidad'!B:B&'2.1 Electricidad'!C:C&'2.1 Electricidad'!D:D,'2.1 Electricidad'!E:E,"-")} -> PENDIENTE | I254: {=_xlfn.XLOOKUP(E254&F254&G254,'2.1 Electricidad'!B:B&'2.1 Electricidad'!C:C&'2.1 Electricidad'!D:D,'2.1 Electricidad'!F:F,"-")} -> kgCO2e/GWh | J254: {=_xlfn.XLOOKUP(E254&F254&G254,'2.1 Electricidad'!B:B&'2.1 Electricidad'!C:C&'2.1 Electricidad'!D:D,'2.1 Electricidad'!G:G,"-")} -> Ministerio de Energía 2025 (Energía Abierta: http://energiaabierta.cl/visualizaciones/factor-de-emision-sic-sing/) | K254: - | L254: -
B255: Emisiones indirectas por energía importada | C255: 2.1 Electricidad | D255: Emisiones indirectas por energía importada | E255: Sistema Eléctrico de Magallanes | F255: 2025 | G255: kWh | H255: {=_xlfn.XLOOKUP(E255&F255&G255,'2.1 Electricidad'!B:B&'2.1 Electricidad'!C:C&'2.1 Electricidad'!D:D,'2.1 Electricidad'!E:E,"-")} -> PENDIENTE | I255: {=_xlfn.XLOOKUP(E255&F255&G255,'2.1 Electricidad'!B:B&'2.1 Electricidad'!C:C&'2.1 Electricidad'!D:D,'2.1 Electricidad'!F:F,"-")} -> kgCO2e/kWh | J255: {=_xlfn.XLOOKUP(E255&F255&G255,'2.1 Electricidad'!B:B&'2.1 Electricidad'!C:C&'2.1 Electricidad'!D:D,'2.1 Electricidad'!G:G,"-")} -> Ministerio de Energía 2025 (Energía Abierta: http://energiaabierta.cl/visualizaciones/factor-de-emision-sic-sing/)
B256: Emisiones indirectas por energía importada | C256: 2.1 Electricidad | D256: Emisiones indirectas por energía importada | E256: Sistema Eléctrico de Los Lagos | F256: 2015 | G256: MWh | H256: {=_xlfn.XLOOKUP(E256&F256&G256,'2.1 Electricidad'!B:B&'2.1 Electricidad'!C:C&'2.1 Electricidad'!D:D,'2.1 Electricidad'!E:E,"-")} -> 619 | I256: {=_xlfn.XLOOKUP(E256&F256&G256,'2.1 Electricidad'!B:B&'2.1 Electricidad'!C:C&'2.1 Electricidad'!D:D,'2.1 Electricidad'!F:F,"-")} -> kgCO2e/MWh | J256: {=_xlfn.XLOOKUP(E256&F256&G256,'2.1 Electricidad'!B:B&'2.1 Electricidad'!C:C&'2.1 Electricidad'!D:D,'2.1 Electricidad'!G:G,"-")} -> Ministerio de Energía 2015 (Energía Abierta: http://energiaabierta.cl/visualizaciones/factor-de-emision-sic-sing/) | K256: - | L256: -
B257: Emisiones indirectas por energía importada | C257: 2.1 Electricidad | D257: Emisiones indirectas por energía importada | E257: Sistema Eléctrico de Los Lagos | F257: 2015 | G257: GWh | H257: {=_xlfn.XLOOKUP(E257&F257&G257,'2.1 Electricidad'!B:B&'2.1 Electricidad'!C:C&'2.1 Electricidad'!D:D,'2.1 Electricidad'!E:E,"-")} -> 619000 | I257: {=_xlfn.XLOOKUP(E257&F257&G257,'2.1 Electricidad'!B:B&'2.1 Electricidad'!C:C&'2.1 Electricidad'!D:D,'2.1 Electricidad'!F:F,"-")} -> kgCO2e/GWh | J257: {=_xlfn.XLOOKUP(E257&F257&G257,'2.1 Electricidad'!B:B&'2.1 Electricidad'!C:C&'2.1 Electricidad'!D:D,'2.1 Electricidad'!G:G,"-")} -> Ministerio de Energía 2015 (Energía Abierta: http://energiaabierta.cl/visualizaciones/factor-de-emision-sic-sing/) | K257: - | L257: -
B258: Emisiones indirectas por energía importada | C258: 2.1 Electricidad | D258: Emisiones indirectas por energía importada | E258: Sistema Eléctrico de Los Lagos | F258: 2015 | G258: kWh | H258: {=_xlfn.XLOOKUP(E258&F258&G258,'2.1 Electricidad'!B:B&'2.1 Electricidad'!C:C&'2.1 Electricidad'!D:D,'2.1 Electricidad'!E:E,"-")} -> 0.619 | I258: {=_xlfn.XLOOKUP(E258&F258&G258,'2.1 Electricidad'!B:B&'2.1 Electricidad'!C:C&'2.1 Electricidad'!D:D,'2.1 Electricidad'!F:F,"-")} -> kgCO2e/kWh | J258: {=_xlfn.XLOOKUP(E258&F258&G258,'2.1 Electricidad'!B:B&'2.1 Electricidad'!C:C&'2.1 Electricidad'!D:D,'2.1 Electricidad'!G:G,"-")} -> Ministerio de Energía 2015 (Energía Abierta: http://energiaabierta.cl/visualizaciones/factor-de-emision-sic-sing/) | K258: - | L258: -
B259: Emisiones indirectas por energía importada | C259: 2.1 Electricidad | D259: Emisiones indirectas por energía importada | E259: Sistema Eléctrico de Los Lagos | F259: 2016 | G259: MWh | H259: {=_xlfn.XLOOKUP(E259&F259&G259,'2.1 Electricidad'!B:B&'2.1 Electricidad'!C:C&'2.1 Electricidad'!D:D,'2.1 Electricidad'!E:E,"-")} -> 608.41667 | I259: {=_xlfn.XLOOKUP(E259&F259&G259,'2.1 Electricidad'!B:B&'2.1 Electricidad'!C:C&'2.1 Electricidad'!D:D,'2.1 Electricidad'!F:F,"-")} -> kgCO2e/MWh | J259: {=_xlfn.XLOOKUP(E259&F259&G259,'2.1 Electricidad'!B:B&'2.1 Electricidad'!C:C&'2.1 Electricidad'!D:D,'2.1 Electricidad'!G:G,"-")} -> Ministerio de Energía 2016 (Energía Abierta: http://energiaabierta.cl/visualizaciones/factor-de-emision-sic-sing/) | K259: - | L259: -
B260: Emisiones indirectas por energía importada | C260: 2.1 Electricidad | D260: Emisiones indirectas por energía importada | E260: Sistema Eléctrico de Los Lagos | F260: 2016 | G260: GWh | H260: {=_xlfn.XLOOKUP(E260&F260&G260,'2.1 Electricidad'!B:B&'2.1 Electricidad'!C:C&'2.1 Electricidad'!D:D,'2.1 Electricidad'!E:E,"-")} -> 608416.67 | I260: {=_xlfn.XLOOKUP(E260&F260&G260,'2.1 Electricidad'!B:B&'2.1 Electricidad'!C:C&'2.1 Electricidad'!D:D,'2.1 Electricidad'!F:F,"-")} -> kgCO2e/GWh | J260: {=_xlfn.XLOOKUP(E260&F260&G260,'2.1 Electricidad'!B:B&'2.1 Electricidad'!C:C&'2.1 Electricidad'!D:D,'2.1 Electricidad'!G:G,"-")} -> Ministerio de Energía 2016 (Energía Abierta: http://energiaabierta.cl/visualizaciones/factor-de-emision-sic-sing/) | K260: - | L260: -
B261: Emisiones indirectas por energía importada | C261: 2.1 Electricidad | D261: Emisiones indirectas por energía importada | E261: Sistema Eléctrico de Los Lagos | F261: 2016 | G261: kWh | H261: {=_xlfn.XLOOKUP(E261&F261&G261,'2.1 Electricidad'!B:B&'2.1 Electricidad'!C:C&'2.1 Electricidad'!D:D,'2.1 Electricidad'!E:E,"-")} -> 0.60841667 | I261: {=_xlfn.XLOOKUP(E261&F261&G261,'2.1 Electricidad'!B:B&'2.1 Electricidad'!C:C&'2.1 Electricidad'!D:D,'2.1 Electricidad'!F:F,"-")} -> kgCO2e/kWh | J261: {=_xlfn.XLOOKUP(E261&F261&G261,'2.1 Electricidad'!B:B&'2.1 Electricidad'!C:C&'2.1 Electricidad'!D:D,'2.1 Electricidad'!G:G,"-")} -> Ministerio de Energía 2016 (Energía Abierta: http://energiaabierta.cl/visualizaciones/factor-de-emision-sic-sing/) | K261: - | L261: -
B262: Emisiones indirectas por energía importada | C262: 2.1 Electricidad | D262: Emisiones indirectas por energía importada | E262: Sistema Eléctrico de Los Lagos | F262: 2017 | G262: MWh | H262: {=_xlfn.XLOOKUP(E262&F262&G262,'2.1 Electricidad'!B:B&'2.1 Electricidad'!C:C&'2.1 Electricidad'!D:D,'2.1 Electricidad'!E:E,"-")} -> 557.08333 | I262: {=_xlfn.XLOOKUP(E262&F262&G262,'2.1 Electricidad'!B:B&'2.1 Electricidad'!C:C&'2.1 Electricidad'!D:D,'2.1 Electricidad'!F:F,"-")} -> kgCO2e/MWh | J262: {=_xlfn.XLOOKUP(E262&F262&G262,'2.1 Electricidad'!B:B&'2.1 Electricidad'!C:C&'2.1 Electricidad'!D:D,'2.1 Electricidad'!G:G,"-")} -> Ministerio de Energía 2017 (Energía Abierta: http://energiaabierta.cl/visualizaciones/factor-de-emision-sic-sing/) | K262: - | L262: -
B263: Emisiones indirectas por energía importada | C263: 2.1 Electricidad | D263: Emisiones indirectas por energía importada | E263: Sistema Eléctrico de Los Lagos | F263: 2017 | G263: GWh | H263: {=_xlfn.XLOOKUP(E263&F263&G263,'2.1 Electricidad'!B:B&'2.1 Electricidad'!C:C&'2.1 Electricidad'!D:D,'2.1 Electricidad'!E:E,"-")} -> 557083.33 | I263: {=_xlfn.XLOOKUP(E263&F263&G263,'2.1 Electricidad'!B:B&'2.1 Electricidad'!C:C&'2.1 Electricidad'!D:D,'2.1 Electricidad'!F:F,"-")} -> kgCO2e/GWh | J263: {=_xlfn.XLOOKUP(E263&F263&G263,'2.1 Electricidad'!B:B&'2.1 Electricidad'!C:C&'2.1 Electricidad'!D:D,'2.1 Electricidad'!G:G,"-")} -> Ministerio de Energía 2017 (Energía Abierta: http://energiaabierta.cl/visualizaciones/factor-de-emision-sic-sing/) | K263: - | L263: -
B264: Emisiones indirectas por energía importada | C264: 2.1 Electricidad | D264: Emisiones indirectas por energía importada | E264: Sistema Eléctrico de Los Lagos | F264: 2017 | G264: kWh | H264: {=_xlfn.XLOOKUP(E264&F264&G264,'2.1 Electricidad'!B:B&'2.1 Electricidad'!C:C&'2.1 Electricidad'!D:D,'2.1 Electricidad'!E:E,"-")} -> 0.55708333 | I264: {=_xlfn.XLOOKUP(E264&F264&G264,'2.1 Electricidad'!B:B&'2.1 Electricidad'!C:C&'2.1 Electricidad'!D:D,'2.1 Electricidad'!F:F,"-")} -> kgCO2e/kWh | J264: {=_xlfn.XLOOKUP(E264&F264&G264,'2.1 Electricidad'!B:B&'2.1 Electricidad'!C:C&'2.1 Electricidad'!D:D,'2.1 Electricidad'!G:G,"-")} -> Ministerio de Energía 2017 (Energía Abierta: http://energiaabierta.cl/visualizaciones/factor-de-emision-sic-sing/) | K264: - | L264: -
B265: Emisiones indirectas por energía importada | C265: 2.1 Electricidad | D265: Emisiones indirectas por energía importada | E265: Sistema Eléctrico de Los Lagos | F265: 2018 | G265: MWh | H265: {=_xlfn.XLOOKUP(E265&F265&G265,'2.1 Electricidad'!B:B&'2.1 Electricidad'!C:C&'2.1 Electricidad'!D:D,'2.1 Electricidad'!E:E,"-")} -> 555.08333 | I265: {=_xlfn.XLOOKUP(E265&F265&G265,'2.1 Electricidad'!B:B&'2.1 Electricidad'!C:C&'2.1 Electricidad'!D:D,'2.1 Electricidad'!F:F,"-")} -> kgCO2e/MWh | J265: {=_xlfn.XLOOKUP(E265&F265&G265,'2.1 Electricidad'!B:B&'2.1 Electricidad'!C:C&'2.1 Electricidad'!D:D,'2.1 Electricidad'!G:G,"-")} -> Ministerio de Energía 2018 (Energía Abierta: http://energiaabierta.cl/visualizaciones/factor-de-emision-sic-sing/) | K265: - | L265: -
B266: Emisiones indirectas por energía importada | C266: 2.1 Electricidad | D266: Emisiones indirectas por energía importada | E266: Sistema Eléctrico de Los Lagos | F266: 2018 | G266: GWh | H266: {=_xlfn.XLOOKUP(E266&F266&G266,'2.1 Electricidad'!B:B&'2.1 Electricidad'!C:C&'2.1 Electricidad'!D:D,'2.1 Electricidad'!E:E,"-")} -> 555083.33 | I266: {=_xlfn.XLOOKUP(E266&F266&G266,'2.1 Electricidad'!B:B&'2.1 Electricidad'!C:C&'2.1 Electricidad'!D:D,'2.1 Electricidad'!F:F,"-")} -> kgCO2e/GWh | J266: {=_xlfn.XLOOKUP(E266&F266&G266,'2.1 Electricidad'!B:B&'2.1 Electricidad'!C:C&'2.1 Electricidad'!D:D,'2.1 Electricidad'!G:G,"-")} -> Ministerio de Energía 2018 (Energía Abierta: http://energiaabierta.cl/visualizaciones/factor-de-emision-sic-sing/) | K266: - | L266: -
B267: Emisiones indirectas por energía importada | C267: 2.1 Electricidad | D267: Emisiones indirectas por energía importada | E267: Sistema Eléctrico de Los Lagos | F267: 2018 | G267: kWh | H267: {=_xlfn.XLOOKUP(E267&F267&G267,'2.1 Electricidad'!B:B&'2.1 Electricidad'!C:C&'2.1 Electricidad'!D:D,'2.1 Electricidad'!E:E,"-")} -> 0.55508333 | I267: {=_xlfn.XLOOKUP(E267&F267&G267,'2.1 Electricidad'!B:B&'2.1 Electricidad'!C:C&'2.1 Electricidad'!D:D,'2.1 Electricidad'!F:F,"-")} -> kgCO2e/kWh | J267: {=_xlfn.XLOOKUP(E267&F267&G267,'2.1 Electricidad'!B:B&'2.1 Electricidad'!C:C&'2.1 Electricidad'!D:D,'2.1 Electricidad'!G:G,"-")} -> Ministerio de Energía 2018 (Energía Abierta: http://energiaabierta.cl/visualizaciones/factor-de-emision-sic-sing/) | K267: - | L267: -
... B288: Emisiones indirectas por energía importada | C288: 2.1 Electricidad | D288: Emisiones indirectas por energía importada | E288: Sistema Eléctrico de Los Lagos | F288: 2025 | G288: kWh | H288: {=_xlfn.XLOOKUP(E288&F288&G288,'2.1 Electricidad'!B:B&'2.1 Electricidad'!C:C&'2.1 Electricidad'!D:D,'2.1 Electricidad'!E:E,"-")} -> PENDIENTE | I288: {=_xlfn.XLOOKUP(E288&F288&G288,'2.1 Electricidad'!B:B&'2.1 Electricidad'!C:C&'2.1 Electricidad'!D:D,'2.1 Electricidad'!F:F,"-")} -> kgCO2e/kWh | J288: {=_xlfn.XLOOKUP(E288&F288&G288,'2.1 Electricidad'!B:B&'2.1 Electricidad'!C:C&'2.1 Electricidad'!D:D,'2.1 Electricidad'!G:G,"-")} -> Ministerio de Energía 2025 (Energía Abierta: http://energiaabierta.cl/visualizaciones/factor-de-emision-sic-sing/) | K288: - | L288: -
B289: Emisiones indirectas por energía importada | C289: 2.2 Pérdidas por T&D | D289: Pérdidas por T&D | E289: Sistema Interconectado del Norte Grande (SING) | F289: 2015 | G289: MWh | H289: {=_xlfn.XLOOKUP(E289&F289&G289,'2.2 Perdidas por T&D'!B:B&'2.2 Perdidas por T&D'!C:C&'2.2 Perdidas por T&D'!D:D,'2.2 Perdidas por T&D'!E:E,"-")} -> 43.5708 | I289: {=_xlfn.XLOOKUP(E289&F289&G289,'2.2 Perdidas por T&D'!B:B&'2.2 Perdidas por T&D'!C:C&'2.2 Perdidas por T&D'!D:D,'2.2 Perdidas por T&D'!F:F,"-")} -> kgCO2e/MWh | J289: {=_xlfn.XLOOKUP(E289&F289&G289,'2.2 Perdidas por T&D'!B:B&'2.2 Perdidas por T&D'!C:C&'2.2 Perdidas por T&D'!D:D,'2.2 Perdidas por T&D'!G:G,"-")} -> Base de Información de Eficiencia Energética - CEPAL- Enerdata, 2018 (https://biee-cepal.enerdata.net/es/datamapper/rate-of-electricity-t&d-losses.html) | K289: - | L289: -
B290: Emisiones indirectas por energía importada | C290: 2.2 Pérdidas por T&D | D290: Pérdidas por T&D | E290: Sistema Interconectado del Norte Grande (SING) | F290: 2015 | G290: GWh | H290: {=_xlfn.XLOOKUP(E290&F290&G290,'2.2 Perdidas por T&D'!B:B&'2.2 Perdidas por T&D'!C:C&'2.2 Perdidas por T&D'!D:D,'2.2 Perdidas por T&D'!E:E,"-")} -> 43570.8 | I290: {=_xlfn.XLOOKUP(E290&F290&G290,'2.2 Perdidas por T&D'!B:B&'2.2 Perdidas por T&D'!C:C&'2.2 Perdidas por T&D'!D:D,'2.2 Perdidas por T&D'!F:F,"-")} -> kgCO2e/GWh | J290: {=_xlfn.XLOOKUP(E290&F290&G290,'2.2 Perdidas por T&D'!B:B&'2.2 Perdidas por T&D'!C:C&'2.2 Perdidas por T&D'!D:D,'2.2 Perdidas por T&D'!G:G,"-")} -> Base de Información de Eficiencia Energética - CEPAL- Enerdata, 2018 (https://biee-cepal.enerdata.net/es/datamapper/rate-of-electricity-t&d-losses.html) | K290: - | L290: -
B291: Emisiones indirectas por energía importada | C291: 2.2 Pérdidas por T&D | D291: Pérdidas por T&D | E291: Sistema Interconectado del Norte Grande (SING) | F291: 2015 | G291: kWh | H291: {=_xlfn.XLOOKUP(E291&F291&G291,'2.2 Perdidas por T&D'!B:B&'2.2 Perdidas por T&D'!C:C&'2.2 Perdidas por T&D'!D:D,'2.2 Perdidas por T&D'!E:E,"-")} -> 0.0435708 | I291: {=_xlfn.XLOOKUP(E291&F291&G291,'2.2 Perdidas por T&D'!B:B&'2.2 Perdidas por T&D'!C:C&'2.2 Perdidas por T&D'!D:D,'2.2 Perdidas por T&D'!F:F,"-")} -> kgCO2e/kWh | J291: {=_xlfn.XLOOKUP(E291&F291&G291,'2.2 Perdidas por T&D'!B:B&'2.2 Perdidas por T&D'!C:C&'2.2 Perdidas por T&D'!D:D,'2.2 Perdidas por T&D'!G:G,"-")} -> Base de Información de Eficiencia Energética - CEPAL- Enerdata, 2018 (https://biee-cepal.enerdata.net/es/datamapper/rate-of-electricity-t&d-losses.html) | K291: - | L291: -
B292: Emisiones indirectas por energía importada | C292: 2.2 Pérdidas por T&D | D292: Pérdidas por T&D | E292: Sistema Interconectado del Norte Grande (SING) | F292: 2016 | G292: MWh | H292: {=_xlfn.XLOOKUP(E292&F292&G292,'2.2 Perdidas por T&D'!B:B&'2.2 Perdidas por T&D'!C:C&'2.2 Perdidas por T&D'!D:D,'2.2 Perdidas por T&D'!E:E,"-")} -> 43.7019 | I292: {=_xlfn.XLOOKUP(E292&F292&G292,'2.2 Perdidas por T&D'!B:B&'2.2 Perdidas por T&D'!C:C&'2.2 Perdidas por T&D'!D:D,'2.2 Perdidas por T&D'!F:F,"-")} -> kgCO2e/MWh | J292: {=_xlfn.XLOOKUP(E292&F292&G292,'2.2 Perdidas por T&D'!B:B&'2.2 Perdidas por T&D'!C:C&'2.2 Perdidas por T&D'!D:D,'2.2 Perdidas por T&D'!G:G,"-")} -> Base de Información de Eficiencia Energética - CEPAL- Enerdata, 2018 (https://biee-cepal.enerdata.net/es/datamapper/rate-of-electricity-t&d-losses.html) | K292: - | L292: -
B293: Emisiones indirectas por energía importada | C293: 2.2 Pérdidas por T&D | D293: Pérdidas por T&D | E293: Sistema Interconectado del Norte Grande (SING) | F293: 2016 | G293: GWh | H293: {=_xlfn.XLOOKUP(E293&F293&G293,'2.2 Perdidas por T&D'!B:B&'2.2 Perdidas por T&D'!C:C&'2.2 Perdidas por T&D'!D:D,'2.2 Perdidas por T&D'!E:E,"-")} -> 43701.9 | I293: {=_xlfn.XLOOKUP(E293&F293&G293,'2.2 Perdidas por T&D'!B:B&'2.2 Perdidas por T&D'!C:C&'2.2 Perdidas por T&D'!D:D,'2.2 Perdidas por T&D'!F:F,"-")} -> kgCO2e/GWh | J293: {=_xlfn.XLOOKUP(E293&F293&G293,'2.2 Perdidas por T&D'!B:B&'2.2 Perdidas por T&D'!C:C&'2.2 Perdidas por T&D'!D:D,'2.2 Perdidas por T&D'!G:G,"-")} -> Base de Información de Eficiencia Energética - CEPAL- Enerdata, 2018 (https://biee-cepal.enerdata.net/es/datamapper/rate-of-electricity-t&d-losses.html) | K293: - | L293: -
B294: Emisiones indirectas por energía importada | C294: 2.2 Pérdidas por T&D | D294: Pérdidas por T&D | E294: Sistema Interconectado del Norte Grande (SING) | F294: 2016 | G294: kWh | H294: {=_xlfn.XLOOKUP(E294&F294&G294,'2.2 Perdidas por T&D'!B:B&'2.2 Perdidas por T&D'!C:C&'2.2 Perdidas por T&D'!D:D,'2.2 Perdidas por T&D'!E:E,"-")} -> 0.0437019 | I294: {=_xlfn.XLOOKUP(E294&F294&G294,'2.2 Perdidas por T&D'!B:B&'2.2 Perdidas por T&D'!C:C&'2.2 Perdidas por T&D'!D:D,'2.2 Perdidas por T&D'!F:F,"-")} -> kgCO2e/kWh | J294: {=_xlfn.XLOOKUP(E294&F294&G294,'2.2 Perdidas por T&D'!B:B&'2.2 Perdidas por T&D'!C:C&'2.2 Perdidas por T&D'!D:D,'2.2 Perdidas por T&D'!G:G,"-")} -> Base de Información de Eficiencia Energética - CEPAL- Enerdata, 2018 (https://biee-cepal.enerdata.net/es/datamapper/rate-of-electricity-t&d-losses.html) | K294: - | L294: -
B295: Emisiones indirectas por energía importada | C295: 2.2 Pérdidas por T&D | D295: Pérdidas por T&D | E295: Sistema Interconectado del Norte Grande (SING) | F295: 2017 | G295: MWh | H295: {=_xlfn.XLOOKUP(E295&F295&G295,'2.2 Perdidas por T&D'!B:B&'2.2 Perdidas por T&D'!C:C&'2.2 Perdidas por T&D'!D:D,'2.2 Perdidas por T&D'!E:E,"-")} -> 44.061 | I295: {=_xlfn.XLOOKUP(E295&F295&G295,'2.2 Perdidas por T&D'!B:B&'2.2 Perdidas por T&D'!C:C&'2.2 Perdidas por T&D'!D:D,'2.2 Perdidas por T&D'!F:F,"-")} -> kgCO2e/MWh | J295: {=_xlfn.XLOOKUP(E295&F295&G295,'2.2 Perdidas por T&D'!B:B&'2.2 Perdidas por T&D'!C:C&'2.2 Perdidas por T&D'!D:D,'2.2 Perdidas por T&D'!G:G,"-")} -> Base de Información de Eficiencia Energética - CEPAL- Enerdata, 2018 (https://biee-cepal.enerdata.net/es/datamapper/rate-of-electricity-t&d-losses.html) | K295: - | L295: -
B296: Emisiones indirectas por energía importada | C296: 2.2 Pérdidas por T&D | D296: Pérdidas por T&D | E296: Sistema Interconectado del Norte Grande (SING) | F296: 2017 | G296: GWh | H296: {=_xlfn.XLOOKUP(E296&F296&G296,'2.2 Perdidas por T&D'!B:B&'2.2 Perdidas por T&D'!C:C&'2.2 Perdidas por T&D'!D:D,'2.2 Perdidas por T&D'!E:E,"-")} -> 44061 | I296: {=_xlfn.XLOOKUP(E296&F296&G296,'2.2 Perdidas por T&D'!B:B&'2.2 Perdidas por T&D'!C:C&'2.2 Perdidas por T&D'!D:D,'2.2 Perdidas por T&D'!F:F,"-")} -> kgCO2e/GWh | J296: {=_xlfn.XLOOKUP(E296&F296&G296,'2.2 Perdidas por T&D'!B:B&'2.2 Perdidas por T&D'!C:C&'2.2 Perdidas por T&D'!D:D,'2.2 Perdidas por T&D'!G:G,"-")} -> Base de Información de Eficiencia Energética - CEPAL- Enerdata, 2018 (https://biee-cepal.enerdata.net/es/datamapper/rate-of-electricity-t&d-losses.html) | K296: - | L296: -
B297: Emisiones indirectas por energía importada | C297: 2.2 Pérdidas por T&D | D297: Pérdidas por T&D | E297: Sistema Interconectado del Norte Grande (SING) | F297: 2017 | G297: kWh | H297: {=_xlfn.XLOOKUP(E297&F297&G297,'2.2 Perdidas por T&D'!B:B&'2.2 Perdidas por T&D'!C:C&'2.2 Perdidas por T&D'!D:D,'2.2 Perdidas por T&D'!E:E,"-")} -> 0.044061 | I297: {=_xlfn.XLOOKUP(E297&F297&G297,'2.2 Perdidas por T&D'!B:B&'2.2 Perdidas por T&D'!C:C&'2.2 Perdidas por T&D'!D:D,'2.2 Perdidas por T&D'!F:F,"-")} -> kgCO2e/kWh | J297: {=_xlfn.XLOOKUP(E297&F297&G297,'2.2 Perdidas por T&D'!B:B&'2.2 Perdidas por T&D'!C:C&'2.2 Perdidas por T&D'!D:D,'2.2 Perdidas por T&D'!G:G,"-")} -> Base de Información de Eficiencia Energética - CEPAL- Enerdata, 2018 (https://biee-cepal.enerdata.net/es/datamapper/rate-of-electricity-t&d-losses.html) | K297: - | L297: -
B298: Emisiones indirectas por energía importada | C298: 2.2 Pérdidas por T&D | D298: Pérdidas por T&D | E298: Sistema Interconectado Central (SIC) | F298: 2015 | G298: MWh | H298: {=_xlfn.XLOOKUP(E298&F298&G298,'2.2 Perdidas por T&D'!B:B&'2.2 Perdidas por T&D'!C:C&'2.2 Perdidas por T&D'!D:D,'2.2 Perdidas por T&D'!E:E,"-")} -> 19.7163 | I298: {=_xlfn.XLOOKUP(E298&F298&G298,'2.2 Perdidas por T&D'!B:B&'2.2 Perdidas por T&D'!C:C&'2.2 Perdidas por T&D'!D:D,'2.2 Perdidas por T&D'!F:F,"-")} -> kgCO2e/MWh | J298: {=_xlfn.XLOOKUP(E298&F298&G298,'2.2 Perdidas por T&D'!B:B&'2.2 Perdidas por T&D'!C:C&'2.2 Perdidas por T&D'!D:D,'2.2 Perdidas por T&D'!G:G,"-")} -> Base de Información de Eficiencia Energética - CEPAL- Enerdata, 2018 (https://biee-cepal.enerdata.net/es/datamapper/rate-of-electricity-t&d-losses.html) | K298: - | L298: -
B299: Emisiones indirectas por energía importada | C299: 2.2 Pérdidas por T&D | D299: Pérdidas por T&D | E299: Sistema Interconectado Central (SIC) | F299: 2015 | G299: GWh | H299: {=_xlfn.XLOOKUP(E299&F299&G299,'2.2 Perdidas por T&D'!B:B&'2.2 Perdidas por T&D'!C:C&'2.2 Perdidas por T&D'!D:D,'2.2 Perdidas por T&D'!E:E,"-")} -> 19716.3 | I299: {=_xlfn.XLOOKUP(E299&F299&G299,'2.2 Perdidas por T&D'!B:B&'2.2 Perdidas por T&D'!C:C&'2.2 Perdidas por T&D'!D:D,'2.2 Perdidas por T&D'!F:F,"-")} -> kgCO2e/GWh | J299: {=_xlfn.XLOOKUP(E299&F299&G299,'2.2 Perdidas por T&D'!B:B&'2.2 Perdidas por T&D'!C:C&'2.2 Perdidas por T&D'!D:D,'2.2 Perdidas por T&D'!G:G,"-")} -> Base de Información de Eficiencia Energética - CEPAL- Enerdata, 2018 (https://biee-cepal.enerdata.net/es/datamapper/rate-of-electricity-t&d-losses.html) | K299: - | L299: -
B300: Emisiones indirectas por energía importada | C300: 2.2 Pérdidas por T&D | D300: Pérdidas por T&D | E300: Sistema Interconectado Central (SIC) | F300: 2015 | G300: kWh | H300: {=_xlfn.XLOOKUP(E300&F300&G300,'2.2 Perdidas por T&D'!B:B&'2.2 Perdidas por T&D'!C:C&'2.2 Perdidas por T&D'!D:D,'2.2 Perdidas por T&D'!E:E,"-")} -> 0.0197163 | I300: {=_xlfn.XLOOKUP(E300&F300&G300,'2.2 Perdidas por T&D'!B:B&'2.2 Perdidas por T&D'!C:C&'2.2 Perdidas por T&D'!D:D,'2.2 Perdidas por T&D'!F:F,"-")} -> kgCO2e/kWh | J300: {=_xlfn.XLOOKUP(E300&F300&G300,'2.2 Perdidas por T&D'!B:B&'2.2 Perdidas por T&D'!C:C&'2.2 Perdidas por T&D'!D:D,'2.2 Perdidas por T&D'!G:G,"-")} -> Base de Información de Eficiencia Energética - CEPAL- Enerdata, 2018 (https://biee-cepal.enerdata.net/es/datamapper/rate-of-electricity-t&d-losses.html) | K300: - | L300: -
... B426: Emisiones indirectas por energía importada | C426: 2.2 Pérdidas por T&D | D426: Pérdidas por T&D | E426: Sistema Eléctrico de Los Lagos | F426: 2024 | G426: kWh | H426: {=_xlfn.XLOOKUP(E426&F426&G426,'2.2 Perdidas por T&D'!B:B&'2.2 Perdidas por T&D'!C:C&'2.2 Perdidas por T&D'!D:D,'2.2 Perdidas por T&D'!E:E,"-")} -> 0.0358245 | I426: {=_xlfn.XLOOKUP(E426&F426&G426,'2.2 Perdidas por T&D'!B:B&'2.2 Perdidas por T&D'!C:C&'2.2 Perdidas por T&D'!D:D,'2.2 Perdidas por T&D'!F:F,"-")} -> kgCO2e/kWh | J426: {=_xlfn.XLOOKUP(E426&F426&G426,'2.2 Perdidas por T&D'!B:B&'2.2 Perdidas por T&D'!C:C&'2.2 Perdidas por T&D'!D:D,'2.2 Perdidas por T&D'!G:G,"-")} -> Base de Información de Eficiencia Energética - CEPAL- Enerdata, 2018 (https://biee-cepal.enerdata.net/es/datamapper/rate-of-electricity-t&d-losses.html) | K426: - | L426: -
B427: Emisiones indirectas por energía importada | C427: 2.2 Pérdidas por T&D | D427: Pérdidas por T&D | E427: Sistema Eléctrico de Los Lagos | F427: 2025 | G427: MWh | H427: {=_xlfn.XLOOKUP(E427&F427&G427,'2.2 Perdidas por T&D'!B:B&'2.2 Perdidas por T&D'!C:C&'2.2 Perdidas por T&D'!D:D,'2.2 Perdidas por T&D'!E:E,"-")} -> PENDIENTE | I427: {=_xlfn.XLOOKUP(E427&F427&G427,'2.2 Perdidas por T&D'!B:B&'2.2 Perdidas por T&D'!C:C&'2.2 Perdidas por T&D'!D:D,'2.2 Perdidas por T&D'!F:F,"-")} -> kgCO2e/MWh | J427: {=_xlfn.XLOOKUP(E427&F427&G427,'2.2 Perdidas por T&D'!B:B&'2.2 Perdidas por T&D'!C:C&'2.2 Perdidas por T&D'!D:D,'2.2 Perdidas por T&D'!G:G,"-")} -> Base de Información de Eficiencia Energética - CEPAL- Enerdata, 2018 (https://biee-cepal.enerdata.net/es/datamapper/rate-of-electricity-t&d-losses.html)
B428: Emisiones indirectas por energía importada | C428: 2.2 Pérdidas por T&D | D428: Pérdidas por T&D | E428: Sistema Eléctrico de Los Lagos | F428: 2025 | G428: GWh | H428: {=_xlfn.XLOOKUP(E428&F428&G428,'2.2 Perdidas por T&D'!B:B&'2.2 Perdidas por T&D'!C:C&'2.2 Perdidas por T&D'!D:D,'2.2 Perdidas por T&D'!E:E,"-")} -> PENDIENTE | I428: {=_xlfn.XLOOKUP(E428&F428&G428,'2.2 Perdidas por T&D'!B:B&'2.2 Perdidas por T&D'!C:C&'2.2 Perdidas por T&D'!D:D,'2.2 Perdidas por T&D'!F:F,"-")} -> kgCO2e/GWh | J428: {=_xlfn.XLOOKUP(E428&F428&G428,'2.2 Perdidas por T&D'!B:B&'2.2 Perdidas por T&D'!C:C&'2.2 Perdidas por T&D'!D:D,'2.2 Perdidas por T&D'!G:G,"-")} -> Base de Información de Eficiencia Energética - CEPAL- Enerdata, 2018 (https://biee-cepal.enerdata.net/es/datamapper/rate-of-electricity-t&d-losses.html)
B429: Emisiones indirectas por energía importada | C429: 2.2 Pérdidas por T&D | D429: Pérdidas por T&D | E429: Sistema Eléctrico de Los Lagos | F429: 2025 | G429: kWh | H429: {=_xlfn.XLOOKUP(E429&F429&G429,'2.2 Perdidas por T&D'!B:B&'2.2 Perdidas por T&D'!C:C&'2.2 Perdidas por T&D'!D:D,'2.2 Perdidas por T&D'!E:E,"-")} -> PENDIENTE | I429: {=_xlfn.XLOOKUP(E429&F429&G429,'2.2 Perdidas por T&D'!B:B&'2.2 Perdidas por T&D'!C:C&'2.2 Perdidas por T&D'!D:D,'2.2 Perdidas por T&D'!F:F,"-")} -> kgCO2e/kWh | J429: {=_xlfn.XLOOKUP(E429&F429&G429,'2.2 Perdidas por T&D'!B:B&'2.2 Perdidas por T&D'!C:C&'2.2 Perdidas por T&D'!D:D,'2.2 Perdidas por T&D'!G:G,"-")} -> Base de Información de Eficiencia Energética - CEPAL- Enerdata, 2018 (https://biee-cepal.enerdata.net/es/datamapper/rate-of-electricity-t&d-losses.html)
B430: Emisiones indirectas por energía importada | C430: 2.3 Adq. de otras energías | D430: Vapor/Calefacción/Refrigeración/Aire comprimido | E430: Petróleo 2 (Diésel) | F430: - | G430: metros cúbicos | H430: {=_xlfn.XLOOKUP(E430&G430,'2.3 Adq. de otras energías'!$B$16:$B$24&'2.3 Adq. de otras energías'!$F$16:$F$24,'2.3 Adq. de otras energías'!$AB$16:$AB$24,"-")} -> 2707.3954 | I430: {=_xlfn.XLOOKUP(E430&G430,'2.3 Adq. de otras energías'!$B$16:$B$24&'2.3 Adq. de otras energías'!$F$16:$F$24,'2.3 Adq. de otras energías'!$AC$16:$AC$24,"-")} -> kgCO2e/metros cúbicos | J430: {=_xlfn.XLOOKUP(E430&G430,'2.3 Adq. de otras energías'!$B$16:$B$24&'2.3 Adq. de otras energías'!$F$16:$F$24,'2.3 Adq. de otras energías'!$AD$16:$AD$24,"-")} -> IPCC 2006 (vol2; chapter 2) , Table 2.2 | K430: {=_xlfn.XLOOKUP(E430&G430,'2.3 Adq. de otras energías'!$B$16:$B$24&'2.3 Adq. de otras energías'!$F$16:$F$24,'2.3 Adq. de otras energías'!$AE$16:$AE$24,"-")} -> CNE BNE 2024 | L430: {=_xlfn.XLOOKUP(E430&G430,'2.3 Adq. de otras energías'!$B$16:$B$24&'2.3 Adq. de otras energías'!$F$16:$F$24,'2.3 Adq. de otras energías'!$AF$16:$AF$24,"-")} -> -
B431: Emisiones indirectas por energía importada | C431: 2.3 Adq. de otras energías | D431: Vapor/Calefacción/Refrigeración/Aire comprimido | E431: Petróleo 2 (Diésel) | F431: - | G431: litros | H431: {=_xlfn.XLOOKUP(E431&G431,'2.3 Adq. de otras energías'!$B$16:$B$24&'2.3 Adq. de otras energías'!$F$16:$F$24,'2.3 Adq. de otras energías'!$AB$16:$AB$24,"-")} -> 2.7073954 | I431: {=_xlfn.XLOOKUP(E431&G431,'2.3 Adq. de otras energías'!$B$16:$B$24&'2.3 Adq. de otras energías'!$F$16:$F$24,'2.3 Adq. de otras energías'!$AC$16:$AC$24,"-")} -> kgCO2e/litros | J431: {=_xlfn.XLOOKUP(E431&G431,'2.3 Adq. de otras energías'!$B$16:$B$24&'2.3 Adq. de otras energías'!$F$16:$F$24,'2.3 Adq. de otras energías'!$AD$16:$AD$24,"-")} -> IPCC 2006 (vol2; chapter 2) , Table 2.2 | K431: {=_xlfn.XLOOKUP(E431&G431,'2.3 Adq. de otras energías'!$B$16:$B$24&'2.3 Adq. de otras energías'!$F$16:$F$24,'2.3 Adq. de otras energías'!$AE$16:$AE$24,"-")} -> CNE BNE 2024 | L431: {=_xlfn.XLOOKUP(E431&G431,'2.3 Adq. de otras energías'!$B$16:$B$24&'2.3 Adq. de otras energías'!$F$16:$F$24,'2.3 Adq. de otras energías'!$AF$16:$AF$24,"-")} -> -
B432: Emisiones indirectas por energía importada | C432: 2.3 Adq. de otras energías | D432: Vapor/Calefacción/Refrigeración/Aire comprimido | E432: Gas licuado de petróleo | F432: - | G432: metros cúbicos | H432: {=_xlfn.XLOOKUP(E432&G432,'2.3 Adq. de otras energías'!$B$16:$B$24&'2.3 Adq. de otras energías'!$F$16:$F$24,'2.3 Adq. de otras energías'!$AB$16:$AB$24,"-")} -> 1671.6994 | I432: {=_xlfn.XLOOKUP(E432&G432,'2.3 Adq. de otras energías'!$B$16:$B$24&'2.3 Adq. de otras energías'!$F$16:$F$24,'2.3 Adq. de otras energías'!$AC$16:$AC$24,"-")} -> kgCO2e/metros cúbicos | J432: {=_xlfn.XLOOKUP(E432&G432,'2.3 Adq. de otras energías'!$B$16:$B$24&'2.3 Adq. de otras energías'!$F$16:$F$24,'2.3 Adq. de otras energías'!$AD$16:$AD$24,"-")} -> IPCC 2006 (vol2; chapter 2) , Table 2.2 | K432: {=_xlfn.XLOOKUP(E432&G432,'2.3 Adq. de otras energías'!$B$16:$B$24&'2.3 Adq. de otras energías'!$F$16:$F$24,'2.3 Adq. de otras energías'!$AE$16:$AE$24,"-")} -> CNE BNE 2024 | L432: {=_xlfn.XLOOKUP(E432&G432,'2.3 Adq. de otras energías'!$B$16:$B$24&'2.3 Adq. de otras energías'!$F$16:$F$24,'2.3 Adq. de otras energías'!$AF$16:$AF$24,"-")} -> -
B433: Emisiones indirectas por energía importada | C433: 2.3 Adq. de otras energías | D433: Vapor/Calefacción/Refrigeración/Aire comprimido | E433: Gas licuado de petróleo | F433: - | G433: litros | H433: {=_xlfn.XLOOKUP(E433&G433,'2.3 Adq. de otras energías'!$B$16:$B$24&'2.3 Adq. de otras energías'!$F$16:$F$24,'2.3 Adq. de otras energías'!$AB$16:$AB$24,"-")} -> 1.6716994 | I433: {=_xlfn.XLOOKUP(E433&G433,'2.3 Adq. de otras energías'!$B$16:$B$24&'2.3 Adq. de otras energías'!$F$16:$F$24,'2.3 Adq. de otras energías'!$AC$16:$AC$24,"-")} -> kgCO2e/litros | J433: {=_xlfn.XLOOKUP(E433&G433,'2.3 Adq. de otras energías'!$B$16:$B$24&'2.3 Adq. de otras energías'!$F$16:$F$24,'2.3 Adq. de otras energías'!$AD$16:$AD$24,"-")} -> IPCC 2006 (vol2; chapter 2) , Table 2.2 | K433: {=_xlfn.XLOOKUP(E433&G433,'2.3 Adq. de otras energías'!$B$16:$B$24&'2.3 Adq. de otras energías'!$F$16:$F$24,'2.3 Adq. de otras energías'!$AE$16:$AE$24,"-")} -> CNE BNE 2024 | L433: {=_xlfn.XLOOKUP(E433&G433,'2.3 Adq. de otras energías'!$B$16:$B$24&'2.3 Adq. de otras energías'!$F$16:$F$24,'2.3 Adq. de otras energías'!$AF$16:$AF$24,"-")} -> -
B434: Emisiones indirectas por energía importada | C434: 2.3 Adq. de otras energías | D434: Vapor/Calefacción/Refrigeración/Aire comprimido | E434: Gas natural | F434: - | G434: metros cúbicos | H434: {=_xlfn.XLOOKUP(E434&G434,'2.3 Adq. de otras energías'!$B$16:$B$24&'2.3 Adq. de otras energías'!$F$16:$F$24,'2.3 Adq. de otras energías'!$AB$16:$AB$24,"-")} -> 1.9765266 | I434: {=_xlfn.XLOOKUP(E434&G434,'2.3 Adq. de otras energías'!$B$16:$B$24&'2.3 Adq. de otras energías'!$F$16:$F$24,'2.3 Adq. de otras energías'!$AC$16:$AC$24,"-")} -> kgCO2e/metros cúbicos | J434: {=_xlfn.XLOOKUP(E434&G434,'2.3 Adq. de otras energías'!$B$16:$B$24&'2.3 Adq. de otras energías'!$F$16:$F$24,'2.3 Adq. de otras energías'!$AD$16:$AD$24,"-")} -> IPCC 2006 (vol2; chapter 2) , Table 2.2 | K434: {=_xlfn.XLOOKUP(E434&G434,'2.3 Adq. de otras energías'!$B$16:$B$24&'2.3 Adq. de otras energías'!$F$16:$F$24,'2.3 Adq. de otras energías'!$AE$16:$AE$24,"-")} -> CNE BNE 2024 | L434: {=_xlfn.XLOOKUP(E434&G434,'2.3 Adq. de otras energías'!$B$16:$B$24&'2.3 Adq. de otras energías'!$F$16:$F$24,'2.3 Adq. de otras energías'!$AF$16:$AF$24,"-")} -> DEFRA 2025 (Fuel properties), Natural Gas
B435: Emisiones indirectas por energía importada | C435: 2.3 Adq. de otras energías | D435: Vapor/Calefacción/Refrigeración/Aire comprimido | E435: Gasolina | F435: - | G435: metros cúbicos | H435: {=_xlfn.XLOOKUP(E435&G435,'2.3 Adq. de otras energías'!$B$16:$B$24&'2.3 Adq. de otras energías'!$F$16:$F$24,'2.3 Adq. de otras energías'!$AB$16:$AB$24,"-")} -> 2261.5184 | I435: {=_xlfn.XLOOKUP(E435&G435,'2.3 Adq. de otras energías'!$B$16:$B$24&'2.3 Adq. de otras energías'!$F$16:$F$24,'2.3 Adq. de otras energías'!$AC$16:$AC$24,"-")} -> kgCO2e/metros cúbicos | J435: {=_xlfn.XLOOKUP(E435&G435,'2.3 Adq. de otras energías'!$B$16:$B$24&'2.3 Adq. de otras energías'!$F$16:$F$24,'2.3 Adq. de otras energías'!$AD$16:$AD$24,"-")} -> IPCC 2006 (vol2; chapter 2) , Table 2.2 | K435: {=_xlfn.XLOOKUP(E435&G435,'2.3 Adq. de otras energías'!$B$16:$B$24&'2.3 Adq. de otras energías'!$F$16:$F$24,'2.3 Adq. de otras energías'!$AE$16:$AE$24,"-")} -> CNE BNE 2024 | L435: {=_xlfn.XLOOKUP(E435&G435,'2.3 Adq. de otras energías'!$B$16:$B$24&'2.3 Adq. de otras energías'!$F$16:$F$24,'2.3 Adq. de otras energías'!$AF$16:$AF$24,"-")} -> -
B436: Emisiones indirectas por energía importada | C436: 2.3 Adq. de otras energías | D436: Vapor/Calefacción/Refrigeración/Aire comprimido | E436: Gasolina | F436: - | G436: litros | H436: {=_xlfn.XLOOKUP(E436&G436,'2.3 Adq. de otras energías'!$B$16:$B$24&'2.3 Adq. de otras energías'!$F$16:$F$24,'2.3 Adq. de otras energías'!$AB$16:$AB$24,"-")} -> 2.2615184 | I436: {=_xlfn.XLOOKUP(E436&G436,'2.3 Adq. de otras energías'!$B$16:$B$24&'2.3 Adq. de otras energías'!$F$16:$F$24,'2.3 Adq. de otras energías'!$AC$16:$AC$24,"-")} -> kgCO2e/litros | J436: {=_xlfn.XLOOKUP(E436&G436,'2.3 Adq. de otras energías'!$B$16:$B$24&'2.3 Adq. de otras energías'!$F$16:$F$24,'2.3 Adq. de otras energías'!$AD$16:$AD$24,"-")} -> IPCC 2006 (vol2; chapter 2) , Table 2.2 | K436: {=_xlfn.XLOOKUP(E436&G436,'2.3 Adq. de otras energías'!$B$16:$B$24&'2.3 Adq. de otras energías'!$F$16:$F$24,'2.3 Adq. de otras energías'!$AE$16:$AE$24,"-")} -> CNE BNE 2024 | L436: {=_xlfn.XLOOKUP(E436&G436,'2.3 Adq. de otras energías'!$B$16:$B$24&'2.3 Adq. de otras energías'!$F$16:$F$24,'2.3 Adq. de otras energías'!$AF$16:$AF$24,"-")} -> -
B437: Emisiones indirectas por energía importada | C437: 2.3 Adq. de otras energías | D437: Vapor/Calefacción/Refrigeración/Aire comprimido | E437: Petróleo 6 | F437: - | G437: metros cúbicos | H437: {=_xlfn.XLOOKUP(E437&G437,'2.3 Adq. de otras energías'!$B$16:$B$24&'2.3 Adq. de otras energías'!$F$16:$F$24,'2.3 Adq. de otras energías'!$AB$16:$AB$24,"-")} -> 3064.2856 | I437: {=_xlfn.XLOOKUP(E437&G437,'2.3 Adq. de otras energías'!$B$16:$B$24&'2.3 Adq. de otras energías'!$F$16:$F$24,'2.3 Adq. de otras energías'!$AC$16:$AC$24,"-")} -> kgCO2e/metros cúbicos | J437: {=_xlfn.XLOOKUP(E437&G437,'2.3 Adq. de otras energías'!$B$16:$B$24&'2.3 Adq. de otras energías'!$F$16:$F$24,'2.3 Adq. de otras energías'!$AD$16:$AD$24,"-")} -> IPCC 2006 (vol2; chapter 2) , Table 2.2 | K437: {=_xlfn.XLOOKUP(E437&G437,'2.3 Adq. de otras energías'!$B$16:$B$24&'2.3 Adq. de otras energías'!$F$16:$F$24,'2.3 Adq. de otras energías'!$AE$16:$AE$24,"-")} -> CNE BNE 2024 | L437: {=_xlfn.XLOOKUP(E437&G437,'2.3 Adq. de otras energías'!$B$16:$B$24&'2.3 Adq. de otras energías'!$F$16:$F$24,'2.3 Adq. de otras energías'!$AF$16:$AF$24,"-")} -> -
...

Sheet CONTROL DE CAMBIOS
B8: Versión | C8: Categoría (Hoja) | D8: Subcategoría | E8: Cambios realizados
B9: 1 | C9: 2.1 Electricidad | D9: Sistema Electrico Nacional | E9: Se actualiza de manera retoactiva los factores de emisión desde 2021 a 2025, según información de Energía Abierta (Ministerio de Energía)
B10: 1 | C10: 2.1 Electricidad | D10: Sistemas Electricos Medianos | E10: En espera de publicación de FE para sistemas medianos desde Energía Abierta (Ministerio de Energía)
B11: 1 | C11: 2.2 Perdidas por T&D | D11: Sistema Electrico Nacional | E11: Se actualiza de manera retoactiva los factores de emisión desde 2021 a 2025, según información de Energía Abierta (Ministerio de Energía)
B12: 1 | C12: 2.2 Perdidas por T&D | D12: Sistemas Electricos Medianos | E12: En espera de publicación de FE para sistemas medianos desde Energía Abierta (Ministerio de Energía)
B13: 1 | C13: 1.1 y 1.2CUADROA1 - BNE 2024 | D13: - | E13: Se actualiza información de Densidades y Poderes Caloríficos de combustibles (sin variaciones respecto a FE 2024)
B14: 1 | C14: 3.1 Adq. Bienes y servicios | D14: - | E14: Se actualizan factores de emisión DEFRA 2025
B15: 1 | C15: 3.2 Transporte de personas | D15: - | E15: Se actualizan factores de emisión DEFRA 2025
B16: 1 | C16: 3.3 Transporte de carga | D16: - | E16: Se actualizan factores de emisión DEFRA 2025
B17: 1 | C17: 3.4 Transporte de residuos | D17: - | E17: Se actualizan factores de emisión DEFRA 2025
B18: 1 | C18: 3.6 Trat. yo disp. de residuos | D18: - | E18: Se actualizan factores de emisión DEFRA 2025
B19: 2 | C19: 2.1 Electricidad | D19: Sistema Electrico Nacional Sistemas Electricos Medianos | E19: Se cambia el nombre de la fuente de origen de los factores para indicar que se utiliza AR5
B20: 2 | C20: 3.2 Transporte de personas | D20: Vehículo eléctrico y Van Electrico | E20: Se actualizan factores de emisión, en base a cálculo realizado por el Programa HuellaChile

Sheet 1.1 Combustión estacionaria
A1: Volver al INICIO
A2: Volver al RESUMEN | B2: Compuesto | C2: Valor | D2: Unidad | E2: Fuente
B3: Dióxido de Carbono (CO2) | C3: ='1.4 AR5 CH8 T8.A.1'!H4 -> 1 | D3: - | E3: AR5
B4: Metano (CH4) | C4: ='1.4 AR5 CH8 T8.A.1'!H5 -> 28 | D4: - | E4: AR5
B5: Óxido Nitroso (N2O) | C5: ='1.4 AR5 CH8 T8.A.1'!H7 -> 265 | D5: - | E5: AR5
B6: 1 kcal | C6: 4.1868 | D6: kJ | E6: IPCC Anex II: Metrics & Methodology
B7: 1 TJ | C7: 1000000000 | D7: kJ
B8: Combustibles sólidos y líquidos | C8: 0.95 | D8: - | E8: IPCC V2 CH1 (int. de confianza 95%)
B9: Combustibles gaseosos | C9: 0.9 | D9: - | E9: IPCC V2 CH1 (int. de confianza 90%)
B11: Huella Organizacional
B12: Emisiones directas
B13: Tipo de fuente: Caldera/Generador/General
T14: kg GEI/unidad | X14: CO2e/unidad
B15: Nombre en HuellaChile | C15: Nombre en BNE 2020 | D15: Nombre en IPCC ESP | E15: Nombre en IPCC EN | F15: Unidad del dato de actividad | G15: Estado del combustible | H15: CO2 kgCO2/TJ | I15: CH4 kgCH4/TJ | J15: N2O kgN2O/TJ | K15: Densidad | L15: Unidad | M15: Poder Calorífico Superior (PCS) | N15: Unidad PCS | O15: Poder Calorífico Inferior (PCI) | P15: Unidad PCI | Q15: Multiplica densidad | R15: PCI | S15: Unidad | T15: CO2 | U15: CH4 | V15: N2O | W15: Unidad | X15: CO2 | Y15: CH4 | Z15: N2O | AA15: Unidad | AB15: kgCO2e total | AC15: Unidad | AD15: Fuente 1 | AE15: Fuente 2 | AF15: Otras fuentes
B16: Nafta | C16: Nafta | D16: Nafta | E16: Naphtha | F16: metros cúbicos | G16: Líquido | H16: ='1.1 V2 CH2 T2.4'!$F$18 -> 73300 | I16: ='1.1 V2 CH2 T2.4'!$I$18 -> 10 | J16: ='1.1 V2 CH2 T2.4'!$L$18 -> 0.6 | K16: ='1.1 y 1.2CUADROA1 - BNE 2024'!$C$14 -> 0.7 | L16: t/m3 | M16: ='1.1 y 1.2CUADROA1 - BNE 2024'!D$14 -> 11500 | N16: ='1.1 y 1.2CUADROA1 - BNE 2024'!E$14 -> kCal/kg | O16: =IF(G16="Gaseoso", M16*$C$9, M16*$C$8) -> 10925 | P16: =N16 -> kCal/kg | Q16: Sí | R16: =O16*$C$6/$C$7*IF(Q16="Sí",K16*1000,1) -> 0.032018553 | S16: =IF(Q16="Sí","TJ/m3", IF(N16="kcal/m3", "TJ/m3","TJ/kg")) -> TJ/m3 | T16: =H16*$R16 -> 2346.9599 | U16: =I16*$R16 -> 0.32018553 | V16: =J16*$R16 -> 0.019211132 | W16: =IF(S16="TJ/m3", "kg GEI/m3", "kg GEI/kg") -> kg GEI/m3 | X16: =$C$3*T16 -> 2346.9599 | Y16: =U16*$C$4 -> 8.9651948 | Z16: =V16*$C$5 -> 5.0909499 | AA16: =IF(S16="TJ/m3", "kg CO2e/m3", "kg CO2e/kg") -> kg CO2e/m3 | AB16: =SUM(X16:Z16)*IF(AND(F16="gramos",S16="TJ/m3")=TRUE(),1/(K16*1000000), IF(AND(F16="gramos",S16="TJ/kg")=TRUE(),1/(1000), IF(AND(F16="kilogramos",S16="TJ/m3")=TRUE(),1/(K16*1000), IF(AND(F16="toneladas",S16="TJ/m3")=TRUE(),1/K16, IF(AND(F16="toneladas",S16="TJ/kg")=TRUE(),1000, IF(AND(S16="TJ/m3",F16="litros")=TRUE(),1/1000, IF(AND(S16="TJ/kg",F16="litros")=TRUE(),K16/1000,1))))))) -> 2361.0161 | AC16: ="kgCO2e/"&F16 -> kgCO2e/metros cúbicos | AD16: IPCC 2006 (vol2; chapter 2) , Table 2.4 | AE16: CNE BNE 2024 | AF16: -
B17: Nafta | C17: Nafta | D17: Nafta | E17: Naphtha | F17: litros | G17: Líquido | H17: ='1.1 V2 CH2 T2.4'!$F$18 -> 73300 | I17: ='1.1 V2 CH2 T2.4'!$I$18 -> 10 | J17: ='1.1 V2 CH2 T2.4'!$L$18 -> 0.6 | K17: ='1.1 y 1.2CUADROA1 - BNE 2024'!$C$14 -> 0.7 | L17: t/m3 | M17: ='1.1 y 1.2CUADROA1 - BNE 2024'!D$14 -> 11500 | N17: ='1.1 y 1.2CUADROA1 - BNE 2024'!E$14 -> kCal/kg | O17: =IF(G17="Gaseoso", M17*$C$9, M17*$C$8) -> 10925 | P17: =N17 -> kCal/kg | Q17: Sí | R17: =O17*$C$6/$C$7*IF(Q17="Sí",K17*1000,1) -> 0.032018553 | S17: =IF(Q17="Sí","TJ/m3", IF(N17="kcal/m3", "TJ/m3","TJ/kg")) -> TJ/m3 | T17: =H17*$R17 -> 2346.9599 | U17: =I17*$R17 -> 0.32018553 | V17: =J17*$R17 -> 0.019211132 | W17: =IF(S17="TJ/m3", "kg GEI/m3", "kg GEI/kg") -> kg GEI/m3 | X17: =$C$3*T17 -> 2346.9599 | Y17: =U17*$C$4 -> 8.9651948 | Z17: =V17*$C$5 -> 5.0909499 | AA17: =IF(S17="TJ/m3", "kg CO2e/m3", "kg CO2e/kg") -> kg CO2e/m3 | AB17: =SUM(X17:Z17)*IF(AND(F17="gramos",S17="TJ/m3")=TRUE(),1/(K17*1000000), IF(AND(F17="gramos",S17="TJ/kg")=TRUE(),1/(1000), IF(AND(F17="kilogramos",S17="TJ/m3")=TRUE(),1/(K17*1000), IF(AND(F17="toneladas",S17="TJ/m3")=TRUE(),1/K17, IF(AND(F17="toneladas",S17="TJ/kg")=TRUE(),1000, IF(AND(S17="TJ/m3",F17="litros")=TRUE(),1/1000, IF(AND(S17="TJ/kg",F17="litros")=TRUE(),K17/1000,1))))))) -> 2.3610161 | AC17: ="kgCO2e/"&F17 -> kgCO2e/litros | AD17: IPCC 2006 (vol2; chapter 2) , Table 2.4 | AE17: CNE BNE 2024 | AF17: -
B18: Carbón metalúrgico | C18: Carbón | D18: Carbón de coque | E18: Coking Coal | F18: toneladas | G18: Sólido | H18: ='1.1 V2 CH2 T2.4'!$F$29 -> 94600 | I18: ='1.1 V2 CH2 T2.4'!$I$29 -> 10 | J18: ='1.1 V2 CH2 T2.4'!$L$29 -> 1.5 | M18: ='1.1 y 1.2CUADROA1 - BNE 2024'!D$26 -> 7000 | N18: ='1.1 y 1.2CUADROA1 - BNE 2024'!E$23 -> kCal/kg | O18: =IF(G18="Gaseoso", M18*$C$9, M18*$C$8) -> 6650 | P18: =N18 -> kCal/kg | Q18: No | R18: =O18*$C$6/$C$7*IF(Q18="Sí",K18*1000,1) -> 2.784222e-05 | S18: =IF(Q18="Sí","TJ/m3", IF(N18="kcal/m3", "TJ/m3","TJ/kg")) -> TJ/kg | T18: =H18*$R18 -> 2.633874 | U18: =I18*$R18 -> 0.0002784222 | V18: =J18*$R18 -> 4.176333e-05 | W18: =IF(S18="TJ/m3", "kg GEI/m3", "kg GEI/kg") -> kg GEI/kg | X18: =$C$3*T18 -> 2.633874 | Y18: =U18*$C$4 -> 0.0077958216 | Z18: =V18*$C$5 -> 0.011067282 | AA18: =IF(S18="TJ/m3", "kg CO2e/m3", "kg CO2e/kg") -> kg CO2e/kg | AB18: =SUM(X18:Z18)*IF(AND(F18="gramos",S18="TJ/m3")=TRUE(),1/(K18*1000000), IF(AND(F18="gramos",S18="TJ/kg")=TRUE(),1/(1000), IF(AND(F18="kilogramos",S18="TJ/m3")=TRUE(),1/(K18*1000), IF(AND(F18="toneladas",S18="TJ/m3")=TRUE(),1/K18, IF(AND(F18="toneladas",S18="TJ/kg")=TRUE(),1000, IF(AND(S18="TJ/m3",F18="litros")=TRUE(),1/1000, IF(AND(S18="TJ/kg",F18="litros")=TRUE(),K18/1000,1))))))) -> 2652.7371 | AC18: ="kgCO2e/"&F18 -> kgCO2e/toneladas | AD18: IPCC 2006 (vol2; chapter 2) , Table 2.4 | AE18: CNE BNE 2024 | AF18: -
B19: Carbón metalúrgico | C19: Carbón | D19: Carbón de coque | E19: Coking Coal | F19: kilogramos | G19: Sólido | H19: ='1.1 V2 CH2 T2.4'!$F$29 -> 94600 | I19: ='1.1 V2 CH2 T2.4'!$I$29 -> 10 | J19: ='1.1 V2 CH2 T2.4'!$L$29 -> 1.5 | M19: ='1.1 y 1.2CUADROA1 - BNE 2024'!D$26 -> 7000 | N19: ='1.1 y 1.2CUADROA1 - BNE 2024'!E$23 -> kCal/kg | O19: =IF(G19="Gaseoso", M19*$C$9, M19*$C$8) -> 6650 | P19: =N19 -> kCal/kg | Q19: No | R19: =O19*$C$6/$C$7*IF(Q19="Sí",K19*1000,1) -> 2.784222e-05 | S19: =IF(Q19="Sí","TJ/m3", IF(N19="kcal/m3", "TJ/m3","TJ/kg")) -> TJ/kg | T19: =H19*$R19 -> 2.633874 | U19: =I19*$R19 -> 0.0002784222 | V19: =J19*$R19 -> 4.176333e-05 | W19: =IF(S19="TJ/m3", "kg GEI/m3", "kg GEI/kg") -> kg GEI/kg | X19: =$C$3*T19 -> 2.633874 | Y19: =U19*$C$4 -> 0.0077958216 | Z19: =V19*$C$5 -> 0.011067282 | AA19: =IF(S19="TJ/m3", "kg CO2e/m3", "kg CO2e/kg") -> kg CO2e/kg | AB19: =SUM(X19:Z19)*IF(AND(F19="gramos",S19="TJ/m3")=TRUE(),1/(K19*1000000), IF(AND(F19="gramos",S19="TJ/kg")=TRUE(),1/(1000), IF(AND(F19="kilogramos",S19="TJ/m3")=TRUE(),1/(K19*1000), IF(AND(F19="toneladas",S19="TJ/m3")=TRUE(),1/K19, IF(AND(F19="toneladas",S19="TJ/kg")=TRUE(),1000, IF(AND(S19="TJ/m3",F19="litros")=TRUE(),1/1000, IF(AND(S19="TJ/kg",F19="litros")=TRUE(),K19/1000,1))))))) -> 2.6527371 | AC19: ="kgCO2e/"&F19 -> kgCO2e/kilogramos | AD19: IPCC 2006 (vol2; chapter 2) , Table 2.4 | AE19: CNE BNE 2024 | AF19: -
B20: Carbón metalúrgico | C20: Carbón | D20: Carbón de coque | E20: Coking Coal | F20: gramos | G20: Sólido | H20: ='1.1 V2 CH2 T2.4'!$F$29 -> 94600 | I20: ='1.1 V2 CH2 T2.4'!$I$29 -> 10 | J20: ='1.1 V2 CH2 T2.4'!$L$29 -> 1.5 | M20: ='1.1 y 1.2CUADROA1 - BNE 2024'!D$26 -> 7000 | N20: ='1.1 y 1.2CUADROA1 - BNE 2024'!E$23 -> kCal/kg | O20: =IF(G20="Gaseoso", M20*$C$9, M20*$C$8) -> 6650 | P20: =N20 -> kCal/kg | Q20: No | R20: =O20*$C$6/$C$7*IF(Q20="Sí",K20*1000,1) -> 2.784222e-05 | S20: =IF(Q20="Sí","TJ/m3", IF(N20="kcal/m3", "TJ/m3","TJ/kg")) -> TJ/kg | T20: =H20*$R20 -> 2.633874 | U20: =I20*$R20 -> 0.0002784222 | V20: =J20*$R20 -> 4.176333e-05 | W20: =IF(S20="TJ/m3", "kg GEI/m3", "kg GEI/kg") -> kg GEI/kg | X20: =$C$3*T20 -> 2.633874 | Y20: =U20*$C$4 -> 0.0077958216 | Z20: =V20*$C$5 -> 0.011067282 | AA20: =IF(S20="TJ/m3", "kg CO2e/m3", "kg CO2e/kg") -> kg CO2e/kg | AB20: =SUM(X20:Z20)*IF(AND(F20="gramos",S20="TJ/m3")=TRUE(),1/(K20*1000000), IF(AND(F20="gramos",S20="TJ/kg")=TRUE(),1/(1000), IF(AND(F20="kilogramos",S20="TJ/m3")=TRUE(),1/(K20*1000), IF(AND(F20="toneladas",S20="TJ/m3")=TRUE(),1/K20, IF(AND(F20="toneladas",S20="TJ/kg")=TRUE(),1000, IF(AND(S20="TJ/m3",F20="litros")=TRUE(),1/1000, IF(AND(S20="TJ/kg",F20="litros")=TRUE(),K20/1000,1))))))) -> 0.0026527371 | AC20: ="kgCO2e/"&F20 -> kgCO2e/gramos | AD20: IPCC 2006 (vol2; chapter 2) , Table 2.4 | AE20: CNE BNE 2024 | AF20: -
B21: Carbón térmico | C21: Carbón | D21: Otro carbón bituminoso | E21: Other Bituminous Coal | F21: toneladas | G21: Sólido | H21: ='1.1 V2 CH2 T2.4'!$F$30 -> 94600 | I21: ='1.1 V2 CH2 T2.4'!$I$30 -> 10 | J21: ='1.1 V2 CH2 T2.4'!$L$30 -> 1.5 | M21: ='1.1 y 1.2CUADROA1 - BNE 2024'!D$26 -> 7000 | N21: ='1.1 y 1.2CUADROA1 - BNE 2024'!E$23 -> kCal/kg | O21: =IF(G21="Gaseoso", M21*$C$9, M21*$C$8) -> 6650 | P21: =N21 -> kCal/kg | Q21: No | R21: =O21*$C$6/$C$7*IF(Q21="Sí",K21*1000,1) -> 2.784222e-05 | S21: =IF(Q21="Sí","TJ/m3", IF(N21="kcal/m3", "TJ/m3","TJ/kg")) -> TJ/kg | T21: =H21*$R21 -> 2.633874 | U21: =I21*$R21 -> 0.0002784222 | V21: =J21*$R21 -> 4.176333e-05 | W21: =IF(S21="TJ/m3", "kg GEI/m3", "kg GEI/kg") -> kg GEI/kg | X21: =$C$3*T21 -> 2.633874 | Y21: =U21*$C$4 -> 0.0077958216 | Z21: =V21*$C$5 -> 0.011067282 | AA21: =IF(S21="TJ/m3", "kg CO2e/m3", "kg CO2e/kg") -> kg CO2e/kg | AB21: =SUM(X21:Z21)*IF(AND(F21="gramos",S21="TJ/m3")=TRUE(),1/(K21*1000000), IF(AND(F21="gramos",S21="TJ/kg")=TRUE(),1/(1000), IF(AND(F21="kilogramos",S21="TJ/m3")=TRUE(),1/(K21*1000), IF(AND(F21="toneladas",S21="TJ/m3")=TRUE(),1/K21, IF(AND(F21="toneladas",S21="TJ/kg")=TRUE(),1000, IF(AND(S21="TJ/m3",F21="litros")=TRUE(),1/1000, IF(AND(S21="TJ/kg",F21="litros")=TRUE(),K21/1000,1))))))) -> 2652.7371 | AC21: ="kgCO2e/"&F21 -> kgCO2e/toneladas | AD21: IPCC 2006 (vol2; chapter 2) , Table 2.4 | AE21: CNE BNE 2024 | AF21: -
B22: Carbón térmico | C22: Carbón | D22: Otro carbón bituminoso | E22: Other Bituminous Coal | F22: kilogramos | G22: Sólido | H22: ='1.1 V2 CH2 T2.4'!$F$30 -> 94600 | I22: ='1.1 V2 CH2 T2.4'!$I$30 -> 10 | J22: ='1.1 V2 CH2 T2.4'!$L$30 -> 1.5 | M22: ='1.1 y 1.2CUADROA1 - BNE 2024'!D$26 -> 7000 | N22: ='1.1 y 1.2CUADROA1 - BNE 2024'!E$23 -> kCal/kg | O22: =IF(G22="Gaseoso", M22*$C$9, M22*$C$8) -> 6650 | P22: =N22 -> kCal/kg | Q22: No | R22: =O22*$C$6/$C$7*IF(Q22="Sí",K22*1000,1) -> 2.784222e-05 | S22: =IF(Q22="Sí","TJ/m3", IF(N22="kcal/m3", "TJ/m3","TJ/kg")) -> TJ/kg | T22: =H22*$R22 -> 2.633874 | U22: =I22*$R22 -> 0.0002784222 | V22: =J22*$R22 -> 4.176333e-05 | W22: =IF(S22="TJ/m3", "kg GEI/m3", "kg GEI/kg") -> kg GEI/kg | X22: =$C$3*T22 -> 2.633874 | Y22: =U22*$C$4 -> 0.0077958216 | Z22: =V22*$C$5 -> 0.011067282 | AA22: =IF(S22="TJ/m3", "kg CO2e/m3", "kg CO2e/kg") -> kg CO2e/kg | AB22: =SUM(X22:Z22)*IF(AND(F22="gramos",S22="TJ/m3")=TRUE(),1/(K22*1000000), IF(AND(F22="gramos",S22="TJ/kg")=TRUE(),1/(1000), IF(AND(F22="kilogramos",S22="TJ/m3")=TRUE(),1/(K22*1000), IF(AND(F22="toneladas",S22="TJ/m3")=TRUE(),1/K22, IF(AND(F22="toneladas",S22="TJ/kg")=TRUE(),1000, IF(AND(S22="TJ/m3",F22="litros")=TRUE(),1/1000, IF(AND(S22="TJ/kg",F22="litros")=TRUE(),K22/1000,1))))))) -> 2.6527371 | AC22: ="kgCO2e/"&F22 -> kgCO2e/kilogramos | AD22: IPCC 2006 (vol2; chapter 2) , Table 2.4 | AE22: CNE BNE 2024 | AF22: -
B23: Carbón térmico | C23: Carbón | D23: Otro carbón bituminoso | E23: Other Bituminous Coal | F23: gramos | G23: Sólido | H23: ='1.1 V2 CH2 T2.4'!$F$30 -> 94600 | I23: ='1.1 V2 CH2 T2.4'!$I$30 -> 10 | J23: ='1.1 V2 CH2 T2.4'!$L$30 -> 1.5 | M23: ='1.1 y 1.2CUADROA1 - BNE 2024'!D$26 -> 7000 | N23: ='1.1 y 1.2CUADROA1 - BNE 2024'!E$23 -> kCal/kg | O23: =IF(G23="Gaseoso", M23*$C$9, M23*$C$8) -> 6650 | P23: =N23 -> kCal/kg | Q23: No | R23: =O23*$C$6/$C$7*IF(Q23="Sí",K23*1000,1) -> 2.784222e-05 | S23: =IF(Q23="Sí","TJ/m3", IF(N23="kcal/m3", "TJ/m3","TJ/kg")) -> TJ/kg | T23: =H23*$R23 -> 2.633874 | U23: =I23*$R23 -> 0.0002784222 | V23: =J23*$R23 -> 4.176333e-05 | W23: =IF(S23="TJ/m3", "kg GEI/m3", "kg GEI/kg") -> kg GEI/kg | X23: =$C$3*T23 -> 2.633874 | Y23: =U23*$C$4 -> 0.0077958216 | Z23: =V23*$C$5 -> 0.011067282 | AA23: =IF(S23="TJ/m3", "kg CO2e/m3", "kg CO2e/kg") -> kg CO2e/kg | AB23: =SUM(X23:Z23)*IF(AND(F23="gramos",S23="TJ/m3")=TRUE(),1/(K23*1000000), IF(AND(F23="gramos",S23="TJ/kg")=TRUE(),1/(1000), IF(AND(F23="kilogramos",S23="TJ/m3")=TRUE(),1/(K23*1000), IF(AND(F23="toneladas",S23="TJ/m3")=TRUE(),1/K23, IF(AND(F23="toneladas",S23="TJ/kg")=TRUE(),1000, IF(AND(S23="TJ/m3",F23="litros")=TRUE(),1/1000, IF(AND(S23="TJ/kg",F23="litros")=TRUE(),K23/1000,1))))))) -> 0.0026527371 | AC23: ="kgCO2e/"&F23 -> kgCO2e/gramos | AD23: IPCC 2006 (vol2; chapter 2) , Table 2.4 | AE23: CNE BNE 2024 | AF23: -
B24: Gasolina | C24: Gasolina Motor | D24: Gasolina para motores | E24: Motor Gasoline | F24: metros cúbicos | G24: Líquido | H24: ='1.1 V2 CH2 T2.4'!$F$8 -> 69300 | I24: ='1.1 V2 CH2 T2.4'!$I$8 -> 10 | J24: ='1.1 V2 CH2 T2.4'!$L$8 -> 0.6 | K24: ='1.1 y 1.2CUADROA1 - BNE 2024'!$C$16 -> 0.73 | L24: t/m3 | M24: ='1.1 y 1.2CUADROA1 - BNE 2024'!D$16 -> 11200 | N24: ='1.1 y 1.2CUADROA1 - BNE 2024'!E$16 -> kCal/kg | O24: =IF(G24="Gaseoso", M24*$C$9, M24*$C$8) -> 10640 | P24: =N24 -> kCal/kg | Q24: Sí | R24: =O24*$C$6/$C$7*IF(Q24="Sí",K24*1000,1) -> 0.032519713 | S24: =IF(Q24="Sí","TJ/m3", IF(N24="kcal/m3", "TJ/m3","TJ/kg")) -> TJ/m3 | T24: =H24*$R24 -> 2253.6161 | U24: =I24*$R24 -> 0.32519713 | V24: =J24*$R24 -> 0.019511828 | W24: =IF(S24="TJ/m3", "kg GEI/m3", "kg GEI/kg") -> kg GEI/m3 | X24: =$C$3*T24 -> 2253.6161 | Y24: =U24*$C$4 -> 9.1055196 | Z24: =V24*$C$5 -> 5.1706344 | AA24: =IF(S24="TJ/m3", "kg CO2e/m3", "kg CO2e/kg") -> kg CO2e/m3 | AB24: =SUM(X24:Z24)*IF(AND(F24="gramos",S24="TJ/m3")=TRUE(),1/(K24*1000000), IF(AND(F24="gramos",S24="TJ/kg")=TRUE(),1/(1000), IF(AND(F24="kilogramos",S24="TJ/m3")=TRUE(),1/(K24*1000), IF(AND(F24="toneladas",S24="TJ/m3")=TRUE(),1/K24, IF(AND(F24="toneladas",S24="TJ/kg")=TRUE(),1000, IF(AND(S24="TJ/m3",F24="litros")=TRUE(),1/1000, IF(AND(S24="TJ/kg",F24="litros")=TRUE(),K24/1000,1))))))) -> 2267.8923 | AC24: ="kgCO2e/"&F24 -> kgCO2e/metros cúbicos | AD24: IPCC 2006 (vol2; chapter 2) , Table 2.4 | AE24: CNE BNE 2024 | AF24: -
B25: Gasolina | C25: Gasolina Motor | D25: Gasolina para motores | E25: Motor Gasoline | F25: litros | G25: Líquido | H25: ='1.1 V2 CH2 T2.4'!$F$8 -> 69300 | I25: ='1.1 V2 CH2 T2.4'!$I$8 -> 10 | J25: ='1.1 V2 CH2 T2.4'!$L$8 -> 0.6 | K25: ='1.1 y 1.2CUADROA1 - BNE 2024'!$C$16 -> 0.73 | L25: t/m3 | M25: ='1.1 y 1.2CUADROA1 - BNE 2024'!D$16 -> 11200 | N25: ='1.1 y 1.2CUADROA1 - BNE 2024'!E$16 -> kCal/kg | O25: =IF(G25="Gaseoso", M25*$C$9, M25*$C$8) -> 10640 | P25: =N25 -> kCal/kg | Q25: Sí | R25: =O25*$C$6/$C$7*IF(Q25="Sí",K25*1000,1) -> 0.032519713 | S25: =IF(Q25="Sí","TJ/m3", IF(N25="kcal/m3", "TJ/m3","TJ/kg")) -> TJ/m3 | T25: =H25*$R25 -> 2253.6161 | U25: =I25*$R25 -> 0.32519713 | V25: =J25*$R25 -> 0.019511828 | W25: =IF(S25="TJ/m3", "kg GEI/m3", "kg GEI/kg") -> kg GEI/m3 | X25: =$C$3*T25 -> 2253.6161 | Y25: =U25*$C$4 -> 9.1055196 | Z25: =V25*$C$5 -> 5.1706344 | AA25: =IF(S25="TJ/m3", "kg CO2e/m3", "kg CO2e/kg") -> kg CO2e/m3 | AB25: =SUM(X25:Z25)*IF(AND(F25="gramos",S25="TJ/m3")=TRUE(),1/(K25*1000000), IF(AND(F25="gramos",S25="TJ/kg")=TRUE(),1/(1000), IF(AND(F25="kilogramos",S25="TJ/m3")=TRUE(),1/(K25*1000), IF(AND(F25="toneladas",S25="TJ/m3")=TRUE(),1/K25, IF(AND(F25="toneladas",S25="TJ/kg")=TRUE(),1000, IF(AND(S25="TJ/m3",F25="litros")=TRUE(),1/1000, IF(AND(S25="TJ/kg",F25="litros")=TRUE(),K25/1000,1))))))) -> 2.2678923 | AC25: ="kgCO2e/"&F25 -> kgCO2e/litros | AD25: IPCC 2006 (vol2; chapter 2) , Table 2.4 | AE25: CNE BNE 2024 | AF25: -
B26: Gas de alto horno | C26: - | D26: Gas de alto horno | E26: Blast Furnace Gas | F26: toneladas | G26: Gaseoso | H26: ='1.1 V2 CH2 T2.4'!$F$41 -> 260000 | I26: ='1.1 V2 CH2 T2.4'!$I$41 -> 5 | J26: ='1.1 V2 CH2 T2.4'!$L$41 -> 0.1 | M26: =2.47*1000/C$6 -> 589.94936 | N26: kcal/kg | O26: =IF(G26="Gaseoso", M26*$C$9, M26*$C$8) -> 530.95443 | P26: =N26 -> kcal/kg | Q26: No | R26: =O26*$C$6/$C$7*IF(Q26="Sí",K26*1000,1) -> 2.223e-06 | S26: =IF(Q26="Sí","TJ/m3", IF(N26="kcal/m3", "TJ/m3","TJ/kg")) -> TJ/kg | T26: =H26*$R26 -> 0.57798 | U26: =I26*$R26 -> 1.1115e-05 | V26: =J26*$R26 -> 2.223e-07 | W26: =IF(S26="TJ/m3", "kg GEI/m3", "kg GEI/kg") -> kg GEI/kg | X26: =$C$3*T26 -> 0.57798 | Y26: =U26*$C$4 -> 0.00031122 | Z26: =V26*$C$5 -> 5.89095e-05 | AA26: =IF(S26="TJ/m3", "kg CO2e/m3", "kg CO2e/kg") -> kg CO2e/kg | AB26: =SUM(X26:Z26)*IF(AND(F26="gramos",S26="TJ/m3")=TRUE(),1/(K26*1000000), IF(AND(F26="gramos",S26="TJ/kg")=TRUE(),1/(1000), IF(AND(F26="kilogramos",S26="TJ/m3")=TRUE(),1/(K26*1000), IF(AND(F26="toneladas",S26="TJ/m3")=TRUE(),1/K26, IF(AND(F26="toneladas",S26="TJ/kg")=TRUE(),1000, IF(AND(S26="TJ/m3",F26="litros")=TRUE(),1/1000, IF(AND(S26="TJ/kg",F26="litros")=TRUE(),K26/1000,1))))))) -> 578.35013 | AC26: ="kgCO2e/"&F26 -> kgCO2e/toneladas | AD26: IPCC 2006 (vol2; chapter 2) , Table 2.4 | AE26: CNE BNE 2024 | AF26: IPCC 2006 (vol2; chapter 1) , Table 1.2
B27: Gas de alto horno | C27: - | D27: Gas de alto horno | E27: Blast Furnace Gas | F27: kilogramos | G27: Gaseoso | H27: ='1.1 V2 CH2 T2.4'!$F$41 -> 260000 | I27: ='1.1 V2 CH2 T2.4'!$I$41 -> 5 | J27: ='1.1 V2 CH2 T2.4'!$L$41 -> 0.1 | M27: =2.47*1000/C$6 -> 589.94936 | N27: kcal/kg | O27: =IF(G27="Gaseoso", M27*$C$9, M27*$C$8) -> 530.95443 | P27: =N27 -> kcal/kg | Q27: No | R27: =O27*$C$6/$C$7*IF(Q27="Sí",K27*1000,1) -> 2.223e-06 | S27: =IF(Q27="Sí","TJ/m3", IF(N27="kcal/m3", "TJ/m3","TJ/kg")) -> TJ/kg | T27: =H27*$R27 -> 0.57798 | U27: =I27*$R27 -> 1.1115e-05 | V27: =J27*$R27 -> 2.223e-07 | W27: =IF(S27="TJ/m3", "kg GEI/m3", "kg GEI/kg") -> kg GEI/kg | X27: =$C$3*T27 -> 0.57798 | Y27: =U27*$C$4 -> 0.00031122 | Z27: =V27*$C$5 -> 5.89095e-05 | AA27: =IF(S27="TJ/m3", "kg CO2e/m3", "kg CO2e/kg") -> kg CO2e/kg | AB27: =SUM(X27:Z27)*IF(AND(F27="gramos",S27="TJ/m3")=TRUE(),1/(K27*1000000), IF(AND(F27="gramos",S27="TJ/kg")=TRUE(),1/(1000), IF(AND(F27="kilogramos",S27="TJ/m3")=TRUE(),1/(K27*1000), IF(AND(F27="toneladas",S27="TJ/m3")=TRUE(),1/K27, IF(AND(F27="toneladas",S27="TJ/kg")=TRUE(),1000, IF(AND(S27="TJ/m3",F27="litros")=TRUE(),1/1000, IF(AND(S27="TJ/kg",F27="litros")=TRUE(),K27/1000,1))))))) -> 0.57835013 | AC27: ="kgCO2e/"&F27 -> kgCO2e/kilogramos | AD27: IPCC 2006 (vol2; chapter 2) , Table 2.4 | AE27: CNE BNE 2024 | AF27: IPCC 2006 (vol2; chapter 1) , Table 1.2
B28: Gas de alto horno | C28: - | D28: Gas de alto horno | E28: Blast Furnace Gas | F28: gramos | G28: Gaseoso | H28: ='1.1 V2 CH2 T2.4'!$F$41 -> 260000 | I28: ='1.1 V2 CH2 T2.4'!$I$41 -> 5 | J28: ='1.1 V2 CH2 T2.4'!$L$41 -> 0.1 | M28: =2.47*1000/C$6 -> 589.94936 | N28: kcal/kg | O28: =IF(G28="Gaseoso", M28*$C$9, M28*$C$8) -> 530.95443 | P28: =N28 -> kcal/kg | Q28: No | R28: =O28*$C$6/$C$7*IF(Q28="Sí",K28*1000,1) -> 2.223e-06 | S28: =IF(Q28="Sí","TJ/m3", IF(N28="kcal/m3", "TJ/m3","TJ/kg")) -> TJ/kg | T28: =H28*$R28 -> 0.57798 | U28: =I28*$R28 -> 1.1115e-05 | V28: =J28*$R28 -> 2.223e-07 | W28: =IF(S28="TJ/m3", "kg GEI/m3", "kg GEI/kg") -> kg GEI/kg | X28: =$C$3*T28 -> 0.57798 | Y28: =U28*$C$4 -> 0.00031122 | Z28: =V28*$C$5 -> 5.89095e-05 | AA28: =IF(S28="TJ/m3", "kg CO2e/m3", "kg CO2e/kg") -> kg CO2e/kg | AB28: =SUM(X28:Z28)*IF(AND(F28="gramos",S28="TJ/m3")=TRUE(),1/(K28*1000000), IF(AND(F28="gramos",S28="TJ/kg")=TRUE(),1/(1000), IF(AND(F28="kilogramos",S28="TJ/m3")=TRUE(),1/(K28*1000), IF(AND(F28="toneladas",S28="TJ/m3")=TRUE(),1/K28, IF(AND(F28="toneladas",S28="TJ/kg")=TRUE(),1000, IF(AND(S28="TJ/m3",F28="litros")=TRUE(),1/1000, IF(AND(S28="TJ/kg",F28="litros")=TRUE(),K28/1000,1))))))) -> 0.00057835013 | AC28: ="kgCO2e/"&F28 -> kgCO2e/gramos | AD28: IPCC 2006 (vol2; chapter 2) , Table 2.4 | AE28: CNE BNE 2024 | AF28: IPCC 2006 (vol2; chapter 1) , Table 1.2
B29: Gas ciudad (cañería o corriente) | C29: Gas Natural | D29: Gas natural | E29: Natural gas | F29: metros cúbicos | G29: Gaseoso | H29: ='1.1 V2 CH2 T2.4'!$F$43 -> 56100 | I29: ='1.1 V2 CH2 T2.4'!$I$43 -> 5 | J29: ='1.1 V2 CH2 T2.4'!$L$43 -> 0.1 | M29: ='1.1 y 1.2CUADROA1 - BNE 2024'!D$21 -> 9341 | N29: ='1.1 y 1.2CUADROA1 - BNE 2024'!E$21 -> kCal/m3 | O29: =IF(G29="Gaseoso", M29*$C$9, M29*$C$8) -> 8406.9 | P29: =N29 -> kCal/m3 | Q29: No | R29: =O29*$C$6/$C$7*IF(Q29="Sí",K29*1000,1) -> 3.5198009e-05 | S29: =IF(Q29="Sí","TJ/m3", IF(N29="kcal/m3", "TJ/m3","TJ/kg")) -> TJ/m3 | T29: =H29*$R29 -> 1.9746083 | U29: =I29*$R29 -> 0.00017599004 | V29: =J29*$R29 -> 3.5198009e-06 | W29: =IF(S29="TJ/m3", "kg GEI/m3", "kg GEI/kg") -> kg GEI/m3 | X29: =$C$3*T29 -> 1.9746083 | Y29: =U29*$C$4 -> 0.0049277212 | Z29: =V29*$C$5 -> 0.00093274724 | AA29: =IF(S29="TJ/m3", "kg CO2e/m3", "kg CO2e/kg") -> kg CO2e/m3 | AB29: =SUM(X29:Z29)*IF(AND(F29="gramos",S29="TJ/m3")=TRUE(),1/(K29*1000000), IF(AND(F29="gramos",S29="TJ/kg")=TRUE(),1/(1000), IF(AND(F29="kilogramos",S29="TJ/m3")=TRUE(),1/(K29*1000), IF(AND(F29="toneladas",S29="TJ/m3")=TRUE(),1/K29, IF(AND(F29="toneladas",S29="TJ/kg")=TRUE(),1000, IF(AND(S29="TJ/m3",F29="litros")=TRUE(),1/1000, IF(AND(S29="TJ/kg",F29="litros")=TRUE(),K29/1000,1))))))) -> 1.9804688 | AC29: ="kgCO2e/"&F29 -> kgCO2e/metros cúbicos | AD29: IPCC 2006 (vol2; chapter 2) , Table 2.4 | AE29: CNE BNE 2024 | AF29: -
B30: Gas ciudad (cañería o corriente) | C30: Gas Natural | D30: Gas natural | E30: Natural gas | F30: toneladas | G30: Gaseoso | H30: ='1.1 V2 CH2 T2.4'!$F$43 -> 56100 | I30: ='1.1 V2 CH2 T2.4'!$I$43 -> 5 | J30: ='1.1 V2 CH2 T2.4'!$L$43 -> 0.1 | K30: =0.802/1000 -> 0.000802 | L30: t/m3 | M30: ='1.1 y 1.2CUADROA1 - BNE 2024'!D$21 -> 9341 | N30: ='1.1 y 1.2CUADROA1 - BNE 2024'!E$21 -> kCal/m3 | O30: =IF(G30="Gaseoso", M30*$C$9, M30*$C$8) -> 8406.9 | P30: =N30 -> kCal/m3 | Q30: No | R30: =O30*$C$6/$C$7*IF(Q30="Sí",K30*1000,1) -> 3.5198009e-05 | S30: =IF(Q30="Sí","TJ/m3", IF(N30="kcal/m3", "TJ/m3","TJ/kg")) -> TJ/m3 | T30: =H30*$R30 -> 1.9746083 | U30: =I30*$R30 -> 0.00017599004 | V30: =J30*$R30 -> 3.5198009e-06 | W30: =IF(S30="TJ/m3", "kg GEI/m3", "kg GEI/kg") -> kg GEI/m3 | X30: =$C$3*T30 -> 1.9746083 | Y30: =U30*$C$4 -> 0.0049277212 | Z30: =V30*$C$5 -> 0.00093274724 | AA30: =IF(S30="TJ/m3", "kg CO2e/m3", "kg CO2e/kg") -> kg CO2e/m3 | AB30: =SUM(X30:Z30)*IF(AND(F30="gramos",S30="TJ/m3")=TRUE(),1/(K30*1000000), IF(AND(F30="gramos",S30="TJ/kg")=TRUE(),1/(1000), IF(AND(F30="kilogramos",S30="TJ/m3")=TRUE(),1/(K30*1000), IF(AND(F30="toneladas",S30="TJ/m3")=TRUE(),1/K30, IF(AND(F30="toneladas",S30="TJ/kg")=TRUE(),1000, IF(AND(S30="TJ/m3",F30="litros")=TRUE(),1/1000, IF(AND(S30="TJ/kg",F30="litros")=TRUE(),K30/1000,1))))))) -> 2469.4124 | AC30: ="kgCO2e/"&F30 -> kgCO2e/toneladas | AD30: IPCC 2006 (vol2; chapter 2) , Table 2.4 | AE30: CNE BNE 2024 | AF30: DEFRA 2025 (Fuel properties), Natural Gas
B31: Gas ciudad (cañería o corriente) | C31: Gas Natural | D31: Gas natural | E31: Natural gas | F31: kilogramos | G31: Gaseoso | H31: ='1.1 V2 CH2 T2.4'!$F$43 -> 56100 | I31: ='1.1 V2 CH2 T2.4'!$I$43 -> 5 | J31: ='1.1 V2 CH2 T2.4'!$L$43 -> 0.1 | K31: =0.802/1000 -> 0.000802 | L31: t/m3 | M31: ='1.1 y 1.2CUADROA1 - BNE 2024'!D$21 -> 9341 | N31: ='1.1 y 1.2CUADROA1 - BNE 2024'!E$21 -> kCal/m3 | O31: =IF(G31="Gaseoso", M31*$C$9, M31*$C$8) -> 8406.9 | P31: =N31 -> kCal/m3 | Q31: No | R31: =O31*$C$6/$C$7*IF(Q31="Sí",K31*1000,1) -> 3.5198009e-05 | S31: =IF(Q31="Sí","TJ/m3", IF(N31="kcal/m3", "TJ/m3","TJ/kg")) -> TJ/m3 | T31: =H31*$R31 -> 1.9746083 | U31: =I31*$R31 -> 0.00017599004 | V31: =J31*$R31 -> 3.5198009e-06 | W31: =IF(S31="TJ/m3", "kg GEI/m3", "kg GEI/kg") -> kg GEI/m3 | X31: =$C$3*T31 -> 1.9746083 | Y31: =U31*$C$4 -> 0.0049277212 | Z31: =V31*$C$5 -> 0.00093274724 | AA31: =IF(S31="TJ/m3", "kg CO2e/m3", "kg CO2e/kg") -> kg CO2e/m3 | AB31: =SUM(X31:Z31)*IF(AND(F31="gramos",S31="TJ/m3")=TRUE(),1/(K31*1000000), IF(AND(F31="gramos",S31="TJ/kg")=TRUE(),1/(1000), IF(AND(F31="kilogramos",S31="TJ/m3")=TRUE(),1/(K31*1000), IF(AND(F31="toneladas",S31="TJ/m3")=TRUE(),1/K31, IF(AND(F31="toneladas",S31="TJ/kg")=TRUE(),1000, IF(AND(S31="TJ/m3",F31="litros")=TRUE(),1/1000, IF(AND(S31="TJ/kg",F31="litros")=TRUE(),K31/1000,1))))))) -> 2.4694124 | AC31: ="kgCO2e/"&F31 -> kgCO2e/kilogramos | AD31: IPCC 2006 (vol2; chapter 2) , Table 2.4 | AE31: CNE BNE 2024 | AF31: DEFRA 2025 (Fuel properties), Natural Gas
B32: Gas ciudad (cañería o corriente) | C32: Gas Natural | D32: Gas natural | E32: Natural gas | F32: gramos | G32: Gaseoso | H32: ='1.1 V2 CH2 T2.4'!$F$43 -> 56100 | I32: ='1.1 V2 CH2 T2.4'!$I$43 -> 5 | J32: ='1.1 V2 CH2 T2.4'!$L$43 -> 0.1 | K32: =0.802/1000 -> 0.000802 | L32: t/m3 | M32: ='1.1 y 1.2CUADROA1 - BNE 2024'!D$21 -> 9341 | N32: ='1.1 y 1.2CUADROA1 - BNE 2024'!E$21 -> kCal/m3 | O32: =IF(G32="Gaseoso", M32*$C$9, M32*$C$8) -> 8406.9 | P32: =N32 -> kCal/m3 | Q32: No | R32: =O32*$C$6/$C$7*IF(Q32="Sí",K32*1000,1) -> 3.5198009e-05 | S32: =IF(Q32="Sí","TJ/m3", IF(N32="kcal/m3", "TJ/m3","TJ/kg")) -> TJ/m3 | T32: =H32*$R32 -> 1.9746083 | U32: =I32*$R32 -> 0.00017599004 | V32: =J32*$R32 -> 3.5198009e-06 | W32: =IF(S32="TJ/m3", "kg GEI/m3", "kg GEI/kg") -> kg GEI/m3 | X32: =$C$3*T32 -> 1.9746083 | Y32: =U32*$C$4 -> 0.0049277212 | Z32: =V32*$C$5 -> 0.00093274724 | AA32: =IF(S32="TJ/m3", "kg CO2e/m3", "kg CO2e/kg") -> kg CO2e/m3 | AB32: =SUM(X32:Z32)*IF(AND(F32="gramos",S32="TJ/m3")=TRUE(),1/(K32*1000000), IF(AND(F32="gramos",S32="TJ/kg")=TRUE(),1/(1000), IF(AND(F32="kilogramos",S32="TJ/m3")=TRUE(),1/(K32*1000), IF(AND(F32="toneladas",S32="TJ/m3")=TRUE(),1/K32, IF(AND(F32="toneladas",S32="TJ/kg")=TRUE(),1000, IF(AND(S32="TJ/m3",F32="litros")=TRUE(),1/1000, IF(AND(S32="TJ/kg",F32="litros")=TRUE(),K32/1000,1))))))) -> 0.0024694124 | AC32: ="kgCO2e/"&F32 -> kgCO2e/gramos | AD32: IPCC 2006 (vol2; chapter 2) , Table 2.4 | AE32: CNE BNE 2024 | AF32: DEFRA 2025 (Fuel properties), Natural Gas
B33: Gas de refinería | C33: Gas de Refinería | D33: Gas de refinería | E33: Refinery Gas | F33: metros cúbicos | G33: Líquido | H33: ='1.1 V2 CH2 T2.4'!$F$23 -> 57600 | I33: ='1.1 V2 CH2 T2.4'!$I$23 -> 5 | J33: ='1.1 V2 CH2 T2.4'!$L$23 -> 0.1 | M33: ='1.1 y 1.2CUADROA1 - BNE 2024'!D$30 -> 4260 | N33: ='1.1 y 1.2CUADROA1 - BNE 2024'!E$30 -> kCal/m3 | O33: =IF(G33="Gaseoso", M33*$C$9, M33*$C$8) -> 4047 | P33: =N33 -> kCal/m3 | Q33: No | R33: =O33*$C$6/$C$7*IF(Q33="Sí",K33*1000,1) -> 1.694398e-05 | S33: =IF(Q33="Sí","TJ/m3", IF(N33="kcal/m3", "TJ/m3","TJ/kg")) -> TJ/m3 | T33: =H33*$R33 -> 0.97597322 | U33: =I33*$R33 -> 8.4719898e-05 | V33: =J33*$R33 -> 1.694398e-06 | W33: =IF(S33="TJ/m3", "kg GEI/m3", "kg GEI/kg") -> kg GEI/m3 | X33: =$C$3*T33 -> 0.97597322 | Y33: =U33*$C$4 -> 0.0023721571 | Z33: =V33*$C$5 -> 0.00044901546 | AA33: =IF(S33="TJ/m3", "kg CO2e/m3", "kg CO2e/kg") -> kg CO2e/m3 | AB33: =SUM(X33:Z33)*IF(AND(F33="gramos",S33="TJ/m3")=TRUE(),1/(K33*1000000), IF(AND(F33="gramos",S33="TJ/kg")=TRUE(),1/(1000), IF(AND(F33="kilogramos",S33="TJ/m3")=TRUE(),1/(K33*1000), IF(AND(F33="toneladas",S33="TJ/m3")=TRUE(),1/K33, IF(AND(F33="toneladas",S33="TJ/kg")=TRUE(),1000, IF(AND(S33="TJ/m3",F33="litros")=TRUE(),1/1000, IF(AND(S33="TJ/kg",F33="litros")=TRUE(),K33/1000,1))))))) -> 0.9787944 | AC33: ="kgCO2e/"&F33 -> kgCO2e/metros cúbicos | AD33: IPCC 2006 (vol2; chapter 2) , Table 2.4 | AE33: CNE BNE 2024 | AF33: -
B34: Gas de refinería | C34: Gas de Refinería | D34: Gas de refinería | E34: Refinery Gas | F34: litros | G34: Líquido | H34: ='1.1 V2 CH2 T2.4'!$F$23 -> 57600 | I34: ='1.1 V2 CH2 T2.4'!$I$23 -> 5 | J34: ='1.1 V2 CH2 T2.4'!$L$23 -> 0.1 | M34: ='1.1 y 1.2CUADROA1 - BNE 2024'!D$30 -> 4260 | N34: ='1.1 y 1.2CUADROA1 - BNE 2024'!E$30 -> kCal/m3 | O34: =IF(G34="Gaseoso", M34*$C$9, M34*$C$8) -> 4047 | P34: =N34 -> kCal/m3 | Q34: No | R34: =O34*$C$6/$C$7*IF(Q34="Sí",K34*1000,1) -> 1.694398e-05 | S34: =IF(Q34="Sí","TJ/m3", IF(N34="kcal/m3", "TJ/m3","TJ/kg")) -> TJ/m3 | T34: =H34*$R34 -> 0.97597322 | U34: =I34*$R34 -> 8.4719898e-05 | V34: =J34*$R34 -> 1.694398e-06 | W34: =IF(S34="TJ/m3", "kg GEI/m3", "kg GEI/kg") -> kg GEI/m3 | X34: =$C$3*T34 -> 0.97597322 | Y34: =U34*$C$4 -> 0.0023721571 | Z34: =V34*$C$5 -> 0.00044901546 | AA34: =IF(S34="TJ/m3", "kg CO2e/m3", "kg CO2e/kg") -> kg CO2e/m3 | AB34: =SUM(X34:Z34)*IF(AND(F34="gramos",S34="TJ/m3")=TRUE(),1/(K34*1000000), IF(AND(F34="gramos",S34="TJ/kg")=TRUE(),1/(1000), IF(AND(F34="kilogramos",S34="TJ/m3")=TRUE(),1/(K34*1000), IF(AND(F34="toneladas",S34="TJ/m3")=TRUE(),1/K34, IF(AND(F34="toneladas",S34="TJ/kg")=TRUE(),1000, IF(AND(S34="TJ/m3",F34="litros")=TRUE(),1/1000, IF(AND(S34="TJ/kg",F34="litros")=TRUE(),K34/1000,1))))))) -> 0.0009787944 | AC34: ="kgCO2e/"&F34 -> kgCO2e/litros | AD34: IPCC 2006 (vol2; chapter 2) , Table 2.4 | AE34: CNE BNE 2024 | AF34: -
B35: Gas licuado de petróleo | C35: Gas Licuado | D35: Gases licuados de petroleo | E35: Liquefied Petroleum Gases | F35: metros cúbicos | G35: Líquido | H35: ='1.1 V2 CH2 T2.4'!$F$16 -> 63100 | I35: ='1.1 V2 CH2 T2.4'!$I$16 -> 5 | J35: ='1.1 V2 CH2 T2.4'!$L$16 -> 0.1 | K35: ='1.1 y 1.2CUADROA1 - BNE 2024'!$C$15 -> 0.55 | L35: t/m3 | M35: ='1.1 y 1.2CUADROA1 - BNE 2024'!D$15 -> 12100 | N35: ='1.1 y 1.2CUADROA1 - BNE 2024'!E$15 -> kCal/kg | O35: =IF(G35="Gaseoso", M35*$C$9, M35*$C$8) -> 11495 | P35: =N35 -> kCal/kg | Q35: Sí | R35: =O35*$C$6/$C$7*IF(Q35="Sí",K35*1000,1) -> 0.026469996 | S35: =IF(Q35="Sí","TJ/m3", IF(N35="kcal/m3", "TJ/m3","TJ/kg")) -> TJ/m3 | T35: =H35*$R35 -> 1670.2568 | U35: =I35*$R35 -> 0.13234998 | V35: =J35*$R35 -> 0.0026469996 | W35: =IF(S35="TJ/m3", "kg GEI/m3", "kg GEI/kg") -> kg GEI/m3 | X35: =$C$3*T35 -> 1670.2568 | Y35: =U35*$C$4 -> 3.7057995 | Z35: =V35*$C$5 -> 0.7014549 | AA35: =IF(S35="TJ/m3", "kg CO2e/m3", "kg CO2e/kg") -> kg CO2e/m3 | AB35: =SUM(X35:Z35)*IF(AND(F35="gramos",S35="TJ/m3")=TRUE(),1/(K35*1000000), IF(AND(F35="gramos",S35="TJ/kg")=TRUE(),1/(1000), IF(AND(F35="kilogramos",S35="TJ/m3")=TRUE(),1/(K35*1000), IF(AND(F35="toneladas",S35="TJ/m3")=TRUE(),1/K35, IF(AND(F35="toneladas",S35="TJ/kg")=TRUE(),1000, IF(AND(S35="TJ/m3",F35="litros")=TRUE(),1/1000, IF(AND(S35="TJ/kg",F35="litros")=TRUE(),K35/1000,1))))))) -> 1674.664 | AC35: ="kgCO2e/"&F35 -> kgCO2e/metros cúbicos | AD35: IPCC 2006 (vol2; chapter 2) , Table 2.4 | AE35: CNE BNE 2024 | AF35: -
B36: Gas licuado de petróleo | C36: Gas Licuado | D36: Gases licuados de petroleo | E36: Liquefied Petroleum Gases | F36: litros | G36: Líquido | H36: ='1.1 V2 CH2 T2.4'!$F$16 -> 63100 | I36: ='1.1 V2 CH2 T2.4'!$I$16 -> 5 | J36: ='1.1 V2 CH2 T2.4'!$L$16 -> 0.1 | K36: ='1.1 y 1.2CUADROA1 - BNE 2024'!$C$15 -> 0.55 | L36: t/m3 | M36: ='1.1 y 1.2CUADROA1 - BNE 2024'!D$15 -> 12100 | N36: ='1.1 y 1.2CUADROA1 - BNE 2024'!E$15 -> kCal/kg | O36: =IF(G36="Gaseoso", M36*$C$9, M36*$C$8) -> 11495 | P36: =N36 -> kCal/kg | Q36: Sí | R36: =O36*$C$6/$C$7*IF(Q36="Sí",K36*1000,1) -> 0.026469996 | S36: =IF(Q36="Sí","TJ/m3", IF(N36="kcal/m3", "TJ/m3","TJ/kg")) -> TJ/m3 | T36: =H36*$R36 -> 1670.2568 | U36: =I36*$R36 -> 0.13234998 | V36: =J36*$R36 -> 0.0026469996 | W36: =IF(S36="TJ/m3", "kg GEI/m3", "kg GEI/kg") -> kg GEI/m3 | X36: =$C$3*T36 -> 1670.2568 | Y36: =U36*$C$4 -> 3.7057995 | Z36: =V36*$C$5 -> 0.7014549 | AA36: =IF(S36="TJ/m3", "kg CO2e/m3", "kg CO2e/kg") -> kg CO2e/m3 | AB36: =SUM(X36:Z36)*IF(AND(F36="gramos",S36="TJ/m3")=TRUE(),1/(K36*1000000), IF(AND(F36="gramos",S36="TJ/kg")=TRUE(),1/(1000), IF(AND(F36="kilogramos",S36="TJ/m3")=TRUE(),1/(K36*1000), IF(AND(F36="toneladas",S36="TJ/m3")=TRUE(),1/K36, IF(AND(F36="toneladas",S36="TJ/kg")=TRUE(),1000, IF(AND(S36="TJ/m3",F36="litros")=TRUE(),1/1000, IF(AND(S36="TJ/kg",F36="litros")=TRUE(),K36/1000,1))))))) -> 1.674664 | AC36: ="kgCO2e/"&F36 -> kgCO2e/litros | AD36: IPCC 2006 (vol2; chapter 2) , Table 2.4 | AE36: CNE BNE 2024 | AF36: -
B37: Gas natural | C37: Gas Natural | D37: Gas natural | E37: Natural gas | F37: metros cúbicos | G37: Gaseoso | H37: ='1.1 V2 CH2 T2.4'!$F$43 -> 56100 | I37: ='1.1 V2 CH2 T2.4'!$I$43 -> 5 | J37: ='1.1 V2 CH2 T2.4'!$L$43 -> 0.1 | K37: =0.802/1000 -> 0.000802 | L37: t/m3 | M37: ='1.1 y 1.2CUADROA1 - BNE 2024'!D$21 -> 9341 | N37: ='1.1 y 1.2CUADROA1 - BNE 2024'!E$21 -> kCal/m3 | O37: =IF(G37="Gaseoso", M37*$C$9, M37*$C$8) -> 8406.9 | P37: =N37 -> kCal/m3 | Q37: No | R37: =O37*$C$6/$C$7*IF(Q37="Sí",K37*1000,1) -> 3.5198009e-05 | S37: =IF(Q37="Sí","TJ/m3", IF(N37="kcal/m3", "TJ/m3","TJ/kg")) -> TJ/m3 | T37: =H37*$R37 -> 1.9746083 | U37: =I37*$R37 -> 0.00017599004 | V37: =J37*$R37 -> 3.5198009e-06 | W37: =IF(S37="TJ/m3", "kg GEI/m3", "kg GEI/kg") -> kg GEI/m3 | X37: =$C$3*T37 -> 1.9746083 | Y37: =U37*$C$4 -> 0.0049277212 | Z37: =V37*$C$5 -> 0.00093274724 | AA37: =IF(S37="TJ/m3", "kg CO2e/m3", "kg CO2e/kg") -> kg CO2e/m3 | AB37: =SUM(X37:Z37)*IF(AND(F37="gramos",S37="TJ/m3")=TRUE(),1/(K37*1000000), IF(AND(F37="gramos",S37="TJ/kg")=TRUE(),1/(1000), IF(AND(F37="kilogramos",S37="TJ/m3")=TRUE(),1/(K37*1000), IF(AND(F37="toneladas",S37="TJ/m3")=TRUE(),1/K37, IF(AND(F37="toneladas",S37="TJ/kg")=TRUE(),1000, IF(AND(S37="TJ/m3",F37="litros")=TRUE(),1/1000, IF(AND(S37="TJ/kg",F37="litros")=TRUE(),K37/1000,1))))))) -> 1.9804688 | AC37: ="kgCO2e/"&F37 -> kgCO2e/metros cúbicos | AD37: IPCC 2006 (vol2; chapter 2) , Table 2.4 | AE37: CNE BNE 2024 | AF37: DEFRA 2025 (Fuel properties), Natural Gas
B38: Kerosene | C38: Kerosene | D38: Otro queroseno | E38: Other Kerosene | F38: metros cúbicos | G38: Líquido | H38: ='1.1 V2 CH2 T2.4'!$F$12 -> 71900 | I38: ='1.1 V2 CH2 T2.4'!$I$12 -> 10 | J38: ='1.1 V2 CH2 T2.4'!$L$12 -> 0.6 | K38: ='1.1 y 1.2CUADROA1 - BNE 2024'!$C$19 -> 0.81 | L38: t/m3 | M38: ='1.1 y 1.2CUADROA1 - BNE 2024'!D$19 -> 11100 | N38: ='1.1 y 1.2CUADROA1 - BNE 2024'!E$19 -> kCal/kg | O38: =IF(G38="Gaseoso", M38*$C$9, M38*$C$8) -> 10545 | P38: =N38 -> kCal/kg | Q38: Sí | R38: =O38*$C$6/$C$7*IF(Q38="Sí",K38*1000,1) -> 0.035761343 | S38: =IF(Q38="Sí","TJ/m3", IF(N38="kcal/m3", "TJ/m3","TJ/kg")) -> TJ/m3 | T38: =H38*$R38 -> 2571.2406 | U38: =I38*$R38 -> 0.35761343 | V38: =J38*$R38 -> 0.021456806 | W38: =IF(S38="TJ/m3", "kg GEI/m3", "kg GEI/kg") -> kg GEI/m3 | X38: =$C$3*T38 -> 2571.2406 | Y38: =U38*$C$4 -> 10.013176 | Z38: =V38*$C$5 -> 5.6860535 | AA38: =IF(S38="TJ/m3", "kg CO2e/m3", "kg CO2e/kg") -> kg CO2e/m3 | AB38: =SUM(X38:Z38)*IF(AND(F38="gramos",S38="TJ/m3")=TRUE(),1/(K38*1000000), IF(AND(F38="gramos",S38="TJ/kg")=TRUE(),1/(1000), IF(AND(F38="kilogramos",S38="TJ/m3")=TRUE(),1/(K38*1000), IF(AND(F38="toneladas",S38="TJ/m3")=TRUE(),1/K38, IF(AND(F38="toneladas",S38="TJ/kg")=TRUE(),1000, IF(AND(S38="TJ/m3",F38="litros")=TRUE(),1/1000, IF(AND(S38="TJ/kg",F38="litros")=TRUE(),K38/1000,1))))))) -> 2586.9398 | AC38: ="kgCO2e/"&F38 -> kgCO2e/metros cúbicos | AD38: IPCC 2006 (vol2; chapter 2) , Table 2.4 | AE38: CNE BNE 2024 | AF38: -
B39: Kerosene | C39: Kerosene | D39: Otro queroseno | E39: Other Kerosene | F39: litros | G39: Líquido | H39: ='1.1 V2 CH2 T2.4'!$F$12 -> 71900 | I39: ='1.1 V2 CH2 T2.4'!$I$12 -> 10 | J39: ='1.1 V2 CH2 T2.4'!$L$12 -> 0.6 | K39: ='1.1 y 1.2CUADROA1 - BNE 2024'!$C$19 -> 0.81 | L39: t/m3 | M39: ='1.1 y 1.2CUADROA1 - BNE 2024'!D$19 -> 11100 | N39: ='1.1 y 1.2CUADROA1 - BNE 2024'!E$19 -> kCal/kg | O39: =IF(G39="Gaseoso", M39*$C$9, M39*$C$8) -> 10545 | P39: =N39 -> kCal/kg | Q39: Sí | R39: =O39*$C$6/$C$7*IF(Q39="Sí",K39*1000,1) -> 0.035761343 | S39: =IF(Q39="Sí","TJ/m3", IF(N39="kcal/m3", "TJ/m3","TJ/kg")) -> TJ/m3 | T39: =H39*$R39 -> 2571.2406 | U39: =I39*$R39 -> 0.35761343 | V39: =J39*$R39 -> 0.021456806 | W39: =IF(S39="TJ/m3", "kg GEI/m3", "kg GEI/kg") -> kg GEI/m3 | X39: =$C$3*T39 -> 2571.2406 | Y39: =U39*$C$4 -> 10.013176 | Z39: =V39*$C$5 -> 5.6860535 | AA39: =IF(S39="TJ/m3", "kg CO2e/m3", "kg CO2e/kg") -> kg CO2e/m3 | AB39: =SUM(X39:Z39)*IF(AND(F39="gramos",S39="TJ/m3")=TRUE(),1/(K39*1000000), IF(AND(F39="gramos",S39="TJ/kg")=TRUE(),1/(1000), IF(AND(F39="kilogramos",S39="TJ/m3")=TRUE(),1/(K39*1000), IF(AND(F39="toneladas",S39="TJ/m3")=TRUE(),1/K39, IF(AND(F39="toneladas",S39="TJ/kg")=TRUE(),1000, IF(AND(S39="TJ/m3",F39="litros")=TRUE(),1/1000, IF(AND(S39="TJ/kg",F39="litros")=TRUE(),K39/1000,1))))))) -> 2.5869398 | AC39: ="kgCO2e/"&F39 -> kgCO2e/litros | AD39: IPCC 2006 (vol2; chapter 2) , Table 2.4 | AE39: CNE BNE 2024 | AF39: -
B40: Petcoke | C40: Coque de Petróleo | D40: Coque de petróleo | E40: Petroleum Coke | F40: toneladas | G40: Sólido | H40: ='1.1 V2 CH2 T2.4'!$F$21 -> 97500 | I40: ='1.1 V2 CH2 T2.4'!$I$21 -> 10 | J40: ='1.1 V2 CH2 T2.4'!$L$21 -> 0.6 | M40: ='1.1 y 1.2CUADROA1 - BNE 2024'!D$28 -> 8100 | N40: ='1.1 y 1.2CUADROA1 - BNE 2024'!E$25 -> kCal/kg | O40: =IF(G40="Gaseoso", M40*$C$9, M40*$C$8) -> 7695 | P40: =N40 -> kCal/kg | Q40: No | R40: =O40*$C$6/$C$7*IF(Q40="Sí",K40*1000,1) -> 3.2217426e-05 | S40: =IF(Q40="Sí","TJ/m3", IF(N40="kcal/m3", "TJ/m3","TJ/kg")) -> TJ/kg | T40: =H40*$R40 -> 3.141199 | U40: =I40*$R40 -> 0.00032217426 | V40: =J40*$R40 -> 1.9330456e-05 | W40: =IF(S40="TJ/m3", "kg GEI/m3", "kg GEI/kg") -> kg GEI/kg | X40: =$C$3*T40 -> 3.141199 | Y40: =U40*$C$4 -> 0.0090208793 | Z40: =V40*$C$5 -> 0.0051225707 | AA40: =IF(S40="TJ/m3", "kg CO2e/m3", "kg CO2e/kg") -> kg CO2e/kg | AB40: =SUM(X40:Z40)*IF(AND(F40="gramos",S40="TJ/m3")=TRUE(),1/(K40*1000000), IF(AND(F40="gramos",S40="TJ/kg")=TRUE(),1/(1000), IF(AND(F40="kilogramos",S40="TJ/m3")=TRUE(),1/(K40*1000), IF(AND(F40="toneladas",S40="TJ/m3")=TRUE(),1/K40, IF(AND(F40="toneladas",S40="TJ/kg")=TRUE(),1000, IF(AND(S40="TJ/m3",F40="litros")=TRUE(),1/1000, IF(AND(S40="TJ/kg",F40="litros")=TRUE(),K40/1000,1))))))) -> 3155.3425 | AC40: ="kgCO2e/"&F40 -> kgCO2e/toneladas | AD40: IPCC 2006 (vol2; chapter 2) , Table 2.4 | AE40: CNE BNE 2024 | AF40: -
B41: Petcoke | C41: Coque de Petróleo | D41: Coque de petróleo | E41: Petroleum Coke | F41: kilogramos | G41: Sólido | H41: ='1.1 V2 CH2 T2.4'!$F$21 -> 97500 | I41: ='1.1 V2 CH2 T2.4'!$I$21 -> 10 | J41: ='1.1 V2 CH2 T2.4'!$L$21 -> 0.6 | M41: ='1.1 y 1.2CUADROA1 - BNE 2024'!D$28 -> 8100 | N41: ='1.1 y 1.2CUADROA1 - BNE 2024'!E$25 -> kCal/kg | O41: =IF(G41="Gaseoso", M41*$C$9, M41*$C$8) -> 7695 | P41: =N41 -> kCal/kg | Q41: No | R41: =O41*$C$6/$C$7*IF(Q41="Sí",K41*1000,1) -> 3.2217426e-05 | S41: =IF(Q41="Sí","TJ/m3", IF(N41="kcal/m3", "TJ/m3","TJ/kg")) -> TJ/kg | T41: =H41*$R41 -> 3.141199 | U41: =I41*$R41 -> 0.00032217426 | V41: =J41*$R41 -> 1.9330456e-05 | W41: =IF(S41="TJ/m3", "kg GEI/m3", "kg GEI/kg") -> kg GEI/kg | X41: =$C$3*T41 -> 3.141199 | Y41: =U41*$C$4 -> 0.0090208793 | Z41: =V41*$C$5 -> 0.0051225707 | AA41: =IF(S41="TJ/m3", "kg CO2e/m3", "kg CO2e/kg") -> kg CO2e/kg | AB41: =SUM(X41:Z41)*IF(AND(F41="gramos",S41="TJ/m3")=TRUE(),1/(K41*1000000), IF(AND(F41="gramos",S41="TJ/kg")=TRUE(),1/(1000), IF(AND(F41="kilogramos",S41="TJ/m3")=TRUE(),1/(K41*1000), IF(AND(F41="toneladas",S41="TJ/m3")=TRUE(),1/K41, IF(AND(F41="toneladas",S41="TJ/kg")=TRUE(),1000, IF(AND(S41="TJ/m3",F41="litros")=TRUE(),1/1000, IF(AND(S41="TJ/kg",F41="litros")=TRUE(),K41/1000,1))))))) -> 3.1553425 | AC41: ="kgCO2e/"&F41 -> kgCO2e/kilogramos | AD41: IPCC 2006 (vol2; chapter 2) , Table 2.4 | AE41: CNE BNE 2024 | AF41: -
B42: Petcoke | C42: Coque de Petróleo | D42: Coque de petróleo | E42: Petroleum Coke | F42: gramos | G42: Sólido | H42: ='1.1 V2 CH2 T2.4'!$F$21 -> 97500 | I42: ='1.1 V2 CH2 T2.4'!$I$21 -> 10 | J42: ='1.1 V2 CH2 T2.4'!$L$21 -> 0.6 | M42: ='1.1 y 1.2CUADROA1 - BNE 2024'!D$28 -> 8100 | N42: ='1.1 y 1.2CUADROA1 - BNE 2024'!E$25 -> kCal/kg | O42: =IF(G42="Gaseoso", M42*$C$9, M42*$C$8) -> 7695 | P42: =N42 -> kCal/kg | Q42: No | R42: =O42*$C$6/$C$7*IF(Q42="Sí",K42*1000,1) -> 3.2217426e-05 | S42: =IF(Q42="Sí","TJ/m3", IF(N42="kcal/m3", "TJ/m3","TJ/kg")) -> TJ/kg | T42: =H42*$R42 -> 3.141199 | U42: =I42*$R42 -> 0.00032217426 | V42: =J42*$R42 -> 1.9330456e-05 | W42: =IF(S42="TJ/m3", "kg GEI/m3", "kg GEI/kg") -> kg GEI/kg | X42: =$C$3*T42 -> 3.141199 | Y42: =U42*$C$4 -> 0.0090208793 | Z42: =V42*$C$5 -> 0.0051225707 | AA42: =IF(S42="TJ/m3", "kg CO2e/m3", "kg CO2e/kg") -> kg CO2e/kg | AB42: =SUM(X42:Z42)*IF(AND(F42="gramos",S42="TJ/m3")=TRUE(),1/(K42*1000000), IF(AND(F42="gramos",S42="TJ/kg")=TRUE(),1/(1000), IF(AND(F42="kilogramos",S42="TJ/m3")=TRUE(),1/(K42*1000), IF(AND(F42="toneladas",S42="TJ/m3")=TRUE(),1/K42, IF(AND(F42="toneladas",S42="TJ/kg")=TRUE(),1000, IF(AND(S42="TJ/m3",F42="litros")=TRUE(),1/1000, IF(AND(S42="TJ/kg",F42="litros")=TRUE(),K42/1000,1))))))) -> 0.0031553425 | AC42: ="kgCO2e/"&F42 -> kgCO2e/gramos | AD42: IPCC 2006 (vol2; chapter 2) , Table 2.4 | AE42: CNE BNE 2024 | AF42: -
B43: Petróleo 2 (Diésel) | C43: Petróleo Diésel | D43: Gas/Diesel Oil | E43: Gas/Diesel Oil | F43: metros cúbicos | G43: Líquido | H43: ='1.1 V2 CH2 T2.4'!$F$14 -> 74100 | I43: ='1.1 V2 CH2 T2.4'!$I$14 -> 10 | J43: ='1.1 V2 CH2 T2.4'!$L$14 -> 0.6 | K43: ='1.1 y 1.2CUADROA1 - BNE 2024'!$C$20 -> 0.84 | L43: t/m3 | M43: ='1.1 y 1.2CUADROA1 - BNE 2024'!D$20 -> 10900 | N43: ='1.1 y 1.2CUADROA1 - BNE 2024'!E$20 -> kCal/kg | O43: =IF(G43="Gaseoso", M43*$C$9, M43*$C$8) -> 10355 | P43: =N43 -> kCal/kg | Q43: Sí | R43: =O43*$C$6/$C$7*IF(Q43="Sí",K43*1000,1) -> 0.036417624 | S43: =IF(Q43="Sí","TJ/m3", IF(N43="kcal/m3", "TJ/m3","TJ/kg")) -> TJ/m3 | T43: =H43*$R43 -> 2698.5459 | U43: =I43*$R43 -> 0.36417624 | V43: =J43*$R43 -> 0.021850574 | W43: =IF(S43="TJ/m3", "kg GEI/m3", "kg GEI/kg") -> kg GEI/m3 | X43: =$C$3*T43 -> 2698.5459 | Y43: =U43*$C$4 -> 10.196935 | Z43: =V43*$C$5 -> 5.7904022 | AA43: =IF(S43="TJ/m3", "kg CO2e/m3", "kg CO2e/kg") -> kg CO2e/m3 | AB43: =SUM(X43:Z43)*IF(AND(F43="gramos",S43="TJ/m3")=TRUE(),1/(K43*1000000), IF(AND(F43="gramos",S43="TJ/kg")=TRUE(),1/(1000), IF(AND(F43="kilogramos",S43="TJ/m3")=TRUE(),1/(K43*1000), IF(AND(F43="toneladas",S43="TJ/m3")=TRUE(),1/K43, IF(AND(F43="toneladas",S43="TJ/kg")=TRUE(),1000, IF(AND(S43="TJ/m3",F43="litros")=TRUE(),1/1000, IF(AND(S43="TJ/kg",F43="litros")=TRUE(),K43/1000,1))))))) -> 2714.5333 | AC43: ="kgCO2e/"&F43 -> kgCO2e/metros cúbicos | AD43: IPCC 2006 (vol2; chapter 2) , Table 2.4 | AE43: CNE BNE 2024 | AF43: -
B44: Petróleo 2 (Diésel) | C44: Petróleo Diésel | D44: Gas/Diesel Oil | E44: Gas/Diesel Oil | F44: litros | G44: Líquido | H44: ='1.1 V2 CH2 T2.4'!$F$14 -> 74100 | I44: ='1.1 V2 CH2 T2.4'!$I$14 -> 10 | J44: ='1.1 V2 CH2 T2.4'!$L$14 -> 0.6 | K44: ='1.1 y 1.2CUADROA1 - BNE 2024'!$C$20 -> 0.84 | L44: t/m3 | M44: ='1.1 y 1.2CUADROA1 - BNE 2024'!D$20 -> 10900 | N44: ='1.1 y 1.2CUADROA1 - BNE 2024'!E$20 -> kCal/kg | O44: =IF(G44="Gaseoso", M44*$C$9, M44*$C$8) -> 10355 | P44: =N44 -> kCal/kg | Q44: Sí | R44: =O44*$C$6/$C$7*IF(Q44="Sí",K44*1000,1) -> 0.036417624 | S44: =IF(Q44="Sí","TJ/m3", IF(N44="kcal/m3", "TJ/m3","TJ/kg")) -> TJ/m3 | T44: =H44*$R44 -> 2698.5459 | U44: =I44*$R44 -> 0.36417624 | V44: =J44*$R44 -> 0.021850574 | W44: =IF(S44="TJ/m3", "kg GEI/m3", "kg GEI/kg") -> kg GEI/m3 | X44: =$C$3*T44 -> 2698.5459 | Y44: =U44*$C$4 -> 10.196935 | Z44: =V44*$C$5 -> 5.7904022 | AA44: =IF(S44="TJ/m3", "kg CO2e/m3", "kg CO2e/kg") -> kg CO2e/m3 | AB44: =SUM(X44:Z44)*IF(AND(F44="gramos",S44="TJ/m3")=TRUE(),1/(K44*1000000), IF(AND(F44="gramos",S44="TJ/kg")=TRUE(),1/(1000), IF(AND(F44="kilogramos",S44="TJ/m3")=TRUE(),1/(K44*1000), IF(AND(F44="toneladas",S44="TJ/m3")=TRUE(),1/K44, IF(AND(F44="toneladas",S44="TJ/kg")=TRUE(),1000, IF(AND(S44="TJ/m3",F44="litros")=TRUE(),1/1000, IF(AND(S44="TJ/kg",F44="litros")=TRUE(),K44/1000,1))))))) -> 2.7145333 | AC44: ="kgCO2e/"&F44 -> kgCO2e/litros | AD44: IPCC 2006 (vol2; chapter 2) , Table 2.4 | AE44: CNE BNE 2024 | AF44: -
B45: Petróleo 5 | C45: Petróleo Combustible 5 | D45: Fuelóleo residual | E45: Residual Fuel Oil | F45: metros cúbicos | G45: Líquido | H45: ='1.1 V2 CH2 T2.4'!$F$15 -> 77400 | I45: ='1.1 V2 CH2 T2.4'!$I$15 -> 10 | J45: ='1.1 V2 CH2 T2.4'!$L$15 -> 0.6 | K45: ='1.1 y 1.2CUADROA1 - BNE 2024'!$C$11 -> 0.927 | L45: t/m3 | M45: ='1.1 y 1.2CUADROA1 - BNE 2024'!D$11 -> 10500 | N45: ='1.1 y 1.2CUADROA1 - BNE 2024'!E$11 -> kCal/kg | O45: =IF(G45="Gaseoso", M45*$C$9, M45*$C$8) -> 9975 | P45: =N45 -> kCal/kg | Q45: Sí | R45: =O45*$C$6/$C$7*IF(Q45="Sí",K45*1000,1) -> 0.038714607 | S45: =IF(Q45="Sí","TJ/m3", IF(N45="kcal/m3", "TJ/m3","TJ/kg")) -> TJ/m3 | T45: =H45*$R45 -> 2996.5106 | U45: =I45*$R45 -> 0.38714607 | V45: =J45*$R45 -> 0.023228764 | W45: =IF(S45="TJ/m3", "kg GEI/m3", "kg GEI/kg") -> kg GEI/m3 | X45: =$C$3*T45 -> 2996.5106 | Y45: =U45*$C$4 -> 10.84009 | Z45: =V45*$C$5 -> 6.1556225 | AA45: =IF(S45="TJ/m3", "kg CO2e/m3", "kg CO2e/kg") -> kg CO2e/m3 | AB45: =SUM(X45:Z45)*IF(AND(F45="gramos",S45="TJ/m3")=TRUE(),1/(K45*1000000), IF(AND(F45="gramos",S45="TJ/kg")=TRUE(),1/(1000), IF(AND(F45="kilogramos",S45="TJ/m3")=TRUE(),1/(K45*1000), IF(AND(F45="toneladas",S45="TJ/m3")=TRUE(),1/K45, IF(AND(F45="toneladas",S45="TJ/kg")=TRUE(),1000, IF(AND(S45="TJ/m3",F45="litros")=TRUE(),1/1000, IF(AND(S45="TJ/kg",F45="litros")=TRUE(),K45/1000,1))))))) -> 3013.5063 | AC45: ="kgCO2e/"&F45 -> kgCO2e/metros cúbicos | AD45: IPCC 2006 (vol2; chapter 2) , Table 2.4 | AE45: CNE BNE 2024 | AF45: -
B46: Petróleo 5 | C46: Petróleo Combustible 5 | D46: Fuelóleo residual | E46: Residual Fuel Oil | F46: litros | G46: Líquido | H46: ='1.1 V2 CH2 T2.4'!$F$15 -> 77400 | I46: ='1.1 V2 CH2 T2.4'!$I$15 -> 10 | J46: ='1.1 V2 CH2 T2.4'!$L$15 -> 0.6 | K46: ='1.1 y 1.2CUADROA1 - BNE 2024'!$C$11 -> 0.927 | L46: t/m3 | M46: ='1.1 y 1.2CUADROA1 - BNE 2024'!D$11 -> 10500 | N46: ='1.1 y 1.2CUADROA1 - BNE 2024'!E$11 -> kCal/kg | O46: =IF(G46="Gaseoso", M46*$C$9, M46*$C$8) -> 9975 | P46: =N46 -> kCal/kg | Q46: Sí | R46: =O46*$C$6/$C$7*IF(Q46="Sí",K46*1000,1) -> 0.038714607 | S46: =IF(Q46="Sí","TJ/m3", IF(N46="kcal/m3", "TJ/m3","TJ/kg")) -> TJ/m3 | T46: =H46*$R46 -> 2996.5106 | U46: =I46*$R46 -> 0.38714607 | V46: =J46*$R46 -> 0.023228764 | W46: =IF(S46="TJ/m3", "kg GEI/m3", "kg GEI/kg") -> kg GEI/m3 | X46: =$C$3*T46 -> 2996.5106 | Y46: =U46*$C$4 -> 10.84009 | Z46: =V46*$C$5 -> 6.1556225 | AA46: =IF(S46="TJ/m3", "kg CO2e/m3", "kg CO2e/kg") -> kg CO2e/m3 | AB46: =SUM(X46:Z46)*IF(AND(F46="gramos",S46="TJ/m3")=TRUE(),1/(K46*1000000), IF(AND(F46="gramos",S46="TJ/kg")=TRUE(),1/(1000), IF(AND(F46="kilogramos",S46="TJ/m3")=TRUE(),1/(K46*1000), IF(AND(F46="toneladas",S46="TJ/m3")=TRUE(),1/K46, IF(AND(F46="toneladas",S46="TJ/kg")=TRUE(),1000, IF(AND(S46="TJ/m3",F46="litros")=TRUE(),1/1000, IF(AND(S46="TJ/kg",F46="litros")=TRUE(),K46/1000,1))))))) -> 3.0135063 | AC46: ="kgCO2e/"&F46 -> kgCO2e/litros | AD46: IPCC 2006 (vol2; chapter 2) , Table 2.4 | AE46: CNE BNE 2024 | AF46: -
B47: Petróleo 6 | C47: Petróleo Combustible 6 | D47: Fuelóleo residual | E47: Residual Fuel Oil | F47: metros cúbicos | G47: Líquido | H47: ='1.1 V2 CH2 T2.4'!$F$15 -> 77400 | I47: ='1.1 V2 CH2 T2.4'!$I$15 -> 10 | J47: ='1.1 V2 CH2 T2.4'!$L$15 -> 0.6 | K47: ='1.1 y 1.2CUADROA1 - BNE 2024'!$C$13 -> 0.945 | L47: t/m3 | M47: ='1.1 y 1.2CUADROA1 - BNE 2024'!D$13 -> 10500 | N47: ='1.1 y 1.2CUADROA1 - BNE 2024'!E$13 -> kCal/kg | O47: =IF(G47="Gaseoso", M47*$C$9, M47*$C$8) -> 9975 | P47: =N47 -> kCal/kg | Q47: Sí | R47: =O47*$C$6/$C$7*IF(Q47="Sí",K47*1000,1) -> 0.039466347 | S47: =IF(Q47="Sí","TJ/m3", IF(N47="kcal/m3", "TJ/m3","TJ/kg")) -> TJ/m3 | T47: =H47*$R47 -> 3054.6952 | U47: =I47*$R47 -> 0.39466347 | V47: =J47*$R47 -> 0.023679808 | W47: =IF(S47="TJ/m3", "kg GEI/m3", "kg GEI/kg") -> kg GEI/m3 | X47: =$C$3*T47 -> 3054.6952 | Y47: =U47*$C$4 -> 11.050577 | Z47: =V47*$C$5 -> 6.2751491 | AA47: =IF(S47="TJ/m3", "kg CO2e/m3", "kg CO2e/kg") -> kg CO2e/m3 | AB47: =SUM(X47:Z47)*IF(AND(F47="gramos",S47="TJ/m3")=TRUE(),1/(K47*1000000), IF(AND(F47="gramos",S47="TJ/kg")=TRUE(),1/(1000), IF(AND(F47="kilogramos",S47="TJ/m3")=TRUE(),1/(K47*1000), IF(AND(F47="toneladas",S47="TJ/m3")=TRUE(),1/K47, IF(AND(F47="toneladas",S47="TJ/kg")=TRUE(),1000, IF(AND(S47="TJ/m3",F47="litros")=TRUE(),1/1000, IF(AND(S47="TJ/kg",F47="litros")=TRUE(),K47/1000,1))))))) -> 3072.021 | AC47: ="kgCO2e/"&F47 -> kgCO2e/metros cúbicos | AD47: IPCC 2006 (vol2; chapter 2) , Table 2.4 | AE47: CNE BNE 2024 | AF47: -
B48: Petróleo 6 | C48: Petróleo Combustible 6 | D48: Fuelóleo residual | E48: Residual Fuel Oil | F48: litros | G48: Líquido | H48: ='1.1 V2 CH2 T2.4'!$F$15 -> 77400 | I48: ='1.1 V2 CH2 T2.4'!$I$15 -> 10 | J48: ='1.1 V2 CH2 T2.4'!$L$15 -> 0.6 | K48: ='1.1 y 1.2CUADROA1 - BNE 2024'!$C$13 -> 0.945 | L48: t/m3 | M48: ='1.1 y 1.2CUADROA1 - BNE 2024'!D$13 -> 10500 | N48: ='1.1 y 1.2CUADROA1 - BNE 2024'!E$13 -> kCal/kg | O48: =IF(G48="Gaseoso", M48*$C$9, M48*$C$8) -> 9975 | P48: =N48 -> kCal/kg | Q48: Sí | R48: =O48*$C$6/$C$7*IF(Q48="Sí",K48*1000,1) -> 0.039466347 | S48: =IF(Q48="Sí","TJ/m3", IF(N48="kcal/m3", "TJ/m3","TJ/kg")) -> TJ/m3 | T48: =H48*$R48 -> 3054.6952 | U48: =I48*$R48 -> 0.39466347 | V48: =J48*$R48 -> 0.023679808 | W48: =IF(S48="TJ/m3", "kg GEI/m3", "kg GEI/kg") -> kg GEI/m3 | X48: =$C$3*T48 -> 3054.6952 | Y48: =U48*$C$4 -> 11.050577 | Z48: =V48*$C$5 -> 6.2751491 | AA48: =IF(S48="TJ/m3", "kg CO2e/m3", "kg CO2e/kg") -> kg CO2e/m3 | AB48: =SUM(X48:Z48)*IF(AND(F48="gramos",S48="TJ/m3")=TRUE(),1/(K48*1000000), IF(AND(F48="gramos",S48="TJ/kg")=TRUE(),1/(1000), IF(AND(F48="kilogramos",S48="TJ/m3")=TRUE(),1/(K48*1000), IF(AND(F48="toneladas",S48="TJ/m3")=TRUE(),1/K48, IF(AND(F48="toneladas",S48="TJ/kg")=TRUE(),1000, IF(AND(S48="TJ/m3",F48="litros")=TRUE(),1/1000, IF(AND(S48="TJ/kg",F48="litros")=TRUE(),K48/1000,1))))))) -> 3.072021 | AC48: ="kgCO2e/"&F48 -> kgCO2e/litros | AD48: IPCC 2006 (vol2; chapter 2) , Table 2.4 | AE48: CNE BNE 2024 | AF48: -

Sheet V2 CH2 T2.2
A1: CUADRO 2.2 FACTORES DE EMISIÓN POR DEFECTO PARA LA COMBUSTIÓN ESTACIONARIA EN LAS INDUSTRIAS ENERGÉTICAS (kg de gas de efecto invernadero por TJ sobre una base calórica neta)
A2: Combustible | C2: CO2
C3: Factor de emisión por defecto | D3: Inferior | E3: Superior | F3: Factor de emisión por defecto | G3: Inferior | H3: Superior | I3: Factor de emisión por defecto | J3: Inferior | K3: Superior
A4: Petróleo crudo | C4: 73300 | D4: 71000 | E4: 75500 | F4: 3 | G4: 1 | H4: 10 | I4: 0.6 | J4: 0.2 | K4: 2
A5: Orimulsión | C5: 77000 | D5: 69300 | E5: 85400 | F5: 3 | G5: 1 | H5: 10 | I5: 0.6 | J5: 0.2 | K5: 2
A6: Gas natural licuado | C6: 64200 | D6: 58300 | E6: 70400 | F6: 3 | G6: 1 | H6: 10 | I6: 0.6 | J6: 0.2 | K6: 2
A7: Gasolina | B7: Gasolina para motores | C7: 69300 | D7: 67500 | E7: 73000 | F7: 3 | G7: 1 | H7: 10 | I7: 0.6 | J7: 0.2 | K7: 2
B8: Gasolina para la aviación | C8: 70000 | D8: 67500 | E8: 73000 | F8: 3 | G8: 1 | H8: 10 | I8: 0.6 | J8: 0.2 | K8: 2
B9: Gasolina para motor a reacción | C9: 70000 | D9: 67500 | E9: 73000 | F9: 3 | G9: 1 | H9: 10 | I9: 0.6 | J9: 0.2 | K9: 2
A10: Queroseno para motor a reacción | C10: 71500 | D10: 69700 | E10: 74400 | F10: 3 | G10: 1 | H10: 10 | I10: 0.6 | J10: 0.2 | K10: 2
A11: Otro queroseno | C11: 71900 | D11: 70800 | E11: 73700 | F11: 3 | G11: 1 | H11: 10 | I11: 0.6 | J11: 0.2 | K11: 2
A12: Esquisto bituminoso | C12: 73300 | D12: 67800 | E12: 79200 | F12: 3 | G12: 1 | H12: 10 | I12: 0.6 | J12: 0.2 | K12: 2
A13: Gas/Diesel Oil | C13: 74100 | D13: 72600 | E13: 74800 | F13: 3 | G13: 1 | H13: 10 | I13: 0.6 | J13: 0.2 | K13: 2
A14: Fuelóleo residual | C14: 77400 | D14: 75500 | E14: 78800 | F14: 3 | G14: 1 | H14: 10 | I14: 0.6 | J14: 0.2 | K14: 2
A15: Gases licuados de petróleo | C15: 63100 | D15: 61600 | E15: 65600 | F15: 1 | G15: 0.3 | H15: 3 | I15: 0.1 | J15: 0.03 | K15: 0.3
A16: Etano | C16: 61600 | D16: 56500 | E16: 68600 | F16: 1 | G16: 0.3 | H16: 3 | I16: 0.1 | J16: 0.03 | K16: 0.3
A17: Nafta | C17: 73300 | D17: 69300 | E17: 76300 | F17: 3 | G17: 1 | H17: 10 | I17: 0.6 | J17: 0.2 | K17: 2
A18: Bitumen | C18: 80700 | D18: 73000 | E18: 89900 | F18: 3 | G18: 1 | H18: 10 | I18: 0.6 | J18: 0.2 | K18: 2
A19: Lubricantes | C19: 73300 | D19: 71900 | E19: 75200 | F19: 3 | G19: 1 | H19: 10 | I19: 0.6 | J19: 0.2 | K19: 2
A20: Coque de petróleo | C20: 97500 | D20: 82900 | E20: 115000 | F20: 3 | G20: 1 | H20: 10 | I20: 0.6 | J20: 0.2 | K20: 2
A21: Alimentación a procesos de refinerías | C21: 73300 | D21: 68900 | E21: 76600 | F21: 3 | G21: 1 | H21: 10 | I21: 0.6 | J21: 0.2 | K21: 2
A22: Otro petróleo | B22: Gas de refinería | C22: 57600 | D22: 48200 | E22: 69000 | F22: 1 | G22: 0.3 | H22: 3 | I22: 0.1 | J22: 0.03 | K22: 0.3
B23: Ceras de parafina | C23: 73300 | D23: 72200 | E23: 74400 | F23: 3 | G23: 1 | H23: 10 | I23: 0.6 | J23: 0.2 | K23: 2
B24: Espíritu blanco y SBP | C24: 73300 | D24: 72200 | E24: 74400 | F24: 3 | G24: 1 | H24: 10 | I24: 0.6 | J24: 0.2 | K24: 2
B25: Otros productos del petróleo | C25: 73300 | D25: 72200 | E25: 74400 | F25: 3 | G25: 1 | H25: 10 | I25: 0.6 | J25: 0.2 | K25: 2
A26: Antracita | C26: 98300 | D26: 94600 | E26: 101000 | F26: 1 | G26: 0.3 | H26: 3 | I26: 1.5 | J26: 0.5 | K26: 5
A27: Carbón de coque | C27: 94600 | D27: 87300 | E27: 101000 | F27: 1 | G27: 0.3 | H27: 3 | I27: 1.5 | J27: 0.5 | K27: 5
A28: Otro carbón bituminoso | C28: 94600 | D28: 89500 | E28: 99700 | F28: 1 | G28: 0.3 | H28: 3 | I28: 1.5 | J28: 0.5 | K28: 5
A29: Carbón sub- bituminoso | C29: 96100 | D29: 92800 | E29: 100000 | F29: 1 | G29: 0.3 | H29: 3 | I29: 1.5 | J29: 0.5 | K29: 5
A30: Lignito | C30: 101000 | D30: 90900 | E30: 115000 | F30: 1 | G30: 0.3 | H30: 3 | I30: 1.5 | J30: 0.5 | K30: 5
A31: Esquisto bituminoso y alquitrán | C31: 107000 | D31: 90200 | E31: 125000 | F31: 1 | G31: 0.3 | H31: 3 | I31: 1.5 | J31: 0.5 | K31: 5
A32: Briquetas de carbón de lignito | C32: 97500 | D32: 87300 | E32: 109000 | F32: 1 | G32: 0.3 | H32: 3 | I32: 1.5 | J32: 0.5 | K32: 5
A33: Combustible evidente | C33: 97500 | D33: 87300 | E33: 109000 | F33: 1 | G33: 0.3 | H33: 3 | I33: 1.5 | J33: 0.5 | K33: 5
A34: Coque | B34: Coque para horno de coque y coque de lignito | C34: 107000 | D34: 95700 | E34: 119000 | F34: 1 | G34: 0.3 | H34: 3 | I34: 1.5 | J34: 0.5 | K34: 5
B35: Coque de gas | C35: 107000 | D35: 95700 | E35: 119000 | F35: 1 | G35: 0.3 | H35: 3 | I35: 0.1 | J35: 0.03 | K35: 0.3
A36: Alquitrán de hulla | C36: 80700 | D36: 68200 | E36: 95300 | F36: 1 | G36: 0.3 | H36: 3 | I36: 1.5 | J36: 0.5 | K36: 5
A37: Gases derivados | B37: Gas de fábricas de gas | C37: 44400 | D37: 37300 | E37: 54100 | F37: 1 | G37: 0.3 | H37: 3 | I37: 0.1 | J37: 0.03 | K37: 0.3
B38: Gas de horno de coque | C38: 44400 | D38: 37300 | E38: 54100 | F38: 1 | G38: 0.3 | H38: 3 | I38: 0.1 | J38: 0.03 | K38: 0.3
B39: Gas de alto horno | C39: 260000 | D39: 219000 | E39: 308000 | F39: 1 | G39: 0.3 | H39: 3 | I39: 0.1 | J39: 0.03 | K39: 0.3
B40: Gas de horno de oxígeno para aceros | C40: 182000 | D40: 145000 | E40: 202000 | F40: 1 | G40: 0.3 | H40: 3 | I40: 0.1 | J40: 0.03 | K40: 0.3
A41: Gas natural | C41: 56100 | D41: 54300 | E41: 58300 | F41: 1 | G41: 0.3 | H41: 3 | I41: 0.1 | J41: 0.03 | K41: 0.3
A42: Desechos municipales (fracción no perteneciente a la biomasa) | C42: 91700 | D42: 73300 | E42: 121000 | F42: 30 | G42: 10 | H42: 100 | I42: 4 | J42: 1.5 | K42: 15
A43: Desechos industriales | C43: 143000 | D43: 110000 | E43: 183000 | F43: 30 | G43: 10 | H43: 100 | I43: 4 | J43: 1.5 | K43: 15
A44: Óleos de desecho | C44: 73300 | D44: 72200 | E44: 74400 | F44: 30 | G44: 10 | H44: 100 | I44: 4 | J44: 1.5 | K44: 15
A45: Turba | C45: 106000 | D45: 100000 | E45: 108000 | F45: 1 | G45: 0.3 | H45: 3 | I45: 1.5 | J45: 0.5 | K45: 5
A46: Biocombustibles sólidos | B46: Madera / Desechos de madera | C46: 112000 | D46: 95000 | E46: 132000 | F46: 30 | G46: 10 | H46: 100 | I46: 4 | J46: 1.5 | K46: 15
B47: Lejía de sulfito (licor negro)(a) | C47: 95300 | D47: 80700 | E47: 110000 | F47: 3 | G47: 1 | H47: 18 | I47: 2 | J47: 1 | K47: 21
B48: Otra biomasa sólida primaria | C48: 100000 | D48: 84700 | E48: 117000 | F48: 30 | G48: 10 | H48: 100 | I48: 4 | J48: 1.5 | K48: 15
B49: Carbón vegetal | C49: 112000 | D49: 95000 | E49: 132000 | F49: 200 | G49: 70 | H49: 600 | I49: 4 | J49: 1.5 | K49: 15
A50: Biocombustibles líquidos | B50: Biogasolina | C50: 70800 | D50: 59800 | E50: 84300 | F50: 3 | G50: 1 | H50: 10 | I50: 0.6 | J50: 0.2 | K50: 2
B51: Biodiésel | C51: 70800 | D51: 59800 | E51: 84300 | F51: 3 | G51: 1 | H51: 10 | I51: 0.6 | J51: 0.2 | K51: 2
B52: Otros biocombus tibles líquidos | C52: 79600 | D52: 67100 | E52: 95300 | F52: 3 | G52: 1 | H52: 10 | I52: 0.6 | J52: 0.2 | K52: 2
A53: Biomasa gaseosa | B53: Gas de vertedero | C53: 54600 | D53: 46200 | E53: 66000 | F53: 1 | G53: 0.3 | H53: 3 | I53: 0.1 | J53: 0.03 | K53: 0.3
B54: Gas de digestión de lodos cloacales | C54: 54600 | D54: 46200 | E54: 66000 | F54: 1 | G54: 0.3 | H54: 3 | I54: 0.1 | J54: 0.03 | K54: 0.3
B55: Otro biogás | C55: 54600 | D55: 46200 | E55: 66000 | F55: 1 | G55: 0.3 | H55: 3 | I55: 0.1 | J55: 0.03 | K55: 0.3
A56: Otros combustibles no fósiles | B56: Desechos municipales (fracción pertenecien te a la biomasa) | C56: 100000 | D56: 84700 | E56: 117000 | F56: 30 | G56: 10 | H56: 100 | I56: 4 | J56: 1.5 | K56: 15
A57: (a)Incluye el CO2 derivado de la biomasa emitido desde la unidad de combustión de licor negro y el CO2 derivado de la biomasa emitido desde el horno de cal de la planta de kraft. n Indica un factor de emisión nuevo que no estaba presente en las Directrices del IPCC de 1996. r Indica un factor de emisión que se revisó a partir de las Directrices del IPCC de 1996.

Sheet V2 CH2 T2.3
A1: CUADRO 2.3 FACTORES DE EMISIÓN POR DEFECTO PARA LA COMBUSTIÓN ESTACIONARIA EN LAS INDUSTRIAS MANUFACTURERAS Y DE LA CONSTRUCCIÓN (kg de gas de efecto invernadero por TJ sobre una base calórica neta)
A2: Combustible | C2: CO2
C3: Factor de emisión por defecto | D3: Inferior | E3: Superior | F3: Factor de emisión por defecto | G3: Inferior | H3: Superior | I3: Factor de emisión por defecto | J3: Inferior | K3: Superior
A4: Petróleo crudo | C4: 73300 | D4: 71100 | E4: 75500 | F4: 3 | G4: 1 | H4: 10 | I4: 0.6 | J4: 0.2 | K4: 2
A5: Orimulsión | C5: 77000 | D5: 69300 | E5: 85400 | F5: 3 | G5: 1 | H5: 10 | I5: 0.6 | J5: 0.2 | K5: 2
A6: Gas natural licuado | C6: 64200 | D6: 58300 | E6: 70400 | F6: 3 | G6: 1 | H6: 10 | I6: 0.6 | J6: 0.2 | K6: 2
A7: Gasolina | B7: Gasolina para motores | C7: 69300 | D7: 67500 | E7: 73000 | F7: 3 | G7: 1 | H7: 10 | I7: 0.6 | J7: 0.2 | K7: 2
B8: Gasolina para la aviación | C8: 70000 | D8: 67500 | E8: 73000 | F8: 3 | G8: 1 | H8: 10 | I8: 0.6 | J8: 0.2 | K8: 2
B9: Gasolina para motor a reacción | C9: 70000 | D9: 67500 | E9: 73000 | F9: 3 | G9: 1 | H9: 10 | I9: 0.6 | J9: 0.2 | K9: 2
A10: Queroseno para motor a reacción | C10: 71500 | D10: 69700 | E10: 74400 | F10: 3 | G10: 1 | H10: 10 | I10: 0.6 | J10: 0.2 | K10: 2
A11: Otro queroseno | C11: 71900 | D11: 70800 | E11: 73700 | F11: 3 | G11: 1 | H11: 10 | I11: 0.6 | J11: 0.2 | K11: 2
A12: Esquisto bituminoso | C12: 73300 | D12: 67800 | E12: 79200 | F12: 3 | G12: 1 | H12: 10 | I12: 0.6 | J12: 0.2 | K12: 2
A13: Gas/Diesel Oil | C13: 74100 | D13: 72600 | E13: 74800 | F13: 3 | G13: 1 | H13: 10 | I13: 0.6 | J13: 0.2 | K13: 2
A14: Fuelóleo residual | C14: 77400 | D14: 75500 | E14: 78800 | F14: 3 | G14: 1 | H14: 10 | I14: 0.6 | J14: 0.2 | K14: 2
A15: Gases licuados de petróleo | C15: 63100 | D15: 61600 | E15: 65600 | F15: 1 | G15: 0.3 | H15: 3 | I15: 0.1 | J15: 0.03 | K15: 0.3
A16: Etano | C16: 61600 | D16: 56500 | E16: 68600 | F16: 1 | G16: 0.3 | H16: 3 | I16: 0.1 | J16: 0.03 | K16: 0.3
A17: Nafta | C17: 73300 | D17: 69300 | E17: 76300 | F17: 3 | G17: 1 | H17: 10 | I17: 0.6 | J17: 0.2 | K17: 2
A18: Bitumen | C18: 80700 | D18: 73000 | E18: 89900 | F18: 3 | G18: 1 | H18: 10 | I18: 0.6 | J18: 0.2 | K18: 2
A19: Lubricantes | C19: 73300 | D19: 71900 | E19: 75200 | F19: 3 | G19: 1 | H19: 10 | I19: 0.6 | J19: 0.2 | K19: 2
A20: Coque de petróleo | C20: 97500 | D20: 82900 | E20: 115000 | F20: 3 | G20: 1 | H20: 10 | I20: 0.6 | J20: 0.2 | K20: 2
A21: Alimentación a procesos de refinerías | C21: 73300 | D21: 68900 | E21: 76600 | F21: 3 | G21: 1 | H21: 10 | I21: 0.6 | J21: 0.2 | K21: 2
A22: Otro petróleo | B22: Gas de refinería | C22: 57600 | D22: 48200 | E22: 69000 | F22: 1 | G22: 0.3 | H22: 3 | I22: 0.1 | J22: 0.03 | K22: 0.3
B23: Ceras de parafina | C23: 73300 | D23: 72200 | E23: 74400 | F23: 3 | G23: 1 | H23: 10 | I23: 0.6 | J23: 0.2 | K23: 2
B24: Espíritu blanco y SBP | C24: 73300 | D24: 72200 | E24: 74400 | F24: 3 | G24: 1 | H24: 10 | I24: 0.6 | J24: 0.2 | K24: 2
B25: Otros productos del petróleo | C25: 73300 | D25: 72200 | E25: 74400 | F25: 3 | G25: 1 | H25: 10 | I25: 0.6 | J25: 0.2 | K25: 2
A26: Antracita | C26: 98300 | D26: 94600 | E26: 101000 | F26: 10 | G26: 3 | H26: 30 | I26: 1.5 | J26: 0.5 | K26: 5
A27: Carbón de coque | C27: 94600 | D27: 87300 | E27: 101000 | F27: 10 | G27: 3 | H27: 30 | I27: 1.5 | J27: 0.5 | K27: 5
A28: Otro carbón bituminoso | C28: 94600 | D28: 89500 | E28: 99700 | F28: 10 | G28: 3 | H28: 30 | I28: 1.5 | J28: 0.5 | K28: 5
A29: Carbón sub- bituminoso | C29: 96100 | D29: 92800 | E29: 100000 | F29: 10 | G29: 3 | H29: 30 | I29: 1.5 | J29: 0.5 | K29: 5
A30: Lignito | C30: 101000 | D30: 90900 | E30: 115000 | F30: 10 | G30: 3 | H30: 30 | I30: 1.5 | J30: 0.5 | K30: 5
A31: Esquisto bituminoso y alquitrán | C31: 107000 | D31: 90200 | E31: 125000 | F31: 10 | G31: 3 | H31: 30 | I31: 1.5 | J31: 0.5 | K31: 5
A32: Briquetas de carbón de lignito | C32: 97500 | D32: 87300 | E32: 109000 | F32: 10 | G32: 3 | H32: 30 | I32: 1.5 | J32: 0.5 | K32: 5
A33: Combustible evidente | C33: 97500 | D33: 87300 | E33: 109000 | F33: 10 | G33: 3 | H33: 30 | I33: 1.5 | J33: 0.5 | K33: 5
A34: Coque | B34: Coque para horno de coque y coque de lignito | C34: 107000 | D34: 95700 | E34: 119000 | F34: 10 | G34: 3 | H34: 30 | I34: 1.5 | J34: 0.5 | K34: 5
B35: Coque de gas | C35: 107000 | D35: 95700 | E35: 119000 | F35: 1 | G35: 0.3 | H35: 3 | I35: 0.1 | J35: 0.03 | K35: 0.3
A36: Alquitrán de hulla | C36: 80700 | D36: 68200 | E36: 95300 | F36: 10 | G36: 3 | H36: 30 | I36: 1.5 | J36: 0.5 | K36: 5
A37: Gases derivados | B37: Gas de fábricas de gas | C37: 44400 | D37: 37300 | E37: 54100 | F37: 1 | G37: 0.3 | H37: 3 | I37: 0.1 | J37: 0.03 | K37: 0.3
B38: Gas de horno de coque | C38: 44400 | D38: 37300 | E38: 54100 | F38: 1 | G38: 0.3 | H38: 3 | I38: 0.1 | J38: 0.03 | K38: 0.3
B39: Gas de alto horno | C39: 260000 | D39: 219000 | E39: 308000 | F39: 1 | G39: 0.3 | H39: 3 | I39: 0.1 | J39: 0.03 | K39: 0.3
B40: Gas de horno de oxígeno para aceros | C40: 182000 | D40: 145000 | E40: 202000 | F40: 1 | G40: 0.3 | H40: 3 | I40: 0.1 | J40: 0.03 | K40: 0.3
A41: Gas natural | C41: 56100 | D41: 54300 | E41: 58300 | F41: 1 | G41: 0.3 | H41: 3 | I41: 0.1 | J41: 0.03 | K41: 0.3
A42: Desechos municipales (fracción no perteneciente a la biomasa) | C42: 91700 | D42: 73300 | E42: 121000 | F42: 30 | G42: 10 | H42: 100 | I42: 4 | J42: 1.5 | K42: 15
A43: Desechos industriales | C43: 143000 | D43: 110000 | E43: 183000 | F43: 30 | G43: 10 | H43: 100 | I43: 4 | J43: 1.5 | K43: 15
A44: Óleos de desecho | C44: 73300 | D44: 72200 | E44: 74400 | F44: 30 | G44: 10 | H44: 100 | I44: 4 | J44: 1.5 | K44: 15
A45: Turba | C45: 106000 | D45: 100000 | E45: 108000 | F45: 2 | G45: 0.6 | H45: 6 | I45: 1.5 | J45: 0.5 | K45: 5
A46: Biocombustibles sólidos | B46: Madera / Desechos de madera | C46: 112000 | D46: 95000 | E46: 132000 | F46: 30 | G46: 10 | H46: 100 | I46: 4 | J46: 1.5 | K46: 15
B47: Lejía de sulfito (licor negro)(a) | C47: 95300 | D47: 80700 | E47: 110000 | F47: 3 | G47: 1 | H47: 18 | I47: 2 | J47: 1 | K47: 21
B48: Otra biomasa sólida primaria | C48: 100000 | D48: 84700 | E48: 117000 | F48: 30 | G48: 10 | H48: 100 | I48: 4 | J48: 1.5 | K48: 15
B49: Carbón vegetal | C49: 112000 | D49: 95000 | E49: 132000 | F49: 200 | G49: 70 | H49: 600 | I49: 4 | J49: 1.5 | K49: 15
A50: Biocombustibles líquidos | B50: Biogasolina | C50: 70800 | D50: 59800 | E50: 84300 | F50: 3 | G50: 1 | H50: 10 | I50: 0.6 | J50: 0.2 | K50: 2
B51: Biodiésel | C51: 70800 | D51: 59800 | E51: 84300 | F51: 3 | G51: 1 | H51: 10 | I51: 0.6 | J51: 0.2 | K51: 2
B52: Otros biocombus tibles líquidos | C52: 79600 | D52: 67100 | E52: 95300 | F52: 3 | G52: 1 | H52: 10 | I52: 0.6 | J52: 0.2 | K52: 2
A53: Biomasa gaseosa | B53: Gas de vertedero | C53: 54600 | D53: 46200 | E53: 66000 | F53: 1 | G53: 0.3 | H53: 3 | I53: 0.1 | J53: 0.03 | K53: 0.3
B54: Gas de digestión de lodos cloacales | C54: 54600 | D54: 46200 | E54: 66000 | F54: 1 | G54: 0.3 | H54: 3 | I54: 0.1 | J54: 0.03 | K54: 0.3
B55: Otro biogás | C55: 54600 | D55: 46200 | E55: 66000 | F55: 1 | G55: 0.3 | H55: 3 | I55: 0.1 | J55: 0.03 | K55: 0.3
A56: Otros combustibles no fósiles | B56: Desechos municipales (fracción pertenecien te a la biomasa) | C56: 100000 | D56: 84700 | E56: 117000 | F56: 30 | G56: 10 | H56: 100 | I56: 4 | J56: 1.5 | K56: 15

Sheet 1.2 Combustión móvil
A1: Volver al INICIO
A2: Volver al RESUMEN | B2: Compuesto | C2: Valor | D2: Unidad | E2: Fuente
B3: Dióxido de Carbono (CO2) | C3: ='1.4 AR5 CH8 T8.A.1'!H4 -> 1 | D3: - | E3: AR5
B4: Metano (CH4) | C4: ='1.4 AR5 CH8 T8.A.1'!H5 -> 28 | D4: - | E4: AR5
B5: Óxido Nitroso (N2O) | C5: ='1.4 AR5 CH8 T8.A.1'!H7 -> 265 | D5: - | E5: AR5
B6: 1 kcal | C6: 4.1868 | D6: kJ | E6: IPCC Anex II: Metrics & Methodology
B7: 1 TJ | C7: 1000000000 | D7: kJ
B8: Combustibles sólidos y líquidos | C8: 0.95 | D8: - | E8: IPCC V2 CH1 (int. de confianza 95%)
B9: Combustibles gaseosos | C9: 0.9 | D9: - | E9: IPCC V2 CH1 (int. de confianza 90%)
B11: Huella Organizacional
B12: Emisiones directas
B13: Tipo de fuente: Vehículos de pasajeros o carga
T14: kg GEI/unidad | X14: CO2e/unidad
B15: Nombre en HuellaChile | C15: Nombre en BNE 2020 | D15: Nombre en IPCC ESP | E15: Nombre en IPCC EN | F15: Unidad del dato de actividad | G15: Estado físico del combustible | H15: CO2 kgCO2/TJ | I15: CH4 kgCH4/TJ | J15: N2O kgN2O/TJ | K15: Densidad | L15: Unidad | M15: Poder Calorífico Superior (PCS) | N15: Unidad PCS | O15: Poder Calorífico Inferior (PCI) | P15: Unidad PCI | Q15: Multiplica densidad | R15: PCI | S15: Unidad | T15: CO2 | U15: CH4 | V15: N2O | W15: Unidad | X15: CO2 | Y15: CH4 | Z15: N2O | AA15: Unidad | AB15: kgCO2e total | AC15: Unidad | AD15: Fuente 1 | AE15: Fuente 2 | AF15: Otras fuentes
B16: Petróleo 2 (Diesel) | C16: Petróleo Diésel | D16: Gas/Diesel Oil | E16: Gas/Diesel Oil | F16: metros cúbicos | G16: Líquido | H16: ='1.2 V2 CH3 T3.2.1'!$C$5 -> 74100 | I16: ='1.2 V2 CH3 T3.2.2'!$C$8 -> 3.9 | J16: ='1.2 V2 CH3 T3.2.2'!$F$8 -> 3.9 | K16: ='1.1 y 1.2CUADROA1 - BNE 2024'!$C$20 -> 0.84 | L16: t/m3 | M16: ='1.1 y 1.2CUADROA1 - BNE 2024'!$D$20 -> 10900 | N16: kcal/kg | O16: =IF(G16="Gaseoso", M16*$C$9, M16*$C$8) -> 10355 | P16: =N16 -> kcal/kg | Q16: Sí | R16: =O16*$C$6/$C$7*IF(Q16="Sí",K16*1000,1) -> 0.036417624 | S16: =IF(Q16="Sí","TJ/m3", IF(N16="kcal/m3", "TJ/m3","TJ/kg")) -> TJ/m3 | T16: =H16*$R16 -> 2698.5459 | U16: =I16*$R16 -> 0.14202873 | V16: =J16*$R16 -> 0.14202873 | W16: =IF(S16="TJ/m3", "kg GEI/m3", "kg GEI/kg") -> kg GEI/m3 | X16: =$C$3*T16 -> 2698.5459 | Y16: =$C$4*U16 -> 3.9768045 | Z16: =$C$5*V16 -> 37.637614 | AA16: =IF(S16="TJ/m3", "kg CO2e/m3", "kg CO2e/kg") -> kg CO2e/m3 | AB16: =SUM(X16:Z16)*IF(AND(F16="gramos",S16="TJ/m3")=TRUE(),1/(K16*1000000), IF(AND(F16="gramos",S16="TJ/kg")=TRUE(),1/(1000), IF(AND(F16="kilogramos",S16="TJ/m3")=TRUE(),1/(K16*1000), IF(AND(F16="toneladas",S16="TJ/m3")=TRUE(),1/K16, IF(AND(F16="toneladas",S16="TJ/kg")=TRUE(),1000, IF(AND(S16="TJ/m3",F16="litros")=TRUE(),1/1000, IF(AND(S16="TJ/kg",F16="litros")=TRUE(),K16/1000,1))))))) -> 2740.1603 | AC16: ="kgCO2e/"&F16 -> kgCO2e/metros cúbicos | AD16: IPCC 2006 (vol2; chapter 3) , Table 3.2.1 and Table 3.2.2 | AE16: CNE BNE 2024 | AF16: -
B17: Petróleo 2 (Diesel) | C17: Petróleo Diésel | D17: Gas/Diesel Oil | E17: Gas/Diesel Oil | F17: litros | G17: Líquido | H17: ='1.2 V2 CH3 T3.2.1'!$C$5 -> 74100 | I17: ='1.2 V2 CH3 T3.2.2'!$C$8 -> 3.9 | J17: ='1.2 V2 CH3 T3.2.2'!$F$8 -> 3.9 | K17: ='1.1 y 1.2CUADROA1 - BNE 2024'!$C$20 -> 0.84 | L17: t/m3 | M17: ='1.1 y 1.2CUADROA1 - BNE 2024'!$D$20 -> 10900 | N17: kcal/kg | O17: =IF(G17="Gaseoso", M17*$C$9, M17*$C$8) -> 10355 | P17: =N17 -> kcal/kg | Q17: Sí | R17: =O17*$C$6/$C$7*IF(Q17="Sí",K17*1000,1) -> 0.036417624 | S17: =IF(Q17="Sí","TJ/m3", IF(N17="kcal/m3", "TJ/m3","TJ/kg")) -> TJ/m3 | T17: =H17*$R17 -> 2698.5459 | U17: =I17*$R17 -> 0.14202873 | V17: =J17*$R17 -> 0.14202873 | W17: =IF(S17="TJ/m3", "kg GEI/m3", "kg GEI/kg") -> kg GEI/m3 | X17: =$C$3*T17 -> 2698.5459 | Y17: =$C$4*U17 -> 3.9768045 | Z17: =$C$5*V17 -> 37.637614 | AA17: =IF(S17="TJ/m3", "kg CO2e/m3", "kg CO2e/kg") -> kg CO2e/m3 | AB17: =SUM(X17:Z17)*IF(AND(F17="gramos",S17="TJ/m3")=TRUE(),1/(K17*1000000), IF(AND(F17="gramos",S17="TJ/kg")=TRUE(),1/(1000), IF(AND(F17="kilogramos",S17="TJ/m3")=TRUE(),1/(K17*1000), IF(AND(F17="toneladas",S17="TJ/m3")=TRUE(),1/K17, IF(AND(F17="toneladas",S17="TJ/kg")=TRUE(),1000, IF(AND(S17="TJ/m3",F17="litros")=TRUE(),1/1000, IF(AND(S17="TJ/kg",F17="litros")=TRUE(),K17/1000,1))))))) -> 2.7401603 | AC17: ="kgCO2e/"&F17 -> kgCO2e/litros | AD17: IPCC 2006 (vol2; chapter 3) , Table 3.2.1 and Table 3.2.2 | AE17: CNE BNE 2024 | AF17: -
B18: Gas licuado | C18: Gas Licuado | D18: Gases licuados de petroleo | E18: Liquefied Petroleum Gases | F18: metros cúbicos | G18: Líquido | H18: ='1.2 V2 CH3 T3.2.1'!$C$6 -> 63100 | I18: ='1.2 V2 CH3 T3.2.2'!$C$10 -> 62 | J18: ='1.2 V2 CH3 T3.2.2'!$F$10 -> 0.2 | K18: ='1.1 y 1.2CUADROA1 - BNE 2024'!$C$15 -> 0.55 | L18: t/m3 | M18: ='1.1 y 1.2CUADROA1 - BNE 2024'!$D$15 -> 12100 | N18: kcal/kg | O18: =IF(G18="Gaseoso", M18*$C$9, M18*$C$8) -> 11495 | P18: =N18 -> kcal/kg | Q18: Sí | R18: =O18*$C$6/$C$7*IF(Q18="Sí",K18*1000,1) -> 0.026469996 | S18: =IF(Q18="Sí","TJ/m3", IF(N18="kcal/m3", "TJ/m3","TJ/kg")) -> TJ/m3 | T18: =H18*$R18 -> 1670.2568 | U18: =I18*$R18 -> 1.6411398 | V18: =J18*$R18 -> 0.0052939993 | W18: =IF(S18="TJ/m3", "kg GEI/m3", "kg GEI/kg") -> kg GEI/m3 | X18: =$C$3*T18 -> 1670.2568 | Y18: =$C$4*U18 -> 45.951914 | Z18: =$C$5*V18 -> 1.4029098 | AA18: =IF(S18="TJ/m3", "kg CO2e/m3", "kg CO2e/kg") -> kg CO2e/m3 | AB18: =SUM(X18:Z18)*IF(AND(F18="gramos",S18="TJ/m3")=TRUE(),1/(K18*1000000), IF(AND(F18="gramos",S18="TJ/kg")=TRUE(),1/(1000), IF(AND(F18="kilogramos",S18="TJ/m3")=TRUE(),1/(K18*1000), IF(AND(F18="toneladas",S18="TJ/m3")=TRUE(),1/K18, IF(AND(F18="toneladas",S18="TJ/kg")=TRUE(),1000, IF(AND(S18="TJ/m3",F18="litros")=TRUE(),1/1000, IF(AND(S18="TJ/kg",F18="litros")=TRUE(),K18/1000,1))))))) -> 1717.6116 | AC18: ="kgCO2e/"&F18 -> kgCO2e/metros cúbicos | AD18: IPCC 2006 (vol2; chapter 3) , Table 3.2.1 and Table 3.2.2 | AE18: CNE BNE 2024 | AF18: -
B19: Gas licuado | C19: Gas Licuado | D19: Gases licuados de petroleo | E19: Liquefied Petroleum Gases | F19: litros | G19: Líquido | H19: ='1.2 V2 CH3 T3.2.1'!$C$6 -> 63100 | I19: ='1.2 V2 CH3 T3.2.2'!$C$10 -> 62 | J19: ='1.2 V2 CH3 T3.2.2'!$F$10 -> 0.2 | K19: ='1.1 y 1.2CUADROA1 - BNE 2024'!$C$15 -> 0.55 | L19: t/m3 | M19: ='1.1 y 1.2CUADROA1 - BNE 2024'!$D$15 -> 12100 | N19: kcal/kg | O19: =IF(G19="Gaseoso", M19*$C$9, M19*$C$8) -> 11495 | P19: =N19 -> kcal/kg | Q19: Sí | R19: =O19*$C$6/$C$7*IF(Q19="Sí",K19*1000,1) -> 0.026469996 | S19: =IF(Q19="Sí","TJ/m3", IF(N19="kcal/m3", "TJ/m3","TJ/kg")) -> TJ/m3 | T19: =H19*$R19 -> 1670.2568 | U19: =I19*$R19 -> 1.6411398 | V19: =J19*$R19 -> 0.0052939993 | W19: =IF(S19="TJ/m3", "kg GEI/m3", "kg GEI/kg") -> kg GEI/m3 | X19: =$C$3*T19 -> 1670.2568 | Y19: =$C$4*U19 -> 45.951914 | Z19: =$C$5*V19 -> 1.4029098 | AA19: =IF(S19="TJ/m3", "kg CO2e/m3", "kg CO2e/kg") -> kg CO2e/m3 | AB19: =SUM(X19:Z19)*IF(AND(F19="gramos",S19="TJ/m3")=TRUE(),1/(K19*1000000), IF(AND(F19="gramos",S19="TJ/kg")=TRUE(),1/(1000), IF(AND(F19="kilogramos",S19="TJ/m3")=TRUE(),1/(K19*1000), IF(AND(F19="toneladas",S19="TJ/m3")=TRUE(),1/K19, IF(AND(F19="toneladas",S19="TJ/kg")=TRUE(),1000, IF(AND(S19="TJ/m3",F19="litros")=TRUE(),1/1000, IF(AND(S19="TJ/kg",F19="litros")=TRUE(),K19/1000,1))))))) -> 1.7176116 | AC19: ="kgCO2e/"&F19 -> kgCO2e/litros | AD19: IPCC 2006 (vol2; chapter 3) , Table 3.2.1 and Table 3.2.2 | AE19: CNE BNE 2024 | AF19: -
B20: Gas natural | C20: Gas Natural | D20: Gas natural | E20: Natural gas | F20: metros cúbicos | G20: Gaseoso | H20: ='1.2 V2 CH3 T3.2.1'!$C$9 -> 56100 | I20: ='1.2 V2 CH3 T3.2.2'!$C$9 -> 92 | J20: ='1.2 V2 CH3 T3.2.2'!$F$9 -> 3 | M20: ='1.1 y 1.2CUADROA1 - BNE 2024'!$D$21 -> 9341 | N20: kcal/m3 | O20: =IF(G20="Gaseoso", M20*$C$9, M20*$C$8) -> 8406.9 | P20: =N20 -> kcal/m3 | Q20: No | R20: =O20*$C$6/$C$7*IF(Q20="Sí",K20*1000,1) -> 3.5198009e-05 | S20: =IF(Q20="Sí","TJ/m3", IF(N20="kcal/m3", "TJ/m3","TJ/kg")) -> TJ/m3 | T20: =H20*$R20 -> 1.9746083 | U20: =I20*$R20 -> 0.0032382168 | V20: =J20*$R20 -> 0.00010559403 | W20: =IF(S20="TJ/m3", "kg GEI/m3", "kg GEI/kg") -> kg GEI/m3 | X20: =$C$3*T20 -> 1.9746083 | Y20: =$C$4*U20 -> 0.090670071 | Z20: =$C$5*V20 -> 0.027982417 | AA20: =IF(S20="TJ/m3", "kg CO2e/m3", "kg CO2e/kg") -> kg CO2e/m3 | AB20: =SUM(X20:Z20)*IF(AND(F20="gramos",S20="TJ/m3")=TRUE(),1/(K20*1000000), IF(AND(F20="gramos",S20="TJ/kg")=TRUE(),1/(1000), IF(AND(F20="kilogramos",S20="TJ/m3")=TRUE(),1/(K20*1000), IF(AND(F20="toneladas",S20="TJ/m3")=TRUE(),1/K20, IF(AND(F20="toneladas",S20="TJ/kg")=TRUE(),1000, IF(AND(S20="TJ/m3",F20="litros")=TRUE(),1/1000, IF(AND(S20="TJ/kg",F20="litros")=TRUE(),K20/1000,1))))))) -> 2.0932608 | AC20: ="kgCO2e/"&F20 -> kgCO2e/metros cúbicos | AD20: IPCC 2006 (vol2; chapter 3) , Table 3.2.1 and Table 3.2.2 | AE20: CNE BNE 2024 | AF20: -
B21: Gasolina | C21: Gasolina Motor | D21: Gasolina para motores | E21: Motor Gasoline | F21: metros cúbicos | G21: Líquido | H21: ='1.2 V2 CH3 T3.2.1'!$C$4 -> 69300 | I21: ='1.2 V2 CH3 T3.2.2'!$C$6 -> 25 | J21: ='1.2 V2 CH3 T3.2.2'!$F$6 -> 8 | K21: ='1.1 y 1.2CUADROA1 - BNE 2024'!$C$16 -> 0.73 | L21: t/m3 | M21: ='1.1 y 1.2CUADROA1 - BNE 2024'!$D$16 -> 11200 | N21: kcal/kg | O21: =IF(G21="Gaseoso", M21*$C$9, M21*$C$8) -> 10640 | P21: =N21 -> kcal/kg | Q21: Sí | R21: =O21*$C$6/$C$7*IF(Q21="Sí",K21*1000,1) -> 0.032519713 | S21: =IF(Q21="Sí","TJ/m3", IF(N21="kcal/m3", "TJ/m3","TJ/kg")) -> TJ/m3 | T21: =H21*$R21 -> 2253.6161 | U21: =I21*$R21 -> 0.81299282 | V21: =J21*$R21 -> 0.2601577 | W21: =IF(S21="TJ/m3", "kg GEI/m3", "kg GEI/kg") -> kg GEI/m3 | X21: =$C$3*T21 -> 2253.6161 | Y21: =$C$4*U21 -> 22.763799 | Z21: =$C$5*V21 -> 68.941791 | AA21: =IF(S21="TJ/m3", "kg CO2e/m3", "kg CO2e/kg") -> kg CO2e/m3 | AB21: =SUM(X21:Z21)*IF(AND(F21="gramos",S21="TJ/m3")=TRUE(),1/(K21*1000000), IF(AND(F21="gramos",S21="TJ/kg")=TRUE(),1/(1000), IF(AND(F21="kilogramos",S21="TJ/m3")=TRUE(),1/(K21*1000), IF(AND(F21="toneladas",S21="TJ/m3")=TRUE(),1/K21, IF(AND(F21="toneladas",S21="TJ/kg")=TRUE(),1000, IF(AND(S21="TJ/m3",F21="litros")=TRUE(),1/1000, IF(AND(S21="TJ/kg",F21="litros")=TRUE(),K21/1000,1))))))) -> 2345.3217 | AC21: ="kgCO2e/"&F21 -> kgCO2e/metros cúbicos | AD21: IPCC 2006 (vol2; chapter 3) , Table 3.2.1 and Table 3.2.2 | AE21: CNE BNE 2024 | AF21: -
B22: Gasolina | C22: Gasolina Motor | D22: Gasolina para motores | E22: Motor Gasoline | F22: litros | G22: Líquido | H22: ='1.2 V2 CH3 T3.2.1'!$C$4 -> 69300 | I22: ='1.2 V2 CH3 T3.2.2'!$C$6 -> 25 | J22: ='1.2 V2 CH3 T3.2.2'!$F$6 -> 8 | K22: ='1.1 y 1.2CUADROA1 - BNE 2024'!$C$16 -> 0.73 | L22: t/m3 | M22: ='1.1 y 1.2CUADROA1 - BNE 2024'!$D$16 -> 11200 | N22: kcal/kg | O22: =IF(G22="Gaseoso", M22*$C$9, M22*$C$8) -> 10640 | P22: =N22 -> kcal/kg | Q22: Sí | R22: =O22*$C$6/$C$7*IF(Q22="Sí",K22*1000,1) -> 0.032519713 | S22: =IF(Q22="Sí","TJ/m3", IF(N22="kcal/m3", "TJ/m3","TJ/kg")) -> TJ/m3 | T22: =H22*$R22 -> 2253.6161 | U22: =I22*$R22 -> 0.81299282 | V22: =J22*$R22 -> 0.2601577 | W22: =IF(S22="TJ/m3", "kg GEI/m3", "kg GEI/kg") -> kg GEI/m3 | X22: =$C$3*T22 -> 2253.6161 | Y22: =$C$4*U22 -> 22.763799 | Z22: =$C$5*V22 -> 68.941791 | AA22: =IF(S22="TJ/m3", "kg CO2e/m3", "kg CO2e/kg") -> kg CO2e/m3 | AB22: =SUM(X22:Z22)*IF(AND(F22="gramos",S22="TJ/m3")=TRUE(),1/(K22*1000000), IF(AND(F22="gramos",S22="TJ/kg")=TRUE(),1/(1000), IF(AND(F22="kilogramos",S22="TJ/m3")=TRUE(),1/(K22*1000), IF(AND(F22="toneladas",S22="TJ/m3")=TRUE(),1/K22, IF(AND(F22="toneladas",S22="TJ/kg")=TRUE(),1000, IF(AND(S22="TJ/m3",F22="litros")=TRUE(),1/1000, IF(AND(S22="TJ/kg",F22="litros")=TRUE(),K22/1000,1))))))) -> 2.3453217 | AC22: ="kgCO2e/"&F22 -> kgCO2e/litros | AD22: IPCC 2006 (vol2; chapter 3) , Table 3.2.1 and Table 3.2.2 | AE22: CNE BNE 2024 | AF22: -
B23: Kerosene | C23: Kerosene | D23: Otro queroseno | E23: Other Kerosene | F23: metros cúbicos | G23: Líquido | H23: ='1.2 V2 CH3 T3.2.1'!$C$7 -> 71900 | I23: ='V2 CH2 T2.3'!F$11 -> 3 | J23: ='V2 CH2 T2.3'!I$11 -> 0.6 | K23: ='1.1 y 1.2CUADROA1 - BNE 2024'!$C$19 -> 0.81 | L23: t/m3 | M23: ='1.1 y 1.2CUADROA1 - BNE 2024'!$D$19 -> 11100 | N23: kcal/kg | O23: =IF(G23="Gaseoso", M23*$C$9, M23*$C$8) -> 10545 | P23: =N23 -> kcal/kg | Q23: Sí | R23: =O23*$C$6/$C$7*IF(Q23="Sí",K23*1000,1) -> 0.035761343 | S23: =IF(Q23="Sí","TJ/m3", IF(N23="kcal/m3", "TJ/m3","TJ/kg")) -> TJ/m3 | T23: =H23*$R23 -> 2571.2406 | U23: =I23*$R23 -> 0.10728403 | V23: =J23*$R23 -> 0.021456806 | W23: =IF(S23="TJ/m3", "kg GEI/m3", "kg GEI/kg") -> kg GEI/m3 | X23: =$C$3*T23 -> 2571.2406 | Y23: =$C$4*U23 -> 3.0039528 | Z23: =$C$5*V23 -> 5.6860535 | AA23: =IF(S23="TJ/m3", "kg CO2e/m3", "kg CO2e/kg") -> kg CO2e/m3 | AB23: =SUM(X23:Z23)*IF(AND(F23="gramos",S23="TJ/m3")=TRUE(),1/(K23*1000000), IF(AND(F23="gramos",S23="TJ/kg")=TRUE(),1/(1000), IF(AND(F23="kilogramos",S23="TJ/m3")=TRUE(),1/(K23*1000), IF(AND(F23="toneladas",S23="TJ/m3")=TRUE(),1/K23, IF(AND(F23="toneladas",S23="TJ/kg")=TRUE(),1000, IF(AND(S23="TJ/m3",F23="litros")=TRUE(),1/1000, IF(AND(S23="TJ/kg",F23="litros")=TRUE(),K23/1000,1))))))) -> 2579.9306 | AC23: ="kgCO2e/"&F23 -> kgCO2e/metros cúbicos | AD23: IPCC 2006 (vol2; chapter 3) , Table 3.2.1 and Table 3.2.2 | AE23: CNE BNE 2024 | AF23: IPCC 2006 (vol2; chapter 2), Table 2.3
B24: Kerosene | C24: Kerosene | D24: Otro queroseno | E24: Other Kerosene | F24: litros | G24: Líquido | H24: ='1.2 V2 CH3 T3.2.1'!$C$7 -> 71900 | I24: ='V2 CH2 T2.3'!F$11 -> 3 | J24: ='V2 CH2 T2.3'!I$11 -> 0.6 | K24: ='1.1 y 1.2CUADROA1 - BNE 2024'!$C$19 -> 0.81 | L24: t/m3 | M24: ='1.1 y 1.2CUADROA1 - BNE 2024'!$D$19 -> 11100 | N24: kcal/kg | O24: =IF(G24="Gaseoso", M24*$C$9, M24*$C$8) -> 10545 | P24: =N24 -> kcal/kg | Q24: Sí | R24: =O24*$C$6/$C$7*IF(Q24="Sí",K24*1000,1) -> 0.035761343 | S24: =IF(Q24="Sí","TJ/m3", IF(N24="kcal/m3", "TJ/m3","TJ/kg")) -> TJ/m3 | T24: =H24*$R24 -> 2571.2406 | U24: =I24*$R24 -> 0.10728403 | V24: =J24*$R24 -> 0.021456806 | W24: =IF(S24="TJ/m3", "kg GEI/m3", "kg GEI/kg") -> kg GEI/m3 | X24: =$C$3*T24 -> 2571.2406 | Y24: =$C$4*U24 -> 3.0039528 | Z24: =$C$5*V24 -> 5.6860535 | AA24: =IF(S24="TJ/m3", "kg CO2e/m3", "kg CO2e/kg") -> kg CO2e/m3 | AB24: =SUM(X24:Z24)*IF(AND(F24="gramos",S24="TJ/m3")=TRUE(),1/(K24*1000000), IF(AND(F24="gramos",S24="TJ/kg")=TRUE(),1/(1000), IF(AND(F24="kilogramos",S24="TJ/m3")=TRUE(),1/(K24*1000), IF(AND(F24="toneladas",S24="TJ/m3")=TRUE(),1/K24, IF(AND(F24="toneladas",S24="TJ/kg")=TRUE(),1000, IF(AND(S24="TJ/m3",F24="litros")=TRUE(),1/1000, IF(AND(S24="TJ/kg",F24="litros")=TRUE(),K24/1000,1))))))) -> 2.5799306 | AC24: ="kgCO2e/"&F24 -> kgCO2e/litros | AD24: IPCC 2006 (vol2; chapter 3) , Table 3.2.1 and Table 3.2.2 | AE24: CNE BNE 2024 | AF24: IPCC 2006 (vol2; chapter 2), Table 2.3

Sheet 1.1 V2 CH2 T2.4
B2: CUADRO 2.4 FACTORES DE EMISIÓN POR DEFECTO PARA LA COMBUSTIÓN ESTACIONARIA EN LA CATEGORÍA COMERCIAL/INSTITUCIONAL (kg de gas de efecto invernadero por TJ sobre una base calórica neta)
B3: Combustible | D3: Fuel | F3: CO2 | I3: CH4 | L3: N2O
F4: Factor de emisión por defecto | G4: Inferior | H4: Superior | I4: Factor de emisión por defecto | J4: Inferior | K4: Superior | L4: Factor de emisión por defecto | M4: Inferior | N4: Superior
B5: Petróleo crudo | D5: Crude Oil | F5: 73300 | G5: 71100 | H5: 75500 | I5: 10 | J5: 3 | K5: 30 | L5: 0.6 | M5: 0.2 | N5: 2
B6: Orimulsión | D6: Orimulsion | F6: 77000 | G6: 69300 | H6: 85400 | I6: 10 | J6: 3 | K6: 30 | L6: 0.6 | M6: 0.2 | N6: 2
B7: Gas natural licuado | D7: Natural Gas Liquids | F7: 64200 | G7: 58300 | H7: 70400 | I7: 10 | J7: 3 | K7: 30 | L7: 0.6 | M7: 0.2 | N7: 2
B8: Gasolina | C8: Gasolina para motores | D8: Gasoline | E8: Motor Gasoline | F8: 69300 | G8: 67500 | H8: 73000 | I8: 10 | J8: 3 | K8: 30 | L8: 0.6 | M8: 0.2 | N8: 2
C9: Gasolina para la aviación | E9: Aviation Gasoline | F9: 70000 | G9: 67500 | H9: 73000 | I9: 10 | J9: 3 | K9: 30 | L9: 0.6 | M9: 0.2 | N9: 2
C10: Gasolina para motor a reacción | E10: Jet Gasoline | F10: 70000 | G10: 67500 | H10: 73000 | I10: 10 | J10: 3 | K10: 30 | L10: 0.6 | M10: 0.2 | N10: 2
B11: Queroseno para motor a reacción | D11: Jet Kerosene | F11: 71500 | G11: 69700 | H11: 74400 | I11: 10 | J11: 3 | K11: 30 | L11: 0.6 | M11: 0.2 | N11: 2
B12: Otro queroseno | D12: Other Kerosene | F12: 71900 | G12: 70800 | H12: 73700 | I12: 10 | J12: 3 | K12: 30 | L12: 0.6 | M12: 0.2 | N12: 2
B13: Esquisto bituminoso | D13: Shale Oil | F13: 73300 | G13: 67800 | H13: 79200 | I13: 10 | J13: 3 | K13: 30 | L13: 0.6 | M13: 0.2 | N13: 2
B14: Gas/Diesel Oil | D14: Gas/Diesel Oil | F14: 74100 | G14: 72600 | H14: 74800 | I14: 10 | J14: 3 | K14: 30 | L14: 0.6 | M14: 0.2 | N14: 2
B15: Fuelóleo residual | D15: Residual Fuel Oil | F15: 77400 | G15: 75500 | H15: 78800 | I15: 10 | J15: 3 | K15: 30 | L15: 0.6 | M15: 0.2 | N15: 2
B16: Gases licuados de petróleo | D16: Liquefied Petroleum Gases | F16: 63100 | G16: 61600 | H16: 65600 | I16: 5 | J16: 1.5 | K16: 15 | L16: 0.1 | M16: 0.03 | N16: 0.3
B17: Etano | D17: Ethane | F17: 61600 | G17: 56500 | H17: 68600 | I17: 5 | J17: 1.5 | K17: 15 | L17: 0.1 | M17: 0.03 | N17: 0.3
B18: Nafta | D18: Naphtha | F18: 73300 | G18: 69300 | H18: 76300 | I18: 10 | J18: 3 | K18: 30 | L18: 0.6 | M18: 0.2 | N18: 2
B19: Bitumen | D19: Bitumen | F19: 80700 | G19: 73000 | H19: 89900 | I19: 10 | J19: 3 | K19: 30 | L19: 0.6 | M19: 0.2 | N19: 2
B20: Lubricantes | D20: Lubricants | F20: 73300 | G20: 71900 | H20: 75200 | I20: 10 | J20: 3 | K20: 30 | L20: 0.6 | M20: 0.2 | N20: 2
B21: Coque de petróleo | D21: Petroleum Coke | F21: 97500 | G21: 82900 | H21: 115000 | I21: 10 | J21: 3 | K21: 30 | L21: 0.6 | M21: 0.2 | N21: 2
B22: Alimentación a procesos de refinerías | D22: Refinery Feedstocks | F22: 73300 | G22: 68900 | H22: 76600 | I22: 10 | J22: 3 | K22: 30 | L22: 0.6 | M22: 0.2 | N22: 2
B23: óleo | C23: Gas de refinería | D23: Other Oil | E23: Refinery Gas | F23: 57600 | G23: 48200 | H23: 69000 | I23: 5 | J23: 1.5 | K23: 15 | L23: 0.1 | M23: 0.03 | N23: 0.3
C24: Ceras de parafina | E24: Paraffin Waxes | F24: 73300 | G24: 72200 | H24: 74400 | I24: 10 | J24: 3 | K24: 30 | L24: 0.6 | M24: 0.2 | N24: 2
B25: Otro petr | C25: Espíritu blanco y | E25: White Spirit and SBP | F25: 73300 | G25: 72200 | H25: 74400 | I25: 10 | J25: 3 | K25: 30 | L25: 0.6 | M25: 0.2 | N25: 2
C26: SBP
C27: Otros productos del petróleo | E27: Other Petroleum Products | F27: 73300 | G27: 72200 | H27: 74400 | I27: 10 | J27: 3 | K27: 30 | L27: 0.6 | M27: 0.2 | N27: 2
B28: Antracita | D28: Anthracite | F28: 98300 | G28: 94600 | H28: 101000 | I28: 10 | J28: 3 | K28: 30 | L28: 1.5 | M28: 0.5 | N28: 5
B29: Carbón de coque | D29: Coking Coal | F29: 94600 | G29: 87300 | H29: 101000 | I29: 10 | J29: 3 | K29: 30 | L29: 1.5 | M29: 0.5 | N29: 5
B30: Otro carbón bituminoso | D30: Other Bituminous Coal | F30: 94600 | G30: 89500 | H30: 99700 | I30: 10 | J30: 3 | K30: 30 | L30: 1.5 | M30: 0.5 | N30: 5
B31: Carbón bitumino | C31: sub- so | D31: Sub-Bituminous Coal | F31: 96100 | G31: 92800 | H31: 100000 | I31: 10 | J31: 3 | K31: 30 | L31: 1.5 | M31: 0.5 | N31: 5
B32: Lignito | D32: Lignite | F32: 101000 | G32: 90900 | H32: 115000 | I32: 10 | J32: 3 | K32: 30 | L32: 1.5 | M32: 0.5 | N32: 5
B33: Esquisto bituminoso y alquitrán | D33: Oil Shale and Tar Sands | F33: 107000 | G33: 90200 | H33: 125000 | I33: 10 | J33: 3 | K33: 30 | L33: 1.5 | M33: 0.5 | N33: 5
B34: Brique de ligni | C34: tas de carbón to | D34: Brown Coal Briquettes | F34: 97500 | G34: 87300 | H34: 109000 | I34: 10 | J34: 3 | K34: 30 | L34: 1.5 | M34: 0.5 | N34: 5
B35: Combustible evidente | D35: Patent Fuel | F35: 97500 | G35: 87300 | H35: 109000 | I35: 10 | J35: 3 | K35: 30 | L35: 1.5 | M35: 0.5 | N35: 5
B36: Coque | C36: Coque para horno de coque y coque de lignito | D36: Coke | E36: Coke Oven Coke and Lignite Coke | F36: 107000 | G36: 95700 | H36: 119000 | I36: 10 | J36: 3 | K36: 30 | L36: 1.5 | M36: 0.5 | N36: 4
C37: Coque de gas | E37: Gas Coke | F37: 107000 | G37: 95700 | H37: 119000 | I37: 5 | J37: 1.5 | K37: 15 | L37: 0.1 | M37: 0.03 | N37: 0.3
B38: Alquitrán de hulla | D38: Coal Tar | F38: 80700 | G38: 68200 | H38: 95300 | I38: 10 | J38: 30 | K38: 30 | L38: 1.5 | M38: 0.5 | N38: 5
B39: Gases derivados | C39: Gas de fábricas de gas | D39: Derived Gases | E39: Gas Works Gas | F39: 44400 | G39: 37300 | H39: 54100 | I39: 5 | J39: 1.5 | K39: 15 | L39: 0.1 | M39: 0.03 | N39: 0.3
C40: Gas de horno de coque | E40: Coke Oven Gas | F40: 44400 | G40: 37300 | H40: 54100 | I40: 5 | J40: 1.5 | K40: 15 | L40: 0.1 | M40: 0.03 | N40: 0.3
C41: Gas de alto horno | E41: Blast Furnace Gas | F41: 260000 | G41: 219000 | H41: 308000 | I41: 5 | J41: 1.5 | K41: 15 | L41: 0.1 | M41: 0.03 | N41: 0.3
C42: Gas de horno de oxígeno para aceros | E42: Oxygen Steel Furnace Gas | F42: 182000 | G42: 145000 | H42: 202000 | I42: 5 | J42: 1.5 | K42: 15 | L42: 0.1 | M42: 0.03 | N42: 0.3
B43: Gas natural | D43: Natural Gas | F43: 56100 | G43: 54300 | H43: 58300 | I43: 5 | J43: 1.5 | K43: 15 | L43: 0.1 | M43: 0.03 | N43: 0.3
B44: Desechos municipales (fracción no perteneciente a la biomasa) | D44: Municipal Wastes (non- biomass fraction) | F44: 91700 | G44: 73300 | H44: 121000 | I44: 300 | J44: 100 | K44: 900 | L44: 4 | M44: 1.5 | N44: 15
B45: Desechos industriales | D45: Industrial Wastes | F45: 143000 | G45: 110000 | H45: 183000 | I45: 300 | J45: 100 | K45: 900 | L45: 4 | M45: 1.5 | N45: 15
B46: Óleos de desecho | D46: Waste Oils | F46: 73300 | G46: 72200 | H46: 74400 | I46: 300 | J46: 100 | K46: 900 | L46: 4 | M46: 1.5 | N46: 15
B47: Turba | D47: Peat | F47: 106000 | G47: 100000 | H47: 108000 | I47: 10 | J47: 3 | K47: 30 | L47: 1.4 | M47: 0.5 | N47: 5
B48: Biocombustibles sólidos | C48: Madera / Desechos de madera | D48: Solid Biofuels | E48: Wood / Wood Waste | F48: 112000 | G48: 95000 | H48: 132000 | I48: 300 | J48: 100 | K48: 900 | L48: 4 | M48: 1.5 | N48: 15
C49: Lejía de sulfito (licor negro)(a) | E49: Sulphite lyes (Black Liquor)a | F49: 95300 | G49: 80700 | H49: 110000 | I49: 3 | J49: 1 | K49: 18 | L49: 2 | M49: 1 | N49: 21
C50: Otra biomasa sólida primaria | E50: Other Primary Solid Biomass | F50: 100000 | G50: 84700 | H50: 117000 | I50: 300 | J50: 100 | K50: 900 | L50: 4 | M50: 1.5 | N50: 15
C51: Carbón vegetal | E51: Charcoal | F51: 112000 | G51: 95000 | H51: 132000 | I51: 200 | J51: 70 | K51: 600 | L51: 1 | M51: 0.3 | N51: 3
B52: Biocombustibles líquidos | C52: Biogasolina | D52: Liquid Biofuels | E52: Biogasoline | F52: 70800 | G52: 59800 | H52: 84300 | I52: 10 | J52: 3 | K52: 30 | L52: 0.6 | M52: 0.2 | N52: 2
C53: Biodiésel | E53: Biodiesels | F53: 70800 | G53: 59800 | H53: 84300 | I53: 10 | J53: 3 | K53: 30 | L53: 0.6 | M53: 0.2 | N53: 2
C54: Otros biocombus tibles líquidos | E54: Other Liquid Biofuels | F54: 79600 | G54: 67100 | H54: 95300 | I54: 10 | J54: 3 | K54: 30 | L54: 0.6 | M54: 0.2 | N54: 2
B55: Biomasa gaseosa | C55: Gas de vertedero | D55: Gas Biomass | E55: Landfill Gas | F55: 54600 | G55: 46200 | H55: 66000 | I55: 5 | J55: 1.5 | K55: 15 | L55: 0.1 | M55: 0.03 | N55: 0.3
C56: Gas de digestión de lodos cloacales | E56: Sludge Gas | F56: 54600 | G56: 46200 | H56: 66000 | I56: 5 | J56: 1.5 | K56: 15 | L56: 0.1 | M56: 0.03 | N56: 0.3
C57: Otro biogás | E57: Other Biogas | F57: 54600 | G57: 46200 | H57: 66000 | I57: 5 | J57: 1.5 | K57: 15 | L57: 0.1 | M57: 0.03 | N57: 0.3
B58: Otros combustibles | C58: Desechos municipales (fracción pertenecien te a la biomasa) | D58: Other non- | E58: Municipal Wastes (biomass fraction) | F58: 100000 | G58: 84700 | H58: 117000 | I58: 300 | J58: 100 | K58: 900 | L58: 4 | M58: 1.5 | N58: 15
B59: (a)Incluye el CO2 derivado de la biomasa emitido desde la unidad de combustión de licor negro y el CO2 derivado de la biomasa emitido desde el horno de cal de la planta de kraft. n Indica un factor de emisión nuevo que no estaba presente en las Directrices del IPCC de 1996. r Indica un factor de emisión que se revisó a partir de las Directrices del IPCC de 1996.

Sheet 1.2 V2 CH3 T3.2.1
B2: CUADRO 3.2.1 FACTORES DE EMISIÓN DE CO2 POR DEFECTO DEL TRANSPORTE TERRESTRE Y RANGOS DE INCERTIDUMBRE (a)
B3: Tipo de combustible | C3: Por defecto (kg/TJ) | D3: Inferior | E3: Superior
B4: Gasolina para motores | C4: 69300 | D4: 67500 | E4: 73000
B5: Gas/Diesel Oil | C5: 74100 | D5: 72600 | E5: 74800
B6: Gases licuados de petróleo | C6: 63100 | D6: 61600 | E6: 65600
B7: Queroseno | C7: 71900 | D7: 70800 | E7: 73700
B8: Lubricantes (b) | C8: 73300 | D8: 71900 | E8: 75200
B9: Gas natural comprimido | C9: 56100 | D9: 54300 | E9: 58300
B10: Gas natural licuado | C10: 56100 | D10: 54300 | E10: 58300
B11: Fuente: Cuadro 1.4 del capítulo Introducción del Volumen Energía. Notas: a Los valores representan el 100 por ciento de oxidación del contenido de carbono del combustible. b Véase el Recuadro 3.2.4 Lubricantes en la combustión móvil para obtener una orientación acerca de los usos de los lubricantes.

Sheet 1.2 V2 CH3 T3.2.2
B2: CUADRO 3.2.2 FACTORES DE EMISIÓN POR DEFECTO DE N2O Y CH4 DEL TRANSPORTE TERRESTRE Y RANGOS DE INCERTIDUMBRE (a)
B3: Tipo de combustible / Categoría representativa de vehículo | C3: CH4 (kg/TJ) | F3: N2O (kg/TJ)
C4: Por defecto (kg/TJ) | D4: Inferior | E4: Superior | F4: Por defecto (kg/TJ) | G4: Inferior | H4: Superior
B5: Gasolina para motores - sin controlar (b) | C5: 33 | D5: 9.6 | E5: 110 | F5: 3.2 | G5: 0.96 | H5: 11
B6: Gasolina para motores - catalizador de oxidación (c) | C6: 25 | D6: 7.5 | E6: 86 | F6: 8 | G6: 2.6 | H6: 24
B7: Gasolina para motores - vehículo para servicio con poco kilometraje, modelo 1995 o más nuevo (d) | C7: 3.8 | D7: 1.1 | E7: 13 | F7: 5.7 | G7: 1.9 | H7: 17
B8: Gas/Diesel Oil (e) | C8: 3.9 | D8: 1.6 | E8: 9.5 | F8: 3.9 | G8: 1.3 | H8: 12
B9: Gas natural (f) | C9: 92 | D9: 50 | E9: 1540 | F9: 3 | G9: 1 | H9: 77
B10: Gas licuado de petróleo (g) | C10: 62 | D10: na | E10: na | F10: 0.2 | G10: na | H10: na
B11: Etanol, camiones Estados Unidos (h) | C11: 260 | D11: 77 | E11: 880 | F11: 41 | G11: 13 | H11: 123
B12: Etanol, cautomóviles, Brasil (i) | C12: 18 | D12: 13 | E12: 84 | F12: na | G12: na | H12: na
B13: Fuentes: USEPA (2004b), AEMA (2005a), TNO (2003) y Borsari (2005) CETESB (2004 & 2005) con las hipótesis que se presentan a continuación Se derivaron los rangos de incertidumbre de los datos incluidos en Lipman y Delucchi (2002), con excepción del etanol en los automóviles. (a) Con excepción de los automóviles que funcionan con GLP y etanol, los valores por defecto se derivan de las fuentes indicadas con los valores VCN declarados en el capítulo Introducción del volumen Energía, los valores de densidad declarados por la Administración de Información de Energía de Estados Unidos; y los siguientes valores de consumo de combustible supuestos y representativos: 10 km/l para los vehículos con motores para gasolina; 5 km/l para los vehículos diesel; 9 km/l para los vehículos a gas natural (se supone que es equivalente a los vehículos a gasolina); 9 km/l para los vehículos que funcionan con etanol. Si están disponibles los valores reales y representativos de la economía del combustible, se recomienda utilizarlos con los datos de uso total de combustible, para estimar los datos totales de distancias recorridas, que luego deben multiplicarse por los factores de emisión del Nivel 2 para N2O y CH4. (b) El valor por defecto sin controlar de la gasolina para motores se basa en el valor de USEPA (2004b) para un vehículo ligero a gasolina de los Estados Unidos (automóvil): sin controlar, convertido con los valores y las hipótesis descritos en la nota (a) del cuadro. Si las motocicletas representan una parte significativa de la población nacional de vehículos, los compiladores del inventario deben ajustar hacia abajo el factor de emisión por defecto dado. (c) Gasolina para motores: el valor por defecto del catalizador de oxidación de los vehículos ligeros se basa en el valor de USEPA (2004b) para un vehículo ligero a gasolina de los Estados Unidos (automóvil): catalizador de oxidación, convertido con los valores y las hipótesis descritos en la nota (a) del cuadro. Si las motocicletas representan una parte significativa de la población nacional de vehículos, los compiladores del inventario deben ajustar hacia abajo el factor de emisión por defecto dado. (d) Gasolina para motores: el valor por defecto de los vehículos ligeros modelo 1995 o más nuevos se basa en el valor de USEPA (2004b) para un vehículo ligero a gasolina de los Estados Unidos (automóvil): Nivel 1, convertido con los valores y las hipótesis descritos en la nota (a) del cuadro. Si las motocicletas representan una parte significativa de la población nacional de vehículos, los compiladores del inventario deben ajustar hacia abajo el factor de emisión por defecto dado. (e) El valor diesel por defecto se basa en el valor de la AEMA (2005a) para un camión pesado diesel europeo, convertido con los valores y las hipótesis descritos en la nota (a) del cuadro. (f) Los valores por defecto e inferiores del gas natural se basaron en un estudio de TNO (2003), realizado usando vehículos europeos y ciclos de pruebas en los Países Bajos. Hay mucha incertidumbre para el N2O. La USEPA (2004b) tiene un valor por defecto de 350 kg CH4/TJ y 28 kg N2O/TJ para un automóvil de GNC de Estados Unidos, convertido usando los valores y las hipótesis descritos en la nota (a) del cuadro. Los límites superior e inferior también fueron tomados de USEPA (2004b) (g) El valor por defecto para las emisiones de metano del GLP, considerando para un valor de calefacción bajo de 50 MJ/kg y se obtuvo 3,1 g CH4/kg GLP de TNO (2003). No se proporcionaron rangos de incertidumbre. (h) El valor por defecto del etanol se basa en el valor de la USEPA (2004b) para un camión pesado a etanol de Estados Unidos, convertido con los valores y las hipótesis descritos en la nota (a) del cuadro. (i) Datos obtenidos en vehículos brasileños por Borsari (2005) y CETESB (2004 & 2005). Para los modelos 2003 nuevos, el mejor caso es: 51,3 kg THC/TJ combustible y 26,0 por ciento de CH4 en THC. Para los vehículos de 5 años de antigüedad: 67 kg THC/TJ combustible y 27,2 por ciento de CH4 en THC. Para los de 10 años de antigüedad: 308 kg THC/TJ combustible y 27,2 por ciento de CH4 en THC.

Sheet 1.1 y 1.2CUADROA1 - BNE 2024
B2: Densidades y Poderes Caloríficos
B3: Utilizados en el Balance
B6: BNE 2024
B7: Producto | C7: Densidad Ton/m3 | D7: Poder Calorífico | E7: Unidad
B9: Petróleo Crudo Nacional | C9: 0.8245 | D9: 10963 | E9: kCal/kg
B10: Petróleo Crudo Importado | C10: 0.855 | D10: 10860 | E10: kCal/kg
B11: Petróleo Combustible 5 | C11: 0.927 | D11: 10500 | E11: kCal/kg
B12: Petróleo Combustible IFO 180 | C12: 0.936 | D12: 10500 | E12: kCal/kg
B13: Petróleo Combustible 6 | C13: 0.945 | D13: 10500 | E13: kCal/kg
B14: Nafta | C14: 0.7 | D14: 11500 | E14: kCal/kg
B15: Gas Licuado | C15: 0.55 | D15: 12100 | E15: kCal/kg
B16: Gasolina Motor | C16: 0.73 | D16: 11200 | E16: kCal/kg
B17: Gasolina de Aviación | C17: 0.7 | D17: 11400 | E17: kCal/kg
B18: Kerosene de Aviación | C18: 0.81 | D18: 11100 | E18: kCal/kg
B19: Kerosene | C19: 0.81 | D19: 11100 | E19: kCal/kg
B20: Petróleo Diésel | C20: 0.84 | D20: 10900 | E20: kCal/kg
B21: Gas Natural | C21: - | D21: 9341 | E21: kCal/m3
B22: Gas Natural Licuado | C22: 0.45 | D22: 9555 | E22: kCal/m3
B23: Biomasa | C23: - | D23: 3500 | E23: kCal/kg
B24: Licor Negro | C24: - | D24: 2885 | E24: kCal/kg
B25: Pellet de Biomasa | C25: 0.6 | D25: 3941 | E25: kCal/kg
B26: Carbón | C26: - | D26: 7000 | E26: kCal/kg
B27: Coque Mineral | C27: - | D27: 7000 | E27: kCal/kg
B28: Coque de Petróleo | C28: - | D28: 8100 | E28: kCal/kg
B29: Biogás | C29: - | D29: 5600 | E29: kCal/m3
B30: Gas de Refinería | C30: - | D30: 4260 | E30: kCal/m3
B31: Electricidad | C31: - | D31: 860 | E31: kCal/kWh
B33: Elaboración: Ministerio de Energía, Enero 2026

Sheet V2 CH3 T3.3.1
B2: TABLE 3.3.1 DEFAULT EMISSION FACTORS FOR OFF-ROAD MOBILE SOURCES AND MACHINERY (a)
C3: CO2 | F3: (b) CH4 | I3: N2O (c)
B4: Off- Road Source | C4: Default (kg/TJ) | D4: Lower | E4: Upper | F4: Default (kg/TJ) | G4: Lower | H4: Upper | I4: Default (kg/TJ) | J4: Lower | K4: Upper
B5: Diesel
B6: Agriculture | C6: 74100 | D6: 72600 | E6: 74800 | F6: 4.15 | G6: 1.67 | H6: 10.4 | I6: 28.6 | J6: 14.3 | K6: 85.8
B7: Forestry | C7: 74100 | D7: 72600 | E7: 74800 | F7: 4.15 | G7: 1.67 | H7: 10.4 | I7: 28.6 | J7: 14.3 | K7: 85.8
B8: Industry | C8: 74100 | D8: 72600 | E8: 74800 | F8: 4.15 | G8: 1.67 | H8: 10.4 | I8: 28.6 | J8: 14.3 | K8: 85.8
B9: Household | C9: 74100 | D9: 72600 | E9: 74800 | F9: 4.15 | G9: 1.67 | H9: 10.4 | I9: 28.6 | J9: 14.3 | K9: 85.8
B10: Motor Gasoline 4-Stroke
B11: Agriculture | C11: 69300 | D11: 67500 | E11: 73000 | F11: 80 | G11: 32 | H11: 200 | I11: 2 | J11: 1 | K11: 6
B12: Forestry | C12: 69300 | D12: 67500 | E12: 73000
B13: Industry | C13: 69300 | D13: 67500 | E13: 73000 | F13: 50 | G13: 20 | H13: 125 | I13: 2 | J13: 1 | K13: 6
B14: Household | C14: 69300 | D14: 67500 | E14: 73000 | F14: 120 | G14: 48 | H14: 300 | I14: 2 | J14: 1 | K14: 6
B15: Motor Gasoline 2-Stroke
B16: Agriculture | C16: 69300 | D16: 67500 | E16: 73000 | F16: 140 | G16: 56 | H16: 350 | I16: 0.4 | J16: 0.2 | K16: 1.2
B17: Forestry | C17: 69300 | D17: 67500 | E17: 73000 | F17: 170 | G17: 68 | H17: 425 | I17: 0.4 | J17: 0.2 | K17: 1.2
B18: Industry | C18: 69300 | D18: 67500 | E18: 73000 | F18: 130 | G18: 52 | H18: 325 | I18: 0.4 | J18: 0.2 | K18: 1.2
B19: Household | C19: 69300 | D19: 67500 | E19: 73000 | F19: 180 | G19: 72 | H19: 450 | I19: 0.4 | J19: 0.2 | K19: 1.2
B20: Source: EEA 2005. Note: CO2 emission factor values represent full carbon content. a Data provided in Table 3.3.1 are based on European off-road mobile sources and machinery. For gasoline, in case fuel consumption by sector is not discriminated, default values may be obtained according to national circumstances, e.g. prevalence of a given sector or weighting by activity b Including diurnal, soak and running losses. c In general, off-road vehicles do not have emission control catalysts installed (there may be exceptions among off-road vehicles in urban areas, such as ground support equipment used in urban airports and harbours). Properly operating catalysts convert nitrogen oxides to N2O and CH4 to CO2. However, exposure of catalysts to high-sulphur or leaded fuels, even once, causes permanent deterioration (Walsh, 2003). This effect, if applicable, should be considered when adjusting emission factors.

Sheet V2 CH3 T3.4.1
B2: TABLE 3.4.1 DEFAULT EMISSION FACTORS FOR THE MOST COMMON FUELS USED FOR RAIL TRANSPORT
B3: Gas | C3: Diesel (kg/TJ) | F3: Sub-bituminous Coal (kg/TJ)
C4: Default | D4: Lower | E4: Upper | F4: Default | G4: Lower | H4: Upper
B5: CO2 | C5: 74100 | D5: 72600 | E5: 74800 | F5: 96100 | G5: 72800 | H5: 100000
B6: CH4 1 | C6: 4.15 | D6: 1.67 | E6: 10.4 | F6: 2 | G6: 0.6 | H6: 6
B7: N2O 1 | C7: 28.6 | D7: 14.3 | E7: 85.8 | F7: 1.5 | G7: 0.5 | H7: 5
B8: Notes: 1 For an average fuel consumption of 0.35 litres per bhp-hr (break horse power-hour) for a 4000 HP locomotive, (0.47 litres per kWh for a 2983 kW locomotive).(Dunn, 2001). 2 The emission factors for diesel are derived from (EEA, 2005) (Table 8-1), while for coal from Table 2.2 of the Stationary Combustion chapter.

Sheet V2 CH3 T3.5.2
B2: TABLE 3.5.2 CO2 EMISSION FACTORS
B3: kg/TJ
B4: Fuel | D4: Default | E4: Lower | F4: Upper
B5: Gasoline | D5: 69300 | E5: 67500 | F5: 73000
B6: Other Kerosene | D6: 71900 | E6: 70800 | F6: 73600
B7: Gas/Diesel Oil | D7: 74100 | E7: 72600 | F7: 74800
B8: Residual Fuel Oil | D8: 77400 | E8: 75500 | F8: 78800
B9: Liquefied Petroleum Gases | D9: 63100 | E9: 61600 | F9: 65600
B10: Other Oil | C10: Refinery Gas | D10: 57600 | E10: 48200 | F10: 69000
C11: Paraffin Waxes | D11: 73300 | E11: 72200 | F11: 74400
C12: White Spirit & SBP | D12: 73300 | E12: 72200 | F12: 74400
C13: Other Petroleum Products | D13: 73300 | E13: 72200 | F13: 74400
B14: Natural Gas | D14: 56100 | E14: 54300 | F14: 58300

Sheet V2 CH3 T3.5.3
B2: TABLE 3.5.3 DEFAULT WATER-BORNE NAVIGATION CH4 AND N2O EMISSION FACTORS
D3: CH4 (kg/TJ) | E3: +-% | F3: N2O (kg/TJ) | G3: +-%
B4: Ocean-going Ships * | D4: 7 | E4: 0.5 | F4: 2 | G4: +140% -40%
B5: *Default values derived for diesel engines using heavy fuel oil. Source: Lloyd’s Register (1995) and EC (2002)

Sheet V2 CH3 T3.6.4
B2: TABLE 3.6.4 CO2 EMISSION FACTORS
B3: Fuel | C3: Default (kg/TJ) | D3: Lower | E3: Upper
B4: Aviation Gasoline | C4: 70000 | D4: 67500 | E4: 73000
B5: Jet Kerosene | C5: 71500 | D5: 69800 | E5: 74400

Sheet V2 CH3 T3.6.5
B2: TABLE 3.6.5 NON-CO2 EMISSION FACTORS
B3: Fuel | C3: CH4 Default (Uncontrolled) Factors (in kg/TJ) | D3: N2O Default (Uncontrolled) Factors (in kg/TJ) | E3: NOx Default (Uncontrolled) Factors (in kg/TJ)
B4: All fuels | C4: 0.5 | D4: 2 | E4: 250
C5: (-57%/+100%)b | D5: (-70%/+150%) b | E5: +25% c
B6: a In the cruise mode CH4 emissions are assumed to be negligible (Wiesen et al., 1994). For LTO cycles only (i.e., below an altitude of 914 metres (3000 ft.)) the emission factor is 5 kg/TJ (10% of total VOC factor) (Olivier, 1991). Since globally about 10% of the total fuel is consumed in LTO cycles (Olivier, 1995), the resulting fleet averaged factor is 0.5 kg/TJ. b IPCC, 1999. c Expert Judgement. Emission factors for other gases (CO and NMVOC) and sulphur content which were included in the 1996 IPCC Guidelines can be found in the EFDB.

Sheet 1.3 Procesos industriales
A1: Volver al INICIO
A2: Volver al RESUMEN | B2: Compuesto | C2: Valor | D2: Unidad | E2: Fuente
B3: Dióxido de Carbono (CO2) | C3: 1 | D3: - | E3: AR5
B4: Metano (CH4) | C4: 28 | D4: - | E4: AR5
B5: Óxido Nitroso (N2O) | C5: 265 | D5: - | E5: AR5
B7: Huella Organizacional
B8: Procesos industriales
B9: Producción minerales
B11: Nombre en HuellaChile | C11: Unidad del dato de actividad | D11: CO2 (kg GEI/ unidad) | E11: CH4 (kg GEI/ unidad) | F11: N2O (kg GEI/ unidad) | G11: HFC (kg GEI/ unidad) | H11: PFC (kg GEI/ unidad) | I11: SF6 (kg GEI/ unidad) | J11: NF3 (kg GEI/ unidad) | K11: Unidad | L11: CO2 (kg CO2e/ unidad) | M11: CH4 (kg CO2e/ unidad) | N11: N2O (kg CO2e/ unidad) | O11: HFC (kg CO2e/ unidad) | P11: PFC (kg CO2e/ unidad) | Q11: SF6 (kg CO2e/ unidad) | R11: NF3 (kg CO2e/ unidad) | S11: Unidad | T11: CO2e (kg CO2e/ unidad) | U11: Unidad | V11: Fuente
B12: Producción de cemento | C12: toneladas | D12: ='1.3 P.I. Cemento'!P5*1000 -> 316.8324 | E12: 0 | F12: 0 | G12: 0 | H12: 0 | I12: 0 | J12: 0 | K12: ="kg GEI/"&C12 -> kg GEI/toneladas | L12: =D12*$C$3 -> 316.8324 | M12: =E12*$C$4 -> 0 | N12: =F12*$C$5 -> 0 | O12: 0 | P12: 0 | Q12: 0 | R12: 0 | S12: ="kgCO2e/"&C12 -> kgCO2e/toneladas | T12: =SUM(L12:R12) -> 316.8324 | U12: =S12 -> kgCO2e/toneladas | V12: INGEI + IPCC 2006. Ver su hoja correspondiente para más detalles.
B13: Producción de cemento | C13: kilogramos | D13: ='1.3 P.I. Cemento'!P5*1000/1000 -> 0.3168324 | E13: 0 | F13: 0 | G13: 0 | H13: 0 | I13: 0 | J13: 0 | K13: ="kg GEI/"&C13 -> kg GEI/kilogramos | L13: =D13*$C$3 -> 0.3168324 | M13: =E13*$C$4 -> 0 | N13: =F13*$C$5 -> 0 | O13: 0 | P13: 0 | Q13: 0 | R13: 0 | S13: ="kgCO2e/"&C13 -> kgCO2e/kilogramos | T13: =SUM(L13:R13) -> 0.3168324 | U13: =S13 -> kgCO2e/kilogramos | V13: INGEI + IPCC 2006. Ver su hoja correspondiente para más detalles.
B14: Producción de cemento | C14: gramos | D14: ='1.3 P.I. Cemento'!P5*1000/1000000 -> 0.0003168324 | E14: 0 | F14: 0 | G14: 0 | H14: 0 | I14: 0 | J14: 0 | K14: ="kg GEI/"&C14 -> kg GEI/gramos | L14: =D14*$C$3 -> 0.0003168324 | M14: =E14*$C$4 -> 0 | N14: =F14*$C$5 -> 0 | O14: 0 | P14: 0 | Q14: 0 | R14: 0 | S14: ="kgCO2e/"&C14 -> kgCO2e/gramos | T14: =SUM(L14:R14) -> 0.0003168324 | U14: =S14 -> kgCO2e/gramos | V14: INGEI + IPCC 2006. Ver su hoja correspondiente para más detalles.
B15: Producción de cal | C15: toneladas | D15: ='1.3 P.I. Cal'!Q10*1000 -> 695.1277 | E15: 0 | F15: 0 | G15: 0 | H15: 0 | I15: 0 | J15: 0 | K15: ="kg GEI/"&C15 -> kg GEI/toneladas | L15: =D15*$C$3 -> 695.1277 | M15: =E15*$C$4 -> 0 | N15: =F15*$C$5 -> 0 | O15: 0 | P15: 0 | Q15: 0 | R15: 0 | S15: ="kgCO2e/"&C15 -> kgCO2e/toneladas | T15: =SUM(L15:R15) -> 695.1277 | U15: =S15 -> kgCO2e/toneladas | V15: INGEI + IPCC 2006. Ver su hoja correspondiente para más detalles.
B16: Producción de cal | C16: kilogramos | D16: ='1.3 P.I. Cal'!Q10*1000/1000 -> 0.6951277 | E16: 0 | F16: 0 | G16: 0 | H16: 0 | I16: 0 | J16: 0 | K16: ="kg GEI/"&C16 -> kg GEI/kilogramos | L16: =D16*$C$3 -> 0.6951277 | M16: =E16*$C$4 -> 0 | N16: =F16*$C$5 -> 0 | O16: 0 | P16: 0 | Q16: 0 | R16: 0 | S16: ="kgCO2e/"&C16 -> kgCO2e/kilogramos | T16: =SUM(L16:R16) -> 0.6951277 | U16: =S16 -> kgCO2e/kilogramos | V16: INGEI + IPCC 2006. Ver su hoja correspondiente para más detalles.
B17: Producción de cal | C17: gramos | D17: ='1.3 P.I. Cal'!Q10*1000/1000000 -> 0.00069512771 | E17: 0 | F17: 0 | G17: 0 | H17: 0 | I17: 0 | J17: 0 | K17: ="kg GEI/"&C17 -> kg GEI/gramos | L17: =D17*$C$3 -> 0.00069512771 | M17: =E17*$C$4 -> 0 | N17: =F17*$C$5 -> 0 | O17: 0 | P17: 0 | Q17: 0 | R17: 0 | S17: ="kgCO2e/"&C17 -> kgCO2e/gramos | T17: =SUM(L17:R17) -> 0.00069512771 | U17: =S17 -> kgCO2e/gramos | V17: INGEI + IPCC 2006. Ver su hoja correspondiente para más detalles.
B18: Producción de vidrio | C18: toneladas | D18: ='1.3 P.I. Vidrio'!N8*1000 -> 145.16437 | E18: 0 | F18: 0 | G18: 0 | H18: 0 | I18: 0 | J18: 0 | K18: ="kg GEI/"&C18 -> kg GEI/toneladas | L18: =D18*$C$3 -> 145.16437 | M18: =E18*$C$4 -> 0 | N18: =F18*$C$5 -> 0 | O18: 0 | P18: 0 | Q18: 0 | R18: 0 | S18: ="kgCO2e/"&C18 -> kgCO2e/toneladas | T18: =SUM(L18:R18) -> 145.16437 | U18: =S18 -> kgCO2e/toneladas | V18: INGEI + IPCC 2006. Ver su hoja correspondiente para más detalles.
B19: Producción de vidrio | C19: kilogramos | D19: ='1.3 P.I. Vidrio'!N8*1000/1000 -> 0.14516437 | E19: 0 | F19: 0 | G19: 0 | H19: 0 | I19: 0 | J19: 0 | K19: ="kg GEI/"&C19 -> kg GEI/kilogramos | L19: =D19*$C$3 -> 0.14516437 | M19: =E19*$C$4 -> 0 | N19: =F19*$C$5 -> 0 | O19: 0 | P19: 0 | Q19: 0 | R19: 0 | S19: ="kgCO2e/"&C19 -> kgCO2e/kilogramos | T19: =SUM(L19:R19) -> 0.14516437 | U19: =S19 -> kgCO2e/kilogramos | V19: INGEI + IPCC 2006. Ver su hoja correspondiente para más detalles.
B20: Producción de vidrio | C20: gramos | D20: ='1.3 P.I. Vidrio'!N8*1000/1000000 -> 0.00014516437 | E20: 0 | F20: 0 | G20: 0 | H20: 0 | I20: 0 | J20: 0 | K20: ="kg GEI/"&C20 -> kg GEI/gramos | L20: =D20*$C$3 -> 0.00014516437 | M20: =E20*$C$4 -> 0 | N20: =F20*$C$5 -> 0 | O20: 0 | P20: 0 | Q20: 0 | R20: 0 | S20: ="kgCO2e/"&C20 -> kgCO2e/gramos | T20: =SUM(L20:R20) -> 0.00014516437 | U20: =S20 -> kgCO2e/gramos | V20: INGEI + IPCC 2006. Ver su hoja correspondiente para más detalles.
B21: Producción de coke | C21: toneladas | D21: ='1.3 P.I. Hierro, Acero y Coque'!$N$11*1000 -> 560 | E21: ='1.3 P.I. Hierro, Acero y Coque'!O11*1000 -> 0.0001 | F21: 0 | G21: 0 | H21: 0 | I21: 0 | J21: 0 | K21: ="kg GEI/"&C21 -> kg GEI/toneladas | L21: =D21*$C$3 -> 560 | M21: =E21*$C$4 -> 0.0028 | N21: =F21*$C$5 -> 0 | O21: 0 | P21: 0 | Q21: 0 | R21: 0 | S21: ="kgCO2e/"&C21 -> kgCO2e/toneladas | T21: =SUM(L21:R21) -> 560.0028 | U21: =S21 -> kgCO2e/toneladas | V21: INGEI + IPCC 2006. Ver su hoja correspondiente para más detalles.
B22: Producción de coke | C22: kilogramos | D22: ='1.3 P.I. Hierro, Acero y Coque'!$N$11*1000/1000 -> 0.56 | E22: ='1.3 P.I. Hierro, Acero y Coque'!O11*1000/1000 -> 1e-07 | F22: 0 | G22: 0 | H22: 0 | I22: 0 | J22: 0 | K22: ="kg GEI/"&C22 -> kg GEI/kilogramos | L22: =D22*$C$3 -> 0.56 | M22: =E22*$C$4 -> 2.8e-06 | N22: =F22*$C$5 -> 0 | O22: 0 | P22: 0 | Q22: 0 | R22: 0 | S22: ="kgCO2e/"&C22 -> kgCO2e/kilogramos | T22: =SUM(L22:R22) -> 0.5600028 | U22: =S22 -> kgCO2e/kilogramos | V22: INGEI + IPCC 2006. Ver su hoja correspondiente para más detalles.
B23: Producción de coke | C23: gramos | D23: ='1.3 P.I. Hierro, Acero y Coque'!$N$11*1000/1000000 -> 0.00056 | E23: ='1.3 P.I. Hierro, Acero y Coque'!O11*1000/1000000 -> 1e-10 | F23: 0 | G23: 0 | H23: 0 | I23: 0 | J23: 0 | K23: ="kg GEI/"&C23 -> kg GEI/gramos | L23: =D23*$C$3 -> 0.00056 | M23: =E23*$C$4 -> 2.8e-09 | N23: =F23*$C$5 -> 0 | O23: 0 | P23: 0 | Q23: 0 | R23: 0 | S23: ="kgCO2e/"&C23 -> kgCO2e/gramos | T23: =SUM(L23:R23) -> 0.0005600028 | U23: =S23 -> kgCO2e/gramos | V23: INGEI + IPCC 2006. Ver su hoja correspondiente para más detalles.
B26: Huella Organizacional
B27: Procesos industriales
B28: Producción de metal
B30: Nombre en HuellaChile | C30: Unidad del dato de actividad | D30: CO2 (kg GEI/ unidad) | E30: CH4 (kg GEI/ unidad) | F30: N2O (kg GEI/ unidad) | G30: HFC (kg GEI/ unidad) | H30: PFC (kg GEI/ unidad) | I30: SF6 (kg GEI/ unidad) | J30: NF3 (kg GEI/ unidad) | K30: Unidad | L30: CO2 (kg CO2e/ unidad) | M30: CH4 (kg CO2e/ unidad) | N30: N2O (kg CO2e/ unidad) | O30: HFC (kg CO2e/ unidad) | P30: PFC (kg CO2e/ unidad) | Q30: SF6 (kg CO2e/ unidad) | R30: NF3 (kg CO2e/ unidad) | S30: Unidad | T30: CO2e (kg CO2e/ unidad) | U30: Unidad | V30: Fuente
B31: Producción de arrabio | C31: tonelada | D31: ='1.3 P.I. Hierro, Acero y Coque'!$N$9*1000 -> 1350 | E31: 0 | F31: 0 | G31: 0 | H31: 0 | I31: 0 | J31: 0 | K31: ="kg GEI/"&C31 -> kg GEI/tonelada | L31: =D31*$C$3 -> 1350 | M31: =E31*$C$4 -> 0 | N31: =F31*$C$5 -> 0 | O31: =G31*$C$3 -> 0 | P31: =H31*$C$3 -> 0 | Q31: =I31*$C$3 -> 0 | R31: =J31*$C$3 -> 0 | S31: ="kgCO2e/"&C31 -> kgCO2e/tonelada | T31: =SUM(L31:R31) -> 1350 | U31: =S31 -> kgCO2e/tonelada | V31: INGEI + IPCC 2006. Ver su hoja correspondiente para más detalles.
